Workbook

Sheet Overview
A1: Type | B1: Variable | C1: Grid | D1: Evidence | E1: Significance | F1: Inputs | G1: Assumptions | H1: Limitations
A2: Scalar | B2: Demand | C2: El | D2: H | E2: H | F2: D_2023(region, sector), D_2035(sector) | G2: D_ind grows due to electrification of existing D_ind D_ ind electrification and D_res,com growth is spatially uniform | H2: Projected growth reverses two-decade-long trends: ind % and total D decline, centralization. FinGrid also expects D_ind growth from new industries (data centers, E-fuels, battery production).
C3: DH | D3: H | E3: M | F3: D_2023(region), D_2035 | G3: Historic distribution
C4: IH | D4: M | E4: M | F4: D_ind_unelectrified(region), D_ih | G4: Proportional to unelectrified D_el
C5: H2 | D5: L | E5: M | F5: D_ind_unelectrified(region), D_h2 | G5: Proportional to unelectrified D_el, except for East | H5: Kirsikka list includes only projects for self-consumption, which is inconsistent with tyndp2024 scenario
B6: Generation | C6: El | D6: H | E6: H | F6: Power plant register, manual identification | G6: Historic distribution, Lovissa nuclear retirement | H6: Wind capacity increases 6-fold. Alternative basis - existing list of proposed wind power projects
C7: El_PV | D7: H | E7: M | F7: Development projects
C8: EL_DR | D8: M | E8: L | F8: - | G8: Omitted because of (1) small capacity and (2) old data in H2 heavy (predates even tyndp2020)
C9: H2 | D9: L | E9: M | F9: P_nonCHP(region), P_h2 | G9: Proportional to P_el_non-CHP, except for East | H9: No strong reason this to be the case
C10: DH | D10: H | E10: M | F10: Power plant register, manual identification | H10: Pauli data could be used dirrectly to identify spatial distribution
C11: IH | D11: H | E11: M | F11: Power plant register, manual identification | G11: All non-RE remains in Uusimaa while the rest is converted to RE
B12: Storage | C12: El_batteries | D12: L | E12: L | F12: P_nonCHP(region), P_h2 | G12: Proportional to P_el_non-CHP, except for East
C13: H2 | D13: L | E13: M | F13: D_ind_unelectrified(region), D_h2 | G13: Proportional to unelectrified D_el, except for East | H13: No strong reason this to be the case
C14: Heat | D14: H | E14: M | F14: Unit specific district heating data from Finnish Energy | G14: Municipality in company or unit name is muncipality where unit is located
B15: Transmission | C15: El | D15: H | E15: H | F15: FinGrid map of existing and future powerlines | G15: Visual mapping to model connections, kV to MW conversions | H15: Sufficiency needs to be tested. Regional model retains same set of cross-border connections, but we now know individual lines - could have multiple connections between individual pairs of nodes.
C16: H2 | D16: H | E16: H | F16: GasGrid map | G16: Extending cross-border capacities along path in GasGrid map | H16: Grid does not reach eastern region
A17: Vector | B17: Demand | C17: El | D17: H | E17: H | F17: D(region), D(customer type, t)
C18: H2, IH | D18: H | E18: M | F18: Constant
C19: DH | D19: M | E19: M | F19: Copy national
B20: Inflow | C20: Hydro | D20: M | E20: M | F20: Copy national
C21: Wind | D21: M | E21: H | F21: Copy national because Copernicus have only 2 regions for FI at highest granularity | H21: Major determinant of system dynamics
C22: Solar | D22: M | E22: H | F22: Copy national because Copernicus have only Nuts2 regions for FI at highest granularity or gridded data
B23: Limits | C23: Hydro | D23: M | E23: M | F23: Copy national
D25: High
D26: Medium
D27: Low

Sheet Geography
A1: Regions | H1: Municipalities | M1: Municipality by region explained
A2: Model | B2: Administrative | C2: Administrative (FI) | E2: Population | H2: Municipality | I2: Region 1990 | J2: Administrative | K2: Model | M2: Source | N2: Kunnat 1990 | Tilastokeskus | Q2: (Statistics Finland)
A3: North | B3: Lapland | C3: Lappi | E3: 176494 | F3: =SUM(E3:E4) -> 592097 | H3: Alahärmä | I3: Etelä-Pohjanmaa | J3: =IF(Municipality[[#This Row],[Region 1990]]=$M$13,$O$13,IF(Municipality[[#This Row],[Region 1990]]=$M$14,$O$14,Municipality[[#This Row],[Region 1990]])) -> Etelä-Pohjanmaa | K3: =_xlfn.XLOOKUP(Municipality[[#This Row],[Administrative]],Region[Administrative (FI)],Region[Model],"") -> West | M3: Aim | N3: Powerplant and other unit allocation to model regions based on their name or their company name
A4: North | B4: North Ostrobothnia | C4: Pohjois-Pohjanmaa | E4: 415603 | H4: Alajärvi | I4: Etelä-Pohjanmaa | J4: =IF(Municipality[[#This Row],[Region 1990]]=$M$13,$O$13,IF(Municipality[[#This Row],[Region 1990]]=$M$14,$O$14,Municipality[[#This Row],[Region 1990]])) -> Etelä-Pohjanmaa | K4: =_xlfn.XLOOKUP(Municipality[[#This Row],[Administrative]],Region[Administrative (FI)],Region[Model],"") -> West | M4: Selection | N4: The most fitting table is assumed to be in:
A5: West | B5: Central Ostrobothnia | C5: Keski-Pohjanmaa | E5: 67915 | F5: =SUM(E5:E8) -> 649999 | H5: Alastaro | I5: Varsinais-Suomi | J5: =IF(Municipality[[#This Row],[Region 1990]]=$M$13,$O$13,IF(Municipality[[#This Row],[Region 1990]]=$M$14,$O$14,Municipality[[#This Row],[Region 1990]])) -> Varsinais-Suomi | K5: =_xlfn.XLOOKUP(Municipality[[#This Row],[Administrative]],Region[Administrative (FI)],Region[Model],"") -> South West | N5: Year | O5: 1990 - earliest municipality by region table available
A6: West | B6: Ostrobothnia | C6: Pohjanmaa | E6: 176041 | H6: Alavieska | I6: Pohjois-Pohjanmaa | J6: =IF(Municipality[[#This Row],[Region 1990]]=$M$13,$O$13,IF(Municipality[[#This Row],[Region 1990]]=$M$14,$O$14,Municipality[[#This Row],[Region 1990]])) -> Pohjois-Pohjanmaa | K6: =_xlfn.XLOOKUP(Municipality[[#This Row],[Administrative]],Region[Administrative (FI)],Region[Model],"") -> North | O6: Municipality merges during 1990-2026 period has reduced municipality list by a thrid
A7: West | B7: South Ostrobothnia | C7: Etelä-Pohjanmaa | E7: 191762 | H7: Alavus | I7: Etelä-Pohjanmaa | J7: =IF(Municipality[[#This Row],[Region 1990]]=$M$13,$O$13,IF(Municipality[[#This Row],[Region 1990]]=$M$14,$O$14,Municipality[[#This Row],[Region 1990]])) -> Etelä-Pohjanmaa | K7: =_xlfn.XLOOKUP(Municipality[[#This Row],[Administrative]],Region[Administrative (FI)],Region[Model],"") -> West | N7: Language | O7: Finnish - instead of English or Swedish
A8: West | B8: Satakunta | C8: Satakunta | E8: 214281 | H8: Anjalankoski | I8: Kymenlaakso | J8: =IF(Municipality[[#This Row],[Region 1990]]=$M$13,$O$13,IF(Municipality[[#This Row],[Region 1990]]=$M$14,$O$14,Municipality[[#This Row],[Region 1990]])) -> Kymenlaakso | K8: =_xlfn.XLOOKUP(Municipality[[#This Row],[Administrative]],Region[Administrative (FI)],Region[Model],"") -> South East | M8: Regional changes
A9: Center | B9: Pirkanmaa | C9: Pirkanmaa | E9: 527478 | F9: =SUM(E9:E10) -> 800161 | H9: Anttola | I9: Etelä-Savo | J9: =IF(Municipality[[#This Row],[Region 1990]]=$M$13,$O$13,IF(Municipality[[#This Row],[Region 1990]]=$M$14,$O$14,Municipality[[#This Row],[Region 1990]])) -> Etelä-Savo | K9: =_xlfn.XLOOKUP(Municipality[[#This Row],[Administrative]],Region[Administrative (FI)],Region[Model],"") -> East | N9: Boundaries | O9: Known to be minor only - here ignored
A10: Center | B10: Central Finland | C10: Keski-Suomi | E10: 272683 | H10: Artjärvi | I10: Uusimaa | J10: =IF(Municipality[[#This Row],[Region 1990]]=$M$13,$O$13,IF(Municipality[[#This Row],[Region 1990]]=$M$14,$O$14,Municipality[[#This Row],[Region 1990]])) -> Uusimaa | K10: =_xlfn.XLOOKUP(Municipality[[#This Row],[Administrative]],Region[Administrative (FI)],Region[Model],"") -> Uusimaa | N10: Names | O10: Two names shown bellow are replaced
A11: East | B11: Kainuu | C11: Kainuu | E11: 71255 | F11: =SUM(E11:E14) -> 614587 | H11: Asikkala | I11: Päijät-Häme | J11: =IF(Municipality[[#This Row],[Region 1990]]=$M$13,$O$13,IF(Municipality[[#This Row],[Region 1990]]=$M$14,$O$14,Municipality[[#This Row],[Region 1990]])) -> Päijät-Häme | K11: =_xlfn.XLOOKUP(Municipality[[#This Row],[Administrative]],Region[Administrative (FI)],Region[Model],"") -> South East
A12: East | B12: North Savo | C12: Pohjois-Savo | E12: 248363 | H12: Askola | I12: Uusimaa | J12: =IF(Municipality[[#This Row],[Region 1990]]=$M$13,$O$13,IF(Municipality[[#This Row],[Region 1990]]=$M$14,$O$14,Municipality[[#This Row],[Region 1990]])) -> Uusimaa | K12: =_xlfn.XLOOKUP(Municipality[[#This Row],[Administrative]],Region[Administrative (FI)],Region[Model],"") -> Uusimaa | M12: 1990 name | O12: 2026 name
A13: East | B13: South Savo | C13: Etelä-Savo | E13: 131688 | H13: Aura | I13: Varsinais-Suomi | J13: =IF(Municipality[[#This Row],[Region 1990]]=$M$13,$O$13,IF(Municipality[[#This Row],[Region 1990]]=$M$14,$O$14,Municipality[[#This Row],[Region 1990]])) -> Varsinais-Suomi | K13: =_xlfn.XLOOKUP(Municipality[[#This Row],[Administrative]],Region[Administrative (FI)],Region[Model],"") -> South West | M13: Häme | O13: Kanta-Häme
A14: East | B14: North Karelia | C14: Pohjois-Karjala | E14: 163281 | H14: Pirkkala | I14: Pirkanmaa | J14: =IF(Municipality[[#This Row],[Region 1990]]=$M$13,$O$13,IF(Municipality[[#This Row],[Region 1990]]=$M$14,$O$14,Municipality[[#This Row],[Region 1990]])) -> Pirkanmaa | K14: =_xlfn.XLOOKUP(Municipality[[#This Row],[Administrative]],Region[Administrative (FI)],Region[Model],"") -> Center | M14: Vaasan rannikkoseutu | O14: Pohjanmaa
A15: South West | B15: Åland | C15: Ahvenanmaa | E15: 30344 | F15: =SUM(E15:E17) -> 684034 | H15: Perniö | I15: Varsinais-Suomi | J15: =IF(Municipality[[#This Row],[Region 1990]]=$M$13,$O$13,IF(Municipality[[#This Row],[Region 1990]]=$M$14,$O$14,Municipality[[#This Row],[Region 1990]])) -> Varsinais-Suomi | K15: =_xlfn.XLOOKUP(Municipality[[#This Row],[Administrative]],Region[Administrative (FI)],Region[Model],"") -> South West
A16: South West | B16: Southwest Finland | C16: Varsinais-Suomi | E16: 483477 | H16: Pori | I16: Satakunta | J16: =IF(Municipality[[#This Row],[Region 1990]]=$M$13,$O$13,IF(Municipality[[#This Row],[Region 1990]]=$M$14,$O$14,Municipality[[#This Row],[Region 1990]])) -> Satakunta | K16: =_xlfn.XLOOKUP(Municipality[[#This Row],[Administrative]],Region[Administrative (FI)],Region[Model],"") -> West | M16: FIN0 | N16: FIW0 | O16: FIC0 | P16: FIE0 | Q16: FISW | R16: FISE | S16: FIUU
A17: South West | B17: Kanta-Häme | C17: Kanta-Häme | E17: 170213 | H17: Pornainen | I17: Uusimaa | J17: =IF(Municipality[[#This Row],[Region 1990]]=$M$13,$O$13,IF(Municipality[[#This Row],[Region 1990]]=$M$14,$O$14,Municipality[[#This Row],[Region 1990]])) -> Uusimaa | K17: =_xlfn.XLOOKUP(Municipality[[#This Row],[Administrative]],Region[Administrative (FI)],Region[Model],"") -> Uusimaa
A18: South East | B18: Päijät-Häme | C18: Päijät-Häme | E18: 205124 | F18: =SUM(E18:E20) -> 492622 | H18: Porvoo | I18: Uusimaa | J18: =IF(Municipality[[#This Row],[Region 1990]]=$M$13,$O$13,IF(Municipality[[#This Row],[Region 1990]]=$M$14,$O$14,Municipality[[#This Row],[Region 1990]])) -> Uusimaa | K18: =_xlfn.XLOOKUP(Municipality[[#This Row],[Administrative]],Region[Administrative (FI)],Region[Model],"") -> Uusimaa
A19: South East | B19: Kymenlaakso | C19: Kymenlaakso | E19: 161391 | H19: Porvoon | I19: Uusimaa | J19: =IF(Municipality[[#This Row],[Region 1990]]=$M$13,$O$13,IF(Municipality[[#This Row],[Region 1990]]=$M$14,$O$14,Municipality[[#This Row],[Region 1990]])) -> Uusimaa | K19: =_xlfn.XLOOKUP(Municipality[[#This Row],[Administrative]],Region[Administrative (FI)],Region[Model],"") -> Uusimaa
A20: South East | B20: South Karelia | C20: Etelä-Karjala | E20: 126107 | H20: Raahe | I20: Pohjois-Pohjanmaa | J20: =IF(Municipality[[#This Row],[Region 1990]]=$M$13,$O$13,IF(Municipality[[#This Row],[Region 1990]]=$M$14,$O$14,Municipality[[#This Row],[Region 1990]])) -> Pohjois-Pohjanmaa | K20: =_xlfn.XLOOKUP(Municipality[[#This Row],[Administrative]],Region[Administrative (FI)],Region[Model],"") -> North
A21: Uusimaa | B21: Uusimaa | C21: Uusimaa | E21: 1714741 | F21: =E21 -> 1714741 | H21: Brändö | I21: Ahvenanmaa | J21: =IF(Municipality[[#This Row],[Region 1990]]=$M$13,$O$13,IF(Municipality[[#This Row],[Region 1990]]=$M$14,$O$14,Municipality[[#This Row],[Region 1990]])) -> Ahvenanmaa | K21: =_xlfn.XLOOKUP(Municipality[[#This Row],[Administrative]],Region[Administrative (FI)],Region[Model],"") -> South West
H22: Karijoki | I22: Etelä-Pohjanmaa | J22: =IF(Municipality[[#This Row],[Region 1990]]=$M$13,$O$13,IF(Municipality[[#This Row],[Region 1990]]=$M$14,$O$14,Municipality[[#This Row],[Region 1990]])) -> Etelä-Pohjanmaa | K22: =_xlfn.XLOOKUP(Municipality[[#This Row],[Administrative]],Region[Administrative (FI)],Region[Model],"") -> West
H23: Dragsfjärd | I23: Varsinais-Suomi | J23: =IF(Municipality[[#This Row],[Region 1990]]=$M$13,$O$13,IF(Municipality[[#This Row],[Region 1990]]=$M$14,$O$14,Municipality[[#This Row],[Region 1990]])) -> Varsinais-Suomi | K23: =_xlfn.XLOOKUP(Municipality[[#This Row],[Administrative]],Region[Administrative (FI)],Region[Model],"") -> South West
H24: Eckerö | I24: Ahvenanmaa | J24: =IF(Municipality[[#This Row],[Region 1990]]=$M$13,$O$13,IF(Municipality[[#This Row],[Region 1990]]=$M$14,$O$14,Municipality[[#This Row],[Region 1990]])) -> Ahvenanmaa | K24: =_xlfn.XLOOKUP(Municipality[[#This Row],[Administrative]],Region[Administrative (FI)],Region[Model],"") -> South West
H25: Tammisaari | I25: Uusimaa | J25: =IF(Municipality[[#This Row],[Region 1990]]=$M$13,$O$13,IF(Municipality[[#This Row],[Region 1990]]=$M$14,$O$14,Municipality[[#This Row],[Region 1990]])) -> Uusimaa | K25: =_xlfn.XLOOKUP(Municipality[[#This Row],[Administrative]],Region[Administrative (FI)],Region[Model],"") -> Uusimaa
H26: Elimäki | I26: Kymenlaakso | J26: =IF(Municipality[[#This Row],[Region 1990]]=$M$13,$O$13,IF(Municipality[[#This Row],[Region 1990]]=$M$14,$O$14,Municipality[[#This Row],[Region 1990]])) -> Kymenlaakso | K26: =_xlfn.XLOOKUP(Municipality[[#This Row],[Administrative]],Region[Administrative (FI)],Region[Model],"") -> South East
H27: Inari | I27: Lappi | J27: =IF(Municipality[[#This Row],[Region 1990]]=$M$13,$O$13,IF(Municipality[[#This Row],[Region 1990]]=$M$14,$O$14,Municipality[[#This Row],[Region 1990]])) -> Lappi | K27: =_xlfn.XLOOKUP(Municipality[[#This Row],[Administrative]],Region[Administrative (FI)],Region[Model],"") -> North
H28: Eno | I28: Pohjois-Karjala | J28: =IF(Municipality[[#This Row],[Region 1990]]=$M$13,$O$13,IF(Municipality[[#This Row],[Region 1990]]=$M$14,$O$14,Municipality[[#This Row],[Region 1990]])) -> Pohjois-Karjala | K28: =_xlfn.XLOOKUP(Municipality[[#This Row],[Administrative]],Region[Administrative (FI)],Region[Model],"") -> East
H29: Enonkoski | I29: Etelä-Savo | J29: =IF(Municipality[[#This Row],[Region 1990]]=$M$13,$O$13,IF(Municipality[[#This Row],[Region 1990]]=$M$14,$O$14,Municipality[[#This Row],[Region 1990]])) -> Etelä-Savo | K29: =_xlfn.XLOOKUP(Municipality[[#This Row],[Administrative]],Region[Administrative (FI)],Region[Model],"") -> East
H30: Enontekiö | I30: Lappi | J30: =IF(Municipality[[#This Row],[Region 1990]]=$M$13,$O$13,IF(Municipality[[#This Row],[Region 1990]]=$M$14,$O$14,Municipality[[#This Row],[Region 1990]])) -> Lappi | K30: =_xlfn.XLOOKUP(Municipality[[#This Row],[Administrative]],Region[Administrative (FI)],Region[Model],"") -> North
H31: Espoo | I31: Uusimaa | J31: =IF(Municipality[[#This Row],[Region 1990]]=$M$13,$O$13,IF(Municipality[[#This Row],[Region 1990]]=$M$14,$O$14,Municipality[[#This Row],[Region 1990]])) -> Uusimaa | K31: =_xlfn.XLOOKUP(Municipality[[#This Row],[Administrative]],Region[Administrative (FI)],Region[Model],"") -> Uusimaa
H32: Ähtäri | I32: Etelä-Pohjanmaa | J32: =IF(Municipality[[#This Row],[Region 1990]]=$M$13,$O$13,IF(Municipality[[#This Row],[Region 1990]]=$M$14,$O$14,Municipality[[#This Row],[Region 1990]])) -> Etelä-Pohjanmaa | K32: =_xlfn.XLOOKUP(Municipality[[#This Row],[Administrative]],Region[Administrative (FI)],Region[Model],"") -> West
H33: Eura | I33: Satakunta | J33: =IF(Municipality[[#This Row],[Region 1990]]=$M$13,$O$13,IF(Municipality[[#This Row],[Region 1990]]=$M$14,$O$14,Municipality[[#This Row],[Region 1990]])) -> Satakunta | K33: =_xlfn.XLOOKUP(Municipality[[#This Row],[Administrative]],Region[Administrative (FI)],Region[Model],"") -> West
... H462: Ylitornio | I462: Lappi | J462: =IF(Municipality[[#This Row],[Region 1990]]=$M$13,$O$13,IF(Municipality[[#This Row],[Region 1990]]=$M$14,$O$14,Municipality[[#This Row],[Region 1990]])) -> Lappi | K462: =_xlfn.XLOOKUP(Municipality[[#This Row],[Administrative]],Region[Administrative (FI)],Region[Model],"") -> North

Sheet D_el
A1: 1. Data
A2: Source [1] | B2: Sahkonkulutus-maakunnittain-2007-2023.xlsx | G2: (Finnish Energy) | L2: Source [2] | M2: Demand Scenarios TYNDP 2024 After Public Consultation.xslx | U2: Statistics Finland (2023) | AA2: Industry | AB2: Commerce | AC2: Residence | AF2: Industry | AG2: Commerce | AH2: Residence
A3: Terminology simplifications: residence - housing and agriculture, commerce - service and buildings | L3: Notations: REF - reference of 2019, DE - Distributed Energy 2035 scenario | T3: Source [4] | U3: Energy use in manufacturing by Year, Region and Information. PxWeb | Z3: 2007 | AA3: =C26 -> 47677 | AB3: =D26 -> 17263 | AC3: =E26 -> 22391 | AE3: Uusimaa | AF3: 4073 | AG3: 6791 | AH3: 5840 | AI3: =W6-V6 -> 16161
A4: [GWh] | C4: 2007 | G4: 2023 | L4: [GWh] | M4: REF | N4: DE | T4: Source [5] | U4: Total electricity consumption by Year, Region, Manufacturing branch and Information. PxWeb | Z4: 2023 | AA4: =G26 -> 34100 | AB4: =H26 -> 19428 | AC4: =I26 -> 23575 | AE4: Southwest Finland | AF4: 1041 | AG4: 1661 | AH4: 2146 | AI4: =W7-V7 -> 1887
C5: Industry | D5: Commerce | E5: Residence | F5: Total | G5: Industry | H5: Commerce | I5: Residence | J5: Total | L5: Households | M5: 24142.483 | N5: 29821.687 | O5: =N5/$N$13 -> 0.22609788 | V5: Electricity | W5: Energy | X5: Electfication | Z5: 2035* | AA5: =N7 -> 85806.024 | AB5: =N6 -> 16269.531 | AC5: =N5 -> 29821.687 | AE5: Satakunta | AF5: 3334 | AG5: 707 | AH5: 1040 | AI5: =W8-V8 -> 6114
A6: Uusimaa | C6: 2912 | D6: 5497 | E6: 4658 | F6: 13066 | G6: 4073 | H6: 6791 | I6: 5840 | J6: 16704 | L6: Buildings | M6: 18496.723 | N6: 16269.531 | O6: =N6/$N$13 -> 0.12335005 | T6: Uusimaa | V6: 4650 | W6: 20811 | X6: =V6/W6 -> 0.22343953 | AA6: =AA5/AA4 -> 2.5163057 | AE6: Kanta-Häme | AF6: 753 | AG6: 578 | AH6: 800 | AI6: =W9-V9 -> 1033
A7: Varsinais-Suomi | C7: 1477 | D7: 1356 | E7: 2018 | F7: 4852 | G7: 1041 | H7: 1661 | I7: 2146 | J7: 4847 | L7: Industry | M7: 41166.333 | N7: 85806.024 | O7: =N7/$N$13 -> 0.65055207 | T7: Varsinais-Suomi | V7: 955 | W7: 2842 | X7: =V7/W7 -> 0.33603096 | AE7: Pirkanmaa | AF7: 1972 | AG7: 1643 | AH7: 2188 | AI7: =W10-V10 -> 2663
A8: Satakunta | C8: 4946 | D8: 574 | E8: 995 | F8: 6514 | G8: 3334 | H8: 707 | I8: 1040 | J8: 5080 | L8: Transport | M8: 859 | N8: 9937.3888 | T8: Satakunta | V8: 3123 | W8: 9237 | X8: =V8/W8 -> 0.33809678 | AE8: Päijät-Häme | AF8: 741 | AG8: 566 | AH8: 848 | AI8: =W11-V11 -> 1551
A9: Kanta-Häme | C9: 803 | D9: 566 | E9: 766 | F9: 2136 | G9: 753 | H9: 578 | I9: 800 | J9: 2130 | L9: Agriculture | M9: 1475 | N9: 1980.3154 | T9: Kanta-Häme | V9: 668 | W9: 1701 | X9: =V9/W9 -> 0.39271017 | AE9: Kymenlaakso | AF9: 2023 | AG9: 945 | AH9: 713 | AI9: =W12-V12 -> 7929
A10: Pirkanmaa | C10: 3170 | D10: 1336 | E10: 1854 | F10: 6360 | G10: 1972 | H10: 1643 | I10: 2188 | J10: 5804 | L10: Other | M10: 0 | N10: 0 | T10: Pirkanmaa | V10: 2012 | W10: 4675 | X10: =V10/W10 -> 0.43037433 | AE10: South Karelia | AF10: 3933 | AG10: 417 | AH10: 492 | AI10: =W13-V13 -> 14579
A11: Päijät-Häme | C11: 873 | D11: 607 | E11: 851 | F11: 2331 | G11: 741 | H11: 566 | I11: 848 | J11: 2154 | L11: Energy | M11: 2597 | N11: 2597 | T11: Päijät-Häme | V11: 706 | W11: 2257 | X11: =V11/W11 -> 0.31280461 | AE11: South Savo | AF11: 332 | AG11: 429 | AH11: 654 | AI11: =W14-V14 -> 869
A12: Kymenlaakso | C12: 5234 | D12: 671 | E12: 790 | F12: 6694 | G12: 2023 | H12: 945 | I12: 713 | J12: 3681 | L12: Total | M12: =SUM(M5:M11) -> 88736.54 | N12: =SUM(N5:N11) -> 146411.95 | T12: Kymenlaakso | V12: 2214 | W12: 10143 | X12: =V12/W12 -> 0.21827862 | AE12: North Savo | AF12: 1569 | AG12: 765 | AH12: 1015 | AI12: =W15-V15 -> 3102
A13: Etelä-Karjala | C13: 4967 | D13: 435 | E13: 551 | F13: 5953 | G13: 3933 | H13: 417 | I13: 492 | J13: 4842 | L13: Total main | M13: =SUM(M5:M7) -> 83805.54 | N13: =SUM(N5:N7) -> 131897.24 | T13: South Karelia | V13: 3580 | W13: 18159 | X13: =V13/W13 -> 0.19714742 | AE13: North Karelia | AF13: 1254 | AG13: 433 | AH13: 701 | AI13: =W16-V16 -> 3665
A14: Etelä-Savo | C14: 411 | D14: 468 | E14: 769 | F14: 1649 | G14: 332 | H14: 429 | I14: 654 | J14: 1415 | T14: Etelä-Savo | V14: 341 | W14: 1210 | X14: =V14/W14 -> 0.28181818 | AE14: Central Finland | AF14: 2365 | AG14: 791 | AH14: 1209 | AI14: =W17-V17 -> 9119
A15: Pohjois-Savo | C15: 2194 | D15: 709 | E15: 1078 | F15: 3981 | G15: 1569 | H15: 765 | I15: 1015 | J15: 3349 | L15: Source [3] TYNDP 2024 Visualization platfrom (DE 2035 scenario) | T15: Pohjois-Savo | V15: 1357 | W15: 4459 | X15: =V15/W15 -> 0.30432832 | AE15: South Ostrobothnia | AF15: 545 | AG15: 622 | AH15: 925 | AI15: =W18-V18 -> 751
A16: Pohjois-Karjala | C16: 1053 | D16: 464 | E16: 734 | F16: 2251 | G16: 1254 | H16: 433 | I16: 701 | J16: 2388 | L16: Native | M16: 132860 | T16: North Karelia | V16: 788 | W16: 4453 | X16: =V16/W16 -> 0.17695935 | AE16: Ostrobothnia | AF16: 1125 | AG16: 619 | AH16: 1250 | AI16: =W19-V19 -> 5358
A17: Keski-Suomi | C17: 4749 | D17: 778 | E17: 1252 | F17: 6779 | G17: 2365 | H17: 791 | I17: 1209 | J17: 4365 | L17: Electrolyser | M17: 72580 | T17: Central Finland | V17: 2226 | W17: 11345 | X17: =V17/W17 -> 0.19620978 | AE17: Central Ostrobothnia | AF17: 1525 | AG17: 176 | AH17: 341 | AI17: =W20-V20 -> 852
A18: Etelä-Pohjanmaa | C18: 538 | D18: 542 | E18: 878 | F18: 1957 | G18: 545 | H18: 622 | I18: 925 | J18: 2092 | L18: EV | M18: 4920 | T18: South Ostrobothnia | V18: 625 | W18: 1376 | X18: =V18/W18 -> 0.45421512 | AE18: North Ostrobothnia | AF18: 2419 | AG18: 1254 | AH18: 1784 | AI18: =W21-V21 -> 10151
A19: Pohjanmaa | C19: 2043 | D19: 462 | E19: 968 | F19: 3474 | G19: 1125 | H19: 619 | I19: 1250 | J19: 2994 | L19: Battery | M19: 1050 | T19: Ostrobothnia | V19: 1477 | W19: 6835 | X19: =V19/W19 -> 0.21609364 | AE19: Kainuu | AF19: 713 | AG19: 249 | AH19: 310 | AI19: =W22-V22 -> 323
A20: Keski-Pohjanmaa | C20: 1507 | D20: 214 | E20: 335 | F20: 2057 | G20: 1525 | H20: 176 | I20: 341 | J20: 2042 | L20: Total | M20: =SUM(M16:M19) -> 211410 | T20: Central Ostrobothnia | V20: 1497 | W20: 2349 | X20: =V20/W20 -> 0.63729246 | AE20: Lapland | AF20: 4357 | AG20: 677 | AH20: 1190 | AI20: =W23-V23 -> 6899
A21: Pohjois-Pohjanmaa | C21: 3129 | D21: 1231 | E21: 1774 | F21: 6135 | G21: 2419 | H21: 1254 | I21: 1784 | J21: 5456 | T21: North Ostrobothnia | V21: 1852 | W21: 12003 | X21: =V21/W21 -> 0.15429476 | AE21: Åland | AF21: 26 | AG21: 106 | AH21: 132 | AI21: =W24-V24 -> 41
A22: Kainuu | C22: 1772 | D22: 291 | E22: 371 | F22: 2433 | G22: 713 | H22: 249 | I22: 310 | J22: 1272 | T22: Kainuu | V22: 694 | W22: 1017 | X22: =V22/W22 -> 0.68239921
A23: Lappi | C23: 4035 | D23: 726 | E23: 1121 | F23: 5882 | G23: 4357 | H23: 677 | I23: 1190 | J23: 6223 | T23: Lapland | V23: 4163 | W23: 11062 | X23: =V23/W23 -> 0.37633339
A24: Itä-Uusimaa | C24: 1831 | D24: 237 | E24: 508 | F24: 2576 | T24: Åland | V24: 31 | W24: 72 | X24: =V24/W24 -> 0.43055556
A25: Ahvenanmaa | C25: 30 | D25: 99 | E25: 120 | F25: 249 | G25: 26 | H25: 106 | I25: 132 | J25: 264 | T25: Total | V25: 32959 | W25: 126006 | X25: =V25/W25 -> 0.26156691
A26: Total | C26: 47677 | D26: 17263 | E26: 22391 | F26: 87330 | G26: 34100 | H26: 19428 | I26: 23575 | J26: 77103 | K26: =N7/G26 -> 2.5163057
C27: =C26/$F$26 -> 0.54594068 | D27: =D26/$F$26 -> 0.19767548 | E27: =E26/$F$26 -> 0.25639528 | G27: =G26/$J$26 -> 0.44226554 | H27: =H26/$J$26 -> 0.25197463 | I27: =I26/$J$26 -> 0.30575983
A29: 2. Assessment of trends
A31: Assessment of national trends | J31: Trends were initially observed by tinkering with regional values (present bellow in hidden rows), but are much more clearly visible when comparing national values.
A32: Trend observed | C32: Coresponding demand | E32: Absolute | G32: Relative
E33: Historic | F33: Projected | G33: Historic | H33: Projected
A34: Total growth | C34: Total | E34: =J26-F26 -> -10227 | F34: =N13-M13 -> 48091.703 | G34: =E34/F26 -> -0.11710752 | H34: =F34/M13 -> 0.57384873
A35: Deindustriliaziation | C35: Industrial | E35: =G26-C26 -> -13577 | F35: =N7-M7 -> 44639.691 | G35: =(G26/J26)-(C26/F26) -> -0.10367514 | H35: =(N7/N13)-(M7/M13) -> 0.15933952
A36: Centralization | C36: Uusimaa | E36: =F6+F24-J6 -> -1062 | F36: =G84-J6 -> 9857.4787 | G36: =(J6/J26)-((F6+F24)/F26) -> 0.03753156 | H36: =(G84/G103)-(J6/J26) -> -0.015232547 | J36: Projected change for Uusimaa demand are based on regional breakdown assumed in part 3
A38: Assessment of historic regional trends | N38: Order: in tables - 2023 values on top of 2007 ones, bar charts - 2007 (in brighter colors) on top of 2023
A39: Administrative regions | F39: Model regions
C40: Industry | D40: Comerce | E40: Residence | F40: Aggregated region | H40: Region | J40: Industry | K40: Commerce | L40: Residence
A41: Uusimaa | C41: 4073 | D41: 6791 | E41: 5840 | F41: North | H41: Lappi | J41: 4357 | K41: 677 | L41: 1190
C42: 4743 | D42: 5734 | E42: 5166 | J42: 4035 | K42: 726 | L42: 1121
A43: Lappi | C43: 4357 | D43: 677 | E43: 1190 | H43: Pohjois-Pohjanmaa | J43: 2419 | K43: 1254 | L43: 1784
C44: 4035 | D44: 726 | E44: 1121 | J44: 3129 | K44: 1231 | L44: 1774
A45: Pirkanmaa | C45: 1972 | D45: 1643 | E45: 2188 | F45: West | H45: Keski-Pohjanmaa | J45: 1525 | K45: 176 | L45: 341
C46: 3170 | D46: 1336 | E46: 1854 | J46: 1507 | K46: 214 | L46: 335
A47: Pohjois-Pohjanmaa | C47: 2419 | D47: 1254 | E47: 1784 | H47: Pohjanmaa | J47: 1125 | K47: 619 | L47: 1250
C48: 3129 | D48: 1231 | E48: 1774 | J48: 2043 | K48: 462 | L48: 968
A49: Satakunta | C49: 3334 | D49: 707 | E49: 1040 | H49: Etlä-Pohjanmaa | J49: 545 | K49: 622 | L49: 925
C50: 4946 | D50: 574 | E50: 995 | J50: 538 | K50: 542 | L50: 878
A51: Varsinais-Suomi | C51: 1041 | D51: 1661 | E51: 2146 | H51: Satakunta | J51: 3334 | K51: 707 | L51: 1040
C52: 1477 | D52: 1356 | E52: 2018 | J52: 4946 | K52: 574 | L52: 995
A53: Etelä-Karjala | C53: 3933 | D53: 417 | E53: 492 | F53: Center | H53: Pirkanmaa | J53: 1972 | K53: 1643 | L53: 2188
C54: 4967 | D54: 435 | E54: 551 | J54: 3170 | K54: 1336 | L54: 1854
A55: Keski-Suomi | C55: 2365 | D55: 791 | E55: 1209 | H55: Keski-Suomi | J55: 2365 | K55: 791 | L55: 1209
C56: 4749 | D56: 778 | E56: 1252 | J56: 4749 | K56: 778 | L56: 1252
A57: Kymenlaakso | C57: 2023 | D57: 945 | E57: 713 | F57: East | H57: Kainuu | J57: 713 | K57: 249 | L57: 310
C58: 5234 | D58: 671 | E58: 790 | J58: 1772 | K58: 291 | L58: 371
A59: Pohjois-Savo | C59: 1569 | D59: 765 | E59: 1015 | H59: Pohjois-Savo | J59: 1569 | K59: 765 | L59: 1015
C60: 2194 | D60: 709 | E60: 1078 | J60: 2194 | K60: 709 | L60: 1078
A61: Pohjanmaa | C61: 1125 | D61: 619 | E61: 1250 | H61: Etelä-Savo | J61: 332 | K61: 429 | L61: 654
C62: 2043 | D62: 462 | E62: 968 | J62: 411 | K62: 468 | L62: 769
A63: Pohjois-Karjala | C63: 1254 | D63: 433 | E63: 701 | H63: Pohjois-Karjala | J63: 1254 | K63: 433 | L63: 701
C64: 1053 | D64: 464 | E64: 734 | J64: 1053 | K64: 464 | L64: 734 | P64: Industry | Q64: Commerce | R64: Ressidence
A65: Päijät-Häme | C65: 741 | D65: 566 | E65: 848 | F65: South West | H65: Ahvenanmaa | J65: 26 | K65: 106 | L65: 132 | P65: =J77 -> 4073 | Q65: =K77 -> 6791 | R65: =L77 -> 5840
C66: 873 | D66: 607 | E66: 851 | J66: 30 | K66: 99 | L66: 120 | N66: Uusimaa | P66: =J78 -> 4743 | Q66: =K78 -> 5734 | R66: =L78 -> 5166
A67: Kanta-Häme | C67: 753 | D67: 578 | E67: 800 | H67: Varsinais-Suomi | J67: 1041 | K67: 1661 | L67: 2146 | P67: =J71+J73+J75 -> 6697 | Q67: =K71+K73+K75 -> 1928 | R67: =L71+L73+L75 -> 2053
C68: 803 | D68: 566 | E68: 766 | J68: 1477 | K68: 1356 | L68: 2018 | N68: South East | P68: =J72+J74+J76 -> 11074 | Q68: =K72+K74+K76 -> 1713 | R68: =L72+L74+L76 -> 2192
A69: Etelä-Pohjanmaa | C69: 545 | D69: 622 | E69: 925 | H69: Kanta-Häme | J69: 753 | K69: 578 | L69: 800 | P69: =J65+J67+J69 -> 1820 | Q69: =K65+K67+K69 -> 2345 | R69: =L65+L67+L69 -> 3078
C70: 538 | D70: 542 | E70: 878 | J70: 803 | K70: 566 | L70: 766 | N70: South West | P70: =J66+J68+J70 -> 2310 | Q70: =K66+K68+K70 -> 2021 | R70: =L66+L68+L70 -> 2904
A71: Keski-Pohjanmaa | C71: 1525 | D71: 176 | E71: 341 | F71: South East | H71: Päijät-Häme | J71: 741 | K71: 566 | L71: 848 | P71: =J57+J59+J61+J63 -> 3868 | Q71: =K57+K59+K61+K63 -> 1876 | R71: =L57+L59+L61+L63 -> 2680
C72: 1507 | D72: 214 | E72: 335 | J72: 873 | K72: 607 | L72: 851 | N72: East | P72: =J58+J60+J62+J64 -> 5430 | Q72: =K58+K60+K62+K64 -> 1932 | R72: =L58+L60+L62+L64 -> 2952
A73: Etelä-Savo | C73: 332 | D73: 429 | E73: 654 | H73: Kymenlaakso | J73: 2023 | K73: 945 | L73: 713 | P73: =J53+J55 -> 4337 | Q73: =K53+K55 -> 2434 | R73: =L53+L55 -> 3397
C74: 411 | D74: 468 | E74: 769 | J74: 5234 | K74: 671 | L74: 790 | N74: Center | P74: =J54+J56 -> 7919 | Q74: =K54+K56 -> 2114 | R74: =L54+L56 -> 3106
A75: Kainuu | C75: 713 | D75: 249 | E75: 310 | H75: Etelä-Karjala | J75: 3933 | K75: 417 | L75: 492 | P75: =J45+J47+J49+J51 -> 6529 | Q75: =K45+K47+K49+K51 -> 2124 | R75: =L45+L47+L49+L51 -> 3556
C76: 1772 | D76: 291 | E76: 371 | J76: 4967 | K76: 435 | L76: 551 | N76: West | P76: =J46+J48+J50+J52 -> 9034 | Q76: =K46+K48+K50+K52 -> 1792 | R76: =L46+L48+L50+L52 -> 3176
A77: Ahvenanmaa | C77: 26 | D77: 106 | E77: 132 | F77: Uusimaa | H77: Uusimaa | J77: 4073 | K77: 6791 | L77: 5840 | P77: =J41+J43 -> 6776 | Q77: =K41+K43 -> 1931 | R77: =L41+L43 -> 2974
C78: 30 | D78: 99 | E78: 120 | J78: 4743 | K78: 5734 | L78: 5166 | N78: North | P78: =J42+J44 -> 7164 | Q78: =K42+K44 -> 1957 | R78: =L42+L44 -> 2895
A80: 3. Attempt #2. Combining sources 1+2+4.
A81: Assumptions | C81: (1) Industrial electricity demand grows due to electrification of existing industrial energy demand. (2) Electrification share of currently unelectrified demand is equal across all regions.
C82: (3) Residencial and commertial demand change by same multiplier for annual value to match tyndp2024 projection.
A83: 2035 [GWh] | C83: Unelectrified industry | D83: Industry | E83: Commerce | F83: Residence | G83: Total | H83: Electrification share
A84: Uusimaa | C84: =W6-G6 -> 16738 | D84: =G6+$M$84*C84 -> 13487.083 | E84: =H6*$N$6/$H$26 -> 5686.9666 | F84: =I6*$N$5/$I$26 -> 7387.4295 | G84: =SUM(D84:F84) -> 26561.479 | H84: =D84/W6 -> 0.6480747 | J84: Electification share increase | M84: =(N7-G26)/C103 -> 0.56243772
A85: Varsinais-Suomi | C85: =W7-G7 -> 1801 | D85: =G7+$M$84*C85 -> 2053.9503 | E85: =H7*$N$6/$H$26 -> 1390.9662 | F85: =I7*$N$5/$I$26 -> 2714.6274 | G85: =SUM(D85:F85) -> 6159.5439 | H85: =D85/W7 -> 0.722713
A86: Satakunta | C86: =W8-G8 -> 5903 | D86: =G8+$M$84*C86 -> 6654.0699 | E86: =H8*$N$6/$H$26 -> 592.06088 | F86: =I8*$N$5/$I$26 -> 1315.5696 | G86: =SUM(D86:F86) -> 8561.7004 | H86: =D86/W8 -> 0.72037132
A87: Kanta-Häme | C87: =W9-G9 -> 948 | D87: =G9+$M$84*C87 -> 1286.191 | E87: =H9*$N$6/$H$26 -> 484.0328 | F87: =I9*$N$5/$I$26 -> 1011.9766 | G87: =SUM(D87:F87) -> 2782.2004 | H87: =D87/W9 -> 0.75613813 | K87: Unelectrified industry | L87: Industry | M87: Commerce | N87: Residence | O87: Total el. [GWh] | Q87: Avg hourly [MW]
A88: Pirkanmaa | C88: =W10-G10 -> 2703 | D88: =G10+$M$84*C88 -> 3492.2692 | E88: =H10*$N$6/$H$26 -> 1375.8925 | F88: =I10*$N$5/$I$26 -> 2767.7561 | G88: =SUM(D88:F88) -> 7635.9178 | H88: =D88/W10 -> 0.74700945 | J88: North | K88: =(C101+C99)*(1-M84) -> 7127.452 | L88: =D101+D99 -> 15937.548 | M88: =E101+E99 -> 1617.0715 | N88: =F101+F99 -> 3762.0232 | O88: =SUM(L88:N88) -> 21316.643 | Q88: =O88/8.76 -> 2433.4067
A89: Päijät-Häme | C89: =W11-G11 -> 1516 | D89: =G11+$M$84*C89 -> 1593.6556 | E89: =H11*$N$6/$H$26 -> 473.98367 | F89: =I11*$N$5/$I$26 -> 1072.6952 | G89: =SUM(D89:F89) -> 3140.3345 | H89: =D89/W11 -> 0.70609463 | J89: West | K89: =(C98+C97+C96+C86)*(1-M84) -> 5805.5763 | L89: =D98+D97+D96+D86 -> 13991.424 | M89: =E98+E97+E96+E86 -> 1778.6949 | N89: =F98+F97+F96+F86 -> 4498.2362 | O89: =SUM(L89:N89) -> 20268.355 | Q89: =O89/8.76 -> 2313.7391
A90: Kymenlaakso | C90: =W12-G12 -> 8120 | D90: =G12+$M$84*C90 -> 6589.9943 | E90: =H12*$N$6/$H$26 -> 791.3685 | F90: =I12*$N$5/$I$26 -> 901.92419 | G90: =SUM(D90:F90) -> 8283.287 | H90: =D90/W12 -> 0.6497086 | J90: Center | K90: =(C88+C95)*(1-M84) -> 5112.0401 | L90: =D88+D95 -> 10907.96 | M90: =E88+E95 -> 2038.2973 | N90: =F88+F95 -> 4297.1058 | O90: =SUM(L90:N90) -> 17243.363 | Q90: =O90/8.76 -> 1968.4204
A91: Etelä-Karjala | C91: =W13-G13 -> 14226 | D91: =G13+$M$84*C91 -> 11934.239 | E91: =H13*$N$6/$H$26 -> 349.20705 | F91: =I13*$N$5/$I$26 -> 622.36564 | G91: =SUM(D91:F91) -> 12905.812 | H91: =D91/W13 -> 0.65720794 | J91: East | K91: =(C100+C93+C92+C94)*(1-M84) -> 3181.5153 | L91: =D100+D93+D92+D94 -> 7957.4847 | M91: =E100+E93+E92+E94 -> 1571.013 | N91: =F100+F93+F92+F94 -> 3390.1218 | O91: =SUM(L91:N91) -> 12918.619 | Q91: =O91/8.76 -> 1474.7282
A92: Etelä-Savo | C92: =W14-G14 -> 878 | D92: =G14+$M$84*C92 -> 825.82032 | E92: =H14*$N$6/$H$26 -> 359.25618 | F92: =I14*$N$5/$I$26 -> 827.29091 | G92: =SUM(D92:F92) -> 2012.3674 | H92: =D92/W14 -> 0.68249613 | J92: South West | K92: =(C102+C85+C87)*(1-M84) -> 1234.3632 | L92: =D102+D85+D87 -> 3380.6368 | M92: =E102+E85+E87 -> 1963.7663 | N92: =F102+F85+F87 -> 3893.5802 | O92: =SUM(L92:N92) -> 9237.9832 | Q92: =O92/8.76 -> 1054.5643
A93: Pohjois-Savo | C93: =W15-G15 -> 2890 | D93: =G15+$M$84*C93 -> 3194.445 | E93: =H15*$N$6/$H$26 -> 640.63164 | F93: =I15*$N$5/$I$26 -> 1283.9454 | G93: =SUM(D93:F93) -> 5119.022 | H93: =D93/W15 -> 0.7164039 | J93: South East | K93: =(C89+C90+C91)*(1-M84) -> 10441.111 | L93: =D89+D90+D91 -> 20117.889 | M93: =E89+E90+E91 -> 1614.5592 | N93: =F89+F90+F91 -> 2596.9851 | O93: =SUM(L93:N93) -> 24329.433 | Q93: =O93/8.76 -> 2777.3326
A94: Pohjois-Karjala | C94: =W16-G16 -> 3199 | D94: =G16+$M$84*C94 -> 3053.2383 | E94: =H16*$N$6/$H$26 -> 362.60588 | F94: =I16*$N$5/$I$26 -> 886.74454 | G94: =SUM(D94:F94) -> 4302.5887 | H94: =D94/W16 -> 0.68565872 | J94: Uusimaa | K94: =C84*(1-M84) -> 7323.9174 | L94: =D84 -> 13487.083 | M94: =E84 -> 5686.9666 | N94: =F84 -> 7387.4295 | O94: =SUM(L94:N94) -> 26561.479 | Q94: =O94/8.76 -> 3032.1323
A95: Keski-Suomi | C95: =W17-G17 -> 8980 | D95: =G17+$M$84*C95 -> 7415.6907 | E95: =H17*$N$6/$H$26 -> 662.40474 | F95: =I17*$N$5/$I$26 -> 1529.3497 | G95: =SUM(D95:F95) -> 9607.4452 | H95: =D95/W17 -> 0.65365277 | K95: =SUM(K88:K94) -> 40225.976 | L95: =SUM(L88:L94) -> 85780.024 | M95: =SUM(M88:M94) -> 16270.369 | N95: =SUM(N88:N94) -> 29825.482 | O95: =SUM(O88:O94) -> 131875.88 | Q95: =O95/8.76 -> 15054.324
A96: Etelä-Pohjanmaa | C96: =W18-G18 -> 831 | D96: =G18+$M$84*C96 -> 1012.3857 | E96: =H18*$N$6/$H$26 -> 520.87958 | F96: =I18*$N$5/$I$26 -> 1170.098 | G96: =SUM(D96:F96) -> 2703.3633 | H96: =D96/W18 -> 0.73574545
A97: Pohjanmaa | C97: =W19-G19 -> 5710 | D97: =G19+$M$84*C97 -> 4336.5194 | E97: =H19*$N$6/$H$26 -> 518.3673 | F97: =I19*$N$5/$I$26 -> 1581.2135 | G97: =SUM(D97:F97) -> 6436.1002 | H97: =D97/W19 -> 0.63445785
A98: Keski-Pohjanmaa | C98: =W20-G20 -> 824 | D98: =G20+$M$84*C98 -> 1988.4487 | E98: =H20*$N$6/$H$26 -> 147.38715 | F98: =I20*$N$5/$I$26 -> 431.35505 | G98: =SUM(D98:F98) -> 2567.1909 | H98: =D98/W20 -> 0.84650859
A99: Pohjois-Pohjanmaa | C99: =W21-G21 -> 9584 | D99: =G21+$M$84*C99 -> 7809.4031 | E99: =H21*$N$6/$H$26 -> 1050.1334 | F99: =I21*$N$5/$I$26 -> 2256.7079 | G99: =SUM(D99:F99) -> 11116.244 | H99: =D99/W21 -> 0.65062094
A100: Kainuu | C100: =W22-G22 -> 304 | D100: =G22+$M$84*C100 -> 883.98107 | E100: =H22*$N$6/$H$26 -> 208.51932 | F100: =I22*$N$5/$I$26 -> 392.14095 | G100: =SUM(D100:F100) -> 1484.6413 | H100: =D100/W22 -> 0.86920459
A101: Lappi | C101: =W23-G23 -> 6705 | D101: =G23+$M$84*C101 -> 8128.1449 | E101: =H23*$N$6/$H$26 -> 566.93807 | F101: =I23*$N$5/$I$26 -> 1505.3153 | G101: =SUM(D101:F101) -> 10200.398 | H101: =D101/W23 -> 0.73478077
A102: Ahvenanmaa | C102: =W24-G24 -> 72 | D102: =G24+$M$84*C102 -> 40.495516 | E102: =H25*$N$6/$H$26 -> 88.76726 | F102: =I25*$N$5/$I$26 -> 166.97615 | G102: =SUM(D102:F102) -> 296.23892 | H102: =D102/W24 -> 0.56243772
A103: Total | C103: =SUM(C84:C102) -> 91932 | D103: =SUM(D84:D102) -> 85780.024 | E103: =SUM(E84:E102) -> 16270.369 | F103: =SUM(F84:F102) -> 29825.482 | G103: =SUM(G84:G102) -> 131875.88 | H103: =D103/W25 -> 0.68076143
C104: =C103*(1-M84) -> 40225.976

Sheet D_heat
A1: 1. DH Data | U1: 3. Industiral heat
A2: Breakdown in National Trends scenario | G2: Regional breakdown from Finnish Energy | L2: DH_Regional_2023.xlsx | V2: TWh | X2: Source | Y2: Other (non)RES sheet in "H2 heavy.xlsx", values derived from near-constant output of "other (non)RES" technology output
A3: Source | B3: demanddata_DH_own_projection.xlsx | G3: [GWh] | I3: SUPPLY | L3: CONSUMPTION | P3: Assume that delivery between dh could be ignored | U3: FI | V3: 20.740078 | X3: Assumption | Y3: Industrial demand consumption is distributed among regions proportionally to distribution of unelectrified industrial demand
B4: Primary source is not specified | I4: DH production (net) by fuels | J4: Heat recovery and heat produced by heat pumps | K4: Purchased from outside | L4: DH delivery | M4: Delivery to other dh company | N4: Network losses and metering errors | O4: Delivery and losses | U4: North | V4: =$V$3*D_el!K88/D_el!$K$95 -> 3.6748372 | Y4: This is obviously inperfect proxy (e.g., sawmill needs a lot of electricity but no steam), but no regional data or better proxy was found
A5: [TWh] | B5: 2025 | C5: 2035 | U5: West | V5: =$V$3*D_el!K89/D_el!$K$95 -> 2.9932924
A6: HKI | B6: 6.5466202 | C6: 6.8940564 | U6: Center | V6: =$V$3*D_el!K90/D_el!$K$95 -> 2.6357126
A7: ESP | B7: 2.2342093 | C7: 2.3116653 | U7: East | V7: =$V$3*D_el!K91/D_el!$K$95 -> 1.6403549
A8: VAN | B8: 1.8913769 | C8: 1.9534343 | U8: South West | V8: =$V$3*D_el!K92/D_el!$K$95 -> 0.63642432 | X8: =V8/0.00876 -> 72.651178
A9: TKU | B9: 2.0784623 | C9: 2.0619271 | U9: South East | V9: =$V$3*D_el!K93/D_el!$K$95 -> 5.383324
A10: TRE | B10: 2.1785868 | C10: 2.2303642 | G10: Uusimaa | I10: 10144 | J10: 2449.8 | K10: 929.3 | L10: 11908.7 | M10: 616.9 | N10: 997.5 | O10: =L10+N10 -> 12906.2 | U10: Uusimaa | V10: =$V$3*D_el!K94/D_el!$K$95 -> 3.7761327
A11: OUL | B11: 1.9651786 | C11: 1.9174791 | G11: Varsinais-Suomi | I11: 2073.8 | J11: 757.3 | K11: 2257.1 | L11: 2596.4 | M11: 2257.1 | N11: 234.7 | O11: =L11+N11 -> 2831.1
A12: JKL | B12: 1.2152906 | C12: 1.2125036 | G12: Satakunta | I12: 1229.6 | J12: 96.6 | K12: 431.9 | L12: 1165.8 | M12: 431.9 | N12: 160.4 | O12: =L12+N12 -> 1326.2
A13: ROF | B13: 20.381214 | C13: 20.045263 | G13: Kanta-Häme | I13: 1088.3 | J13: 214.3 | K13: 237.9 | L13: 855.9 | M13: 549.8 | N13: 134.8 | O13: =L13+N13 -> 990.7
A14: FI | B14: =SUM(B6:B13) -> 38.490939 | C14: =SUM(C6:C13) -> 38.626693 | G14: Pirkanmaa | I14: 2583.3 | J14: 468.1 | K14: 513.1 | L14: 2816.7 | M14: 513.1 | N14: 234.7 | O14: =L14+N14 -> 3051.4
G15: Päijät-Häme | I15: 1277.8 | J15: 231.1 | K15: 134.1 | L15: 1328.9 | M15: 128.2 | N15: 185.9 | O15: =L15+N15 -> 1514.8
G16: Kymenlaakso | I16: 820.4 | J16: 112.2 | K16: 794.3 | L16: 815.6 | M16: 794.3 | N16: 117 | O16: =L16+N16 -> 932.6
G17: Etelä-Karjala | I17: 775.5 | J17: 34.8 | K17: 610.1 | L17: 698.3 | M17: 610.1 | N17: 112 | O17: =L17+N17 -> 810.3
G18: Etelä-Savo | I18: 840.6 | J18: 25.9 | K18: 184 | L18: 751.6 | M18: 191.3 | N18: 107.6 | O18: =L18+N18 -> 859.2
G19: Pohjois-Savo | I19: 1476.9 | J19: 305.2 | K19: 264.7 | L19: 1616.8 | M19: 246.8 | N19: 183.2 | O19: =L19+N19 -> 1800
G20: Pohjois-Karjala | I20: 802.1 | J20: 185.5 | K20: 28.3 | L20: 874.7 | M20: 28.3 | N20: 112.9 | O20: =L20+N20 -> 987.6
G21: Keski-Suomi | I21: 1533.5 | J21: 113.1 | K21: 1578.8 | L21: 1530.6 | M21: 1482.5 | N21: 212.3 | O21: =L21+N21 -> 1742.9
G22: Etelä-Pohjanmaa | I22: 961.5 | J22: 85.3 | K22: 588.1 | L22: 912.1 | M22: 579.5 | N22: 143.3 | O22: =L22+N22 -> 1055.4
G23: Pohjanmaa | I23: 999.5 | J23: 68.6 | K23: 1004.6 | L23: 940.1 | M23: 1004.6 | N23: 128 | O23: =L23+N23 -> 1068.1
G24: Keski-Pohjanmaa | I24: 321.1 | J24: 113.7 | K24: 9 | L24: 379.9 | N24: 63.9 | O24: =L24+N24 -> 443.8
G25: Pohjois-Pohjanmaa | I25: 2004.2 | J25: 793.7 | K25: 498.8 | L25: 2496.2 | M25: 496.3 | N25: 304.2 | O25: =L25+N25 -> 2800.4
G26: Kainuu | I26: 404 | J26: 58 | K26: 304.8 | L26: 396.4 | M26: 304.8 | N26: 65.6 | O26: =L26+N26 -> 462
G27: Lappi | I27: 1045.8 | J27: 121.8 | K27: 140 | L27: 1035.1 | M27: 144.4 | N27: 128.1 | O27: =L27+N27 -> 1163.2
G28: Ahvenanmaa | I28: 108.4 | J28: 13.9 | K28: 108.1 | L28: 107.6 | M28: 108.1 | N28: 14.7 | O28: =L28+N28 -> 122.3
G29: Total | I29: 30490.3 | J29: 6248.9 | K29: 10617 | L29: 33227.4 | M29: 10488 | N29: 3640.8 | O29: =L29+N29 -> 36868.2
A31: 2. DH Processing [TWh]
A32: Scaling | E32: Aggregating regions | I32: Disaggregating cities from regions | M32: North | O32: Lappi
A33: Uusimaa | C33: =O10*$C$14/$O$29 -> 13.521784 | E33: North | G33: =C50+C48 -> 4.1526508 | I33: HKI | K33: =C6 -> 6.8940564 | O33: Pohjois-Pohjanmaa
A34: Varsinais-Suomi | C34: =O11*$C$14/$O$29 -> 2.9661342 | E34: West | G34: =C47+C46+C45+C35 -> 4.0792072 | I34: ESP | K34: =C7 -> 2.3116653 | M34: West | O34: Keski-Pohjanmaa
A35: Satakunta | C35: =O12*$C$14/$O$29 -> 1.3894554 | E35: Center | G35: =C37+C44 -> 5.0229724 | I35: VAN | K35: =C8 -> 1.9534343 | O35: Pohjanmaa
A36: Kanta-Häme | C36: =O13*$C$14/$O$29 -> 1.0379532 | E36: East | G36: =C49+C42+C41+C43 -> 4.3047763 | I36: TKU | K36: =C9 -> 2.0619271 | O36: Etlä-Pohjanmaa
A37: Pirkanmaa | C37: =O14*$C$14/$O$29 -> 3.1969418 | E37: South West | G37: =C51+C34+C36 -> 4.1322207 | I37: TRE | K37: =C10 -> 2.2303642 | O37: Satakunta
A38: Päijät-Häme | C38: =O15*$C$14/$O$29 -> 1.587051 | E38: South East | G38: =C38+C39+C40 -> 3.4130816 | I38: OUL | K38: =C11 -> 1.9174791 | M38: Center | O38: Pirkanmaa
A39: Kymenlaakso | C39: =O16*$C$14/$O$29 -> 0.97708197 | E39: Uusimaa | G39: =C33 -> 13.521784 | I39: JKL | K39: =C12 -> 1.2125036 | O39: Keski-Suomi
A40: Etelä-Karjala | C40: =O17*$C$14/$O$29 -> 0.84894866 | E40: Total | G40: =SUM(G33:G39) -> 38.626693 | I40: North | K40: =G33-K38 -> 2.2351716 | M40: East | O40: Kainuu
A41: Etelä-Savo | C41: =O18*$C$14/$O$29 -> 0.90018103 | I41: West | K41: =G34 -> 4.0792072 | O41: Pohjois-Savo
A42: Pohjois-Savo | C42: =O19*$C$14/$O$29 -> 1.8858541 | I42: Center | K42: =G35-K39-K37 -> 1.5801047 | O42: Etelä-Savo
A43: Pohjois-Karjala | C43: =O20*$C$14/$O$29 -> 1.0347053 | I43: East | K43: =G36 -> 4.3047763 | O43: Pohjois-Karjala
A44: Keski-Suomi | C44: =O21*$C$14/$O$29 -> 1.8260306 | I44: South West | K44: =G37-K36 -> 2.0702936 | M44: South West | O44: Ahvenanmaa
A45: Etelä-Pohjanmaa | C45: =O22*$C$14/$O$29 -> 1.1057391 | I45: South East | K45: =G38 -> 3.4130816 | O45: Varsinais-Suomi
A46: Pohjanmaa | C46: =O23*$C$14/$O$29 -> 1.1190449 | I46: Uusimaa | K46: =G39-SUM(K33:K35) -> 2.3626276 | O46: Kanta-Häme
A47: Keski-Pohjanmaa | C47: =O24*$C$14/$O$29 -> 0.46496781 | I47: Total | K47: =SUM(K33:K46) -> 38.626693 | M47: South East | O47: Päijät-Häme
A48: Pohjois-Pohjanmaa | C48: =O25*$C$14/$O$29 -> 2.9339699 | O48: Kymenlaakso
A49: Kainuu | C49: =O26*$C$14/$O$29 -> 0.48403589 | O49: Etelä-Karjala
A50: Lappi | C50: =O27*$C$14/$O$29 -> 1.2186808 | M50: Uusimaa | O50: Uusimaa
A51: Ahvenanmaa | C51: =O28*$C$14/$O$29 -> 0.12813331
A52: Total | C52: =O29*$C$14/$O$29 -> 38.626693

Sheet Tr_el
A1: Cross border
A2: Existing | H2: Future
A3: Sources | B3: Part of the Nordic power system - Fingrid | H3: Consideration 1: | K3: Consideration 2: TYNDP 2024 data | T3: Consideration 3: Fingrid data
B4: fingrid_kehittamissuunnitelma_syksy23_en.pdf | H4: Possible connections | K4: Modeled | M4: Ref | O4: DE 2035 | Q4: Increase | T4: Best source found: | V4: Main grid developments 2024-2033
C5: [MW] | D5: [MW] | E5: [kV] | H5: FINO | I5: NON1 | K5: FIN0 | L5: SE01 | M5: 2000 | N5: 2000 | O5: 4400 | P5: 4500 | Q5: =O5-M5 -> 2400 | R5: =P5-N5 -> 2500 | V5: Figue 2
A6: FINO | B6: NON1 | C6: 100 | E6: 220 | F6: AC | H6: FINO | I6: SE01 | K6: FISW | L6: SE03 | M6: 1200 | N6: 1200 | O6: 1700 | P6: 1700 | Q6: =O6-M6 -> 500 | R6: =P6-N6 -> 500 | T6: New Line | U6: Nodes | W6: Capacity [MW] | X6: Required to match [MW] | Y6: Likely in single line
A7: FINO | B7: SE01 | C7: 1100 | D7: 1200 | E7: 400x2 | F7: AC | H7: FINO | I7: SE02 | K7: FIUU | L7: EE00 | M7: 1016 | N7: 1016 | O7: 1716 | P7: 1716 | Q7: =O7-M7 -> 700 | R7: =P7-N7 -> 700
A8: FIWE | B8: SE03 | C8: 400 | F8: DC | H8: FIW0 | I8: SE01 | K8: Investment candidates
A9: FIWE | B9: SE03 | C9: 800 | F9: DC | H9: FIW0 | I9: SE02 | K9: FI00 | L9: NON1 | M9: Concept 1 | N9: 2040 | O9: 500 | P9: 500 | T9: EstLink 3 | U9: FIUU | V9: EE00 | W9: Not yet known | X9: =R7 -> 700 | Y9: Y
A10: FIUU | B10: EE00 | C10: 350 | F10: DC | H10: FIW0 | I10: SE03 | K10: FI00 | L10: NON1 | M10: Concept 2 | N10: 2040 | O10: 500 | P10: 500 | T10: Aurora 1 | U10: FINO | V10: SE04 | W10: 800 / 900 | Y10: Y
A11: FIUU | B11: EE00 | C11: 650 | F11: DC | H11: FISW | I11: SE03 | K11: FI00 | L11: SE01 | M11: Real 1 | N11: 2035 | O11: 800 | P11: 800 | T11: Aurora 2 | U11: FINO | V11: SE04 | W11: Not yet known | X11: =Q5-800 -> 1600 | Y11: N
H12: FISW | I12: IBFI | K12: FI00 | L12: SE01 | M12: Real 2 | N12: 2030 | O12: 800 | P12: 900 | U12: FINO | V12: NON1 | W12: ~150 MW | Y12: Y
H13: FIUU | I13: EE00 | K13: FI00 | L13: SE01 | M13: Concept 1 | N13: 2030 | O13: 800 | P13: 800
H14: FISE | I14: EE00 | K14: FI00 | L14: SE01 | M14: Concept 2 | N14: 2040 | O14: 800 | P14: 800 | T14: Conclusion - new capacities will connect the same regions
K15: FI00 | L15: SE01 | M15: Concept 3 | N15: 2040 | O15: 800 | P15: 800
K16: FI00 | L16: SE02 | M16: Concept 1 | N16: 2030 | O16: 500 | P16: 500
K17: FI00 | L17: SE02 | M17: Concept 2 | N17: 2040 | O17: 500 | P17: 500
K18: FI00 | L18: SE02 | M18: Concept 3 | N18: 2040 | O18: 500 | P18: 500
K19: FI00 | L19: SE02 | M19: Concept 4 | N19: 2040 | O19: 500 | P19: 500
K20: FI00 | L20: SE03 | M20: Real 1 | N20: 2040 | O20: 800 | P20: 800
K21: FI00 | L21: SE03 | M21: Concept 1 | N21: 2030 | O21: 500 | P21: 500
K22: FI00 | L22: SE03 | M22: Concept 2 | N22: 2040 | O22: 500 | P22: 500
K23: FI00 | L23: SE03 | M23: Concept 3 | N23: 2040 | O23: 500 | P23: 500
K24: FI00 | L24: SE03 | M24: Concept 4 | N24: 2040 | O24: 500 | P24: 500
K25: FI00 | L25: EE00 | M25: Real 1 | N25: 2035 | O25: 700 | P25: 700
K26: FI00 | L26: EE00 | M26: Concept 1 | N26: 2030 | O26: 700 | P26: 700
K27: FI00 | L27: EE00 | M27: Concept 2 | N27: 2040 | O27: 700 | P27: 700
K28: Investment candidates aggregated
K29: FI00 | L29: NON1 | O29: =SUM(O9:O10) -> 1000 | P29: =SUM(P9:P10) -> 1000
K30: FI00 | L30: SE01 | O30: =SUM(O11:O15) -> 4000 | P30: =SUM(P11:P15) -> 4100
K31: FI00 | L31: SE02 | O31: =SUM(O16:O19) -> 2000 | P31: =SUM(P16:P19) -> 2000
K32: FI00 | L32: SE03 | O32: =SUM(O20:O24) -> 2800 | P32: =SUM(P20:P24) -> 2800
K33: FI00 | L33: EE00 | O33: =SUM(O25:O27) -> 2100 | P33: =SUM(P25:P27) -> 2100
A35: Domestic
A36: Source | B36: FinGrid map | Q36: Dirrect Copilot answer. It's assumptions:
C37: Current | G37: Investment projects | J37: Planned routes | L37: Future | Q37: 400 kV single main corridor ≈ 1,200 MW
C38: 400 kV | D38: 220 kV | E38: 100 kV | F38: MW | G38: Changes | I38: New | L38: 400 kV | M38: 220 kV | N38: 100 kV | O38: MW | Q38: 2 strong corridors / upgrade completed ≈ 1,800–2,400 MW
A39: FIN0 | B39: FIW0 | C39: 2 | D39: 1 | F39: =C39*$C$59+D39*$D$59+E39*$E$59 -> 2300 | G39: 220 -> 400 | L39: 3 | O39: =L39*$C$59+M39*$D$59+N39*$E$59 -> 3000 | Q39: Major reinforced trunk (2035 north–south) up to 3,000 MW
A40: FIN0 | B40: FIC0 | C40: 1 | F40: =C40*$C$59+D40*$D$59+E40*$E$59 -> 1000 | G40: 400 -> ? | I40: +400 | L40: 2 | O40: =L40*$C$59+M40*$D$59+N40*$E$59 -> 2000 | S40: 2025 | T40: 2035 | U40: Δ
A41: FIN0 | B41: FIE0 | C41: 1 | D41: 1 | E41: 1 | F41: =C41*$C$59+D41*$D$59+E41*$E$59 -> 1400 | G41: 220 -> ? | L41: 1 | M41: 1 | N41: 1 | O41: =L41*$C$59+M41*$D$59+N41*$E$59 -> 1400 | Q41: FIN0 | R41: FIW0 | S41: 1200 | T41: 1600 | U41: =T41-S41 -> 400
A42: FIW0 | B42: FIC0 | C42: 4 | D42: 3 | F42: =C42*$C$59+D42*$D$59+E42*$E$59 -> 4900 | G42: 220 -> 400+110 | I42: +400 | L42: 6 | M42: 2 | N42: 1 | O42: =L42*$C$59+M42*$D$59+N42*$E$59 -> 6700 | Q42: FIN0 | R42: FIC0 | S42: 1800 | T42: 3000 | U42: =T42-S42 -> 1200
A43: FIW0 | B43: FISW | C43: 2 | D43: 1 | F43: =C43*$C$59+D43*$D$59+E43*$E$59 -> 2300 | L43: 2 | M43: 1 | O43: =L43*$C$59+M43*$D$59+N43*$E$59 -> 2300 | Q43: FIN0 | R43: FIE0 | S43: 1200 | T43: 2400 | U43: =T43-S43 -> 1200
A44: FIC0 | B44: FISW | C44: 1 | D44: 1 | F44: =C44*$C$59+D44*$D$59+E44*$E$59 -> 1300 | G44: 220 -> 2X400+110 | L44: 3 | N44: 1 | O44: =L44*$C$59+M44*$D$59+N44*$E$59 -> 3100 | Q44: FIW0 | R44: FIC0 | S44: 1200 | T44: 2400 | U44: =T44-S44 -> 1200
A45: FIC0 | B45: FISE | F45: =C45*$C$59+D45*$D$59+E45*$E$59 -> 0 | O45: =L45*$C$59+M45*$D$59+N45*$E$59 -> 0 | Q45: FIW0 | R45: FISW | S45: 1500 | T45: 1800 | U45: =T45-S45 -> 300
A46: FIC0 | B46: FIE0 | C46: 1 | D46: 1 | F46: =C46*$C$59+D46*$D$59+E46*$E$59 -> 1300 | J46: +? | L46: 1 | M46: 1 | O46: =L46*$C$59+M46*$D$59+N46*$E$59 -> 1300 | Q46: FIC0 | R46: FISW | S46: 1500 | T46: 1800 | U46: =T46-S46 -> 300
A47: FIE0 | B47: FISE | C47: 1 | D47: 3 | F47: =C47*$C$59+D47*$D$59+E47*$E$59 -> 1900 | L47: 1 | M47: 3 | O47: =L47*$C$59+M47*$D$59+N47*$E$59 -> 1900 | Q47: FIC0 | R47: FISE | S47: 1200 | T47: 2000 | U47: =T47-S47 -> 800
A48: FISW | B48: FISE | D48: 1 | F48: =C48*$C$59+D48*$D$59+E48*$E$59 -> 300 | M48: 1 | O48: =L48*$C$59+M48*$D$59+N48*$E$59 -> 300 | Q48: FIC0 | R48: FIE0 | S48: 1200 | T48: 1800 | U48: =T48-S48 -> 600
A49: FISW | B49: FIUU | C49: 4 | D49: 3 | F49: =C49*$C$59+D49*$D$59+E49*$E$59 -> 4900 | I49: +400 | J49: +? | L49: 5 | M49: 3 | O49: =L49*$C$59+M49*$D$59+N49*$E$59 -> 5900 | Q49: FIE0 | R49: FISE | S49: 1200 | T49: 1800 | U49: =T49-S49 -> 600
A50: FISE | B50: FIUU | C50: 2 | D50: 1 | F50: =C50*$C$59+D50*$D$59+E50*$E$59 -> 2300 | L50: 2 | M50: 1 | O50: =L50*$C$59+M50*$D$59+N50*$E$59 -> 2300 | Q50: FISW | R50: FIUU | S50: 1800 | T50: 2200 | U50: =T50-S50 -> 400
F51: =SUM(F39:F50) -> 23900 | O51: =SUM(O39:O50) -> 30200 | Q51: FISE | R51: FIUU | S51: 1200 | T51: 1500 | U51: =T51-S51 -> 300
Q52: FISW | R52: FISE | S52: 700 | T52: 1000 | U52: =T52-S52 -> 300
A53: Line capacities | S53: =SUM(S41:S52) -> 15700 | T53: =SUM(T41:T52) -> 23300 | U53: =SUM(U41:U52) -> 7600
A54: Source | B54: Copilot dirrecting to (behind pay-wall):
B55: Thermal behaviour of overhead conductors - eCIGRE
A56: Line capacities | C56: 400 kV | D56: 220 kV | E56: 100 kV
A57: Min | C57: 700 | D57: 230 | E57: 60
A58: Max | C58: 1030 | D58: 320 | E58: 95
A59: Rounded values | C59: 1000 | D59: 300 | E59: 100

Sheet H2
A1: 1. National data | L1: 3. Transmission
A2: Source | C2: [1] Visual Platform. TYNDP 2024 release - Distributed Energy 2035 scenario. | L2: Existing h2 connections
C3: [2] H2 Storages.xlsx | L3: FINO | M3: SE01 | N3: 7899 | O3: 7546
A4: Simplifications | C4: No H2 inports and production from CH4 -> demand is scaled down to production capacity of electrolyser over all countries present in North European model | L4: FISW | M4: IBFI | N4: 21000 | O4: 21000
L5: FIUU | M5: EE00 | N5: 8330 | O5: 4205
C6: H2 supply is determined by the model. H2 demand sectors are not modeled.
E7: FI | F7: NE | L7: Extending tyndp2024 cross-border lines internally
A8: Capacity [1] | B8: Electrolyser | D8: MW_h2 | E8: 15300 | F8: 146690 | L8: FINO | M8: FIW0 | N8: 8000
B9: Imports | E9: 55310 | F9: 326130 | L9: FIW0 | M9: FISW | N9: 8000
B10: Steam CH4 reformer | E10: 500 | F10: 21860 | L10: FISW | M10: FIC0 | N10: 8000
A11: Supply [1] | B11: Electrolyser | D11: TWh_h2 | E11: 50.48 | F11: 397.6 | L11: FIC0 | M11: FISE | N11: 8000
B12: Imports | E12: -28.74 | F12: 175.8 | L12: FISE | M12: FIUU | N12: 8000
B13: Steam CH4 reformer | E13: 2.2 | F13: 156.96
B14: Total | E14: =SUMIF(E11:E13,">0",E11:E13) -> 52.68 | F14: =SUM(F11:F13) -> 730.36
A15: Demand [1] | B15: E-diesel | D15: TWh_h2 | E15: 3.2 | F15: 108.9
B16: E-kerosene | E16: 3.18 | F16: 108.27
B17: H2 boiler | F17: 7.14
B18: H2P | F18: 3.53
B19: Native | E19: 14.91 | F19: 588
B20: SNG | E20: 2.66 | F20: 93.92
B21: Total | E21: =SUM(E15:E20) -> 23.95 | F21: =SUM(F15:F20) -> 909.76
B22: Native share | E22: =E19/E21 -> 0.62254697 | F22: =F19/F21 -> 0.64632431
B23: Total (normalized) | E23: =E21*$F$11/$F$21 -> 10.467068
A24: Storage [2] | B24: ST (dis)charge | D24: MW_h2 | E24: 266.7168 | F24: 8048.5537
B25: LT charge | E25: 3129.4252 | F25: 56360.978
B26: LT discharge | E26: 1659.0324 | F26: 29879.189
A28: 2. Regional breakdown
A29: Assumtions | B29: Electrolyser capacity is distributed proportionally to projectected non-CHP electricity production capacity
B31: H2 demand and storage capacities are distributed proportionally to non-electrified demand
B32: Both omit East as H2 grid does not reach it
B33: [MW] | C33: [TWh_h2] | D33: [MW_h2]
A34: Column1 | B34: Electrolyser | C34: Demand | D34: Store_short | E34: Store_long_in | F34: Store_long_out | G34: Valve
A35: North | B35: =$E$8*B46/$B$54 -> 5878.5239 | C35: =$E$23*D_el!$K88/(D_el!$K$95-D_el!$K$91) -> 2.0138916 | D35: =$E$24*D_el!$K88/(D_el!$K$95-D_el!$K$91) -> 51.317017 | E35: =$E$25*D_el!$K88/(D_el!$K$95-D_el!$K$91) -> 602.10968 | F35: =$E$26*D_el!$K88/(D_el!$K$95-D_el!$K$91) -> 319.20221 | G35: =P_H2[[#This Row],[Demand]]/0.00876*1.01 -> 232.19526
A36: West | B36: =$E$8*B47/$B$54 -> 6753.5638 | C36: =$E$23*D_el!$K89/(D_el!$K$95-D_el!$K$91) -> 1.64039 | D36: =$E$24*D_el!$K89/(D_el!$K$95-D_el!$K$91) -> 41.79963 | E36: =$E$25*D_el!$K89/(D_el!$K$95-D_el!$K$91) -> 490.44086 | F36: =$E$26*D_el!$K89/(D_el!$K$95-D_el!$K$91) -> 260.00214 | G36: =P_H2[[#This Row],[Demand]]/0.00876*1.01 -> 189.13173
A37: Center | B37: =$E$8*B48/$B$54 -> 571.70859 | C37: =$E$23*D_el!$K90/(D_el!$K$95-D_el!$K$91) -> 1.4444285 | D37: =$E$24*D_el!$K90/(D_el!$K$95-D_el!$K$91) -> 36.806232 | E37: =$E$25*D_el!$K90/(D_el!$K$95-D_el!$K$91) -> 431.85262 | F37: =$E$26*D_el!$K90/(D_el!$K$95-D_el!$K$91) -> 228.94219 | G37: =P_H2[[#This Row],[Demand]]/0.00876*1.01 -> 166.53799
A38: East
A39: South West | B39: =$E$8*B50/$B$54 -> 831.65527 | C39: =$E$23*D_el!$K92/(D_el!$K$95-D_el!$K$91) -> 0.34877452 | D39: =$E$24*D_el!$K92/(D_el!$K$95-D_el!$K$91) -> 8.8873046 | E39: =$E$25*D_el!$K92/(D_el!$K$95-D_el!$K$91) -> 104.27598 | F39: =$E$26*D_el!$K92/(D_el!$K$95-D_el!$K$91) -> 55.280829 | G39: =P_H2[[#This Row],[Demand]]/0.00876*1.01 -> 40.212587
A40: South East | B40: =$E$8*B51/$B$54 -> 828.01815 | C40: =$E$23*D_el!$K93/(D_el!$K$95-D_el!$K$91) -> 2.9501799 | D40: =$E$24*D_el!$K93/(D_el!$K$95-D_el!$K$91) -> 75.175066 | E40: =$E$25*D_el!$K93/(D_el!$K$95-D_el!$K$91) -> 882.03948 | F40: =$E$26*D_el!$K93/(D_el!$K$95-D_el!$K$91) -> 467.6041 | G40: =P_H2[[#This Row],[Demand]]/0.00876*1.01 -> 340.14632
A41: Uusimaa | B41: =$E$8*B52/$B$54 -> 436.53023 | C41: =$E$23*D_el!$K94/(D_el!$K$95-D_el!$K$91) -> 2.0694037 | D41: =$E$24*D_el!$K94/(D_el!$K$95-D_el!$K$91) -> 52.731551 | E41: =$E$25*D_el!$K94/(D_el!$K$95-D_el!$K$91) -> 618.7066 | F41: =$E$26*D_el!$K94/(D_el!$K$95-D_el!$K$91) -> 328.00089 | G41: =P_H2[[#This Row],[Demand]]/0.00876*1.01 -> 238.59563
B42: =SUM(B35:B41) -> 15300 | C42: =SUM(C35:C41) -> 10.467068 | D42: =SUM(D35:D41) -> 266.7168 | E42: =SUM(E35:E41) -> 3129.4252 | F42: =SUM(F35:F41) -> 1659.0324
A44: non-CHP electricity generation capacity
A45: Region | B45: Capacity
A46: North | B46: =P_hydro!K11+P_el1!AM15 -> 28516.768
A47: West | B47: =P_hydro!K12+P_el1!AM16 -> 32761.593
A48: Center | B48: =P_hydro!K13+P_el1!AM17 -> 2773.363
A49: East | B49: =P_hydro!K14+P_el1!AM18 -> 4788.625
A50: South West | B50: =P_hydro!K15+P_el1!AM19 -> 4034.3665
A51: South East | B51: =P_hydro!K16+P_el1!AM20 -> 4016.7228
A52: Uusimaa | B52: =P_hydro!K17+P_el1!AM21 -> 2117.6117
A53: Total | B53: =SUM(B46:B52) -> 79009.05
A54: Total - East | B54: =SUM(B46:B48,B50:B52) -> 74220.425

Sheet P_el1
A1: Source [1] | B1: Power plant register (latest update 27.6.2025) | D1: Delivery reliability | Energy Authority | P1: Sources | Q1: [2] Visual Platform, [3] Plexos output | V1: Source [4] | W1: Global Energy Monitor | AA1: Source [5] | AB1: Renewables Finland | AF1: Merging sources [1-5] | AT1: Batteries
A2: Capacity column selection | B2: Capacities are taken from column "Maximum, total, MW" | Q2: Distributed Energy 2035 scenario | V2: Checking pages of individual thermal plants (from plant register with over 50 MW) to determine their type more precise matching with data from Plexos output. | AA2: Selection | AF2: Assumptions are unit type specific | AT2: Assume proportional distribution to non-CHP generation capacity
B3: Taking "Maximum, total, MW" as it contains no zero values, unlike "Hour, total, MW" | P3: Type [2] | R3: Capacity | AA3: The most easy-to-use data in Rewnewables Finland website is in "PV development projects" report. It contains exact capacities only for top 10/19 regions with 80+% of all capacities. It also contains % of capacities for all regions, but less precisely. To fill the absolute values of remaining regions, I need total capacity. I chose to compute it for sataukunta, region with the largest regional capacity, by dividing regional capacity from regional share. Note that same computation for other regions give different values beyond possible error bounds from rounding of regional share percentage. | AF3: Nuclear | AG3: Decrease of 1 119 MW match closure of two Loviisa units
A4: Region search | B4: Performed with Copilot, which provides one of three basis: | P4: Solar | R4: 21270 | AF4: Wind | AG4: While capacity increases 6-fold, there already a lot of wind capacity to be representative for making following assumptions
B5: [1] Municipality in Location mapped to administrative region | F5: sources: sheet "Regions", Statistics Finland municipal → region mapping | P5: Wind Onshore | R5: 46000 | V5: Name | W5: Capacity | X5: Technology | Y5: Fuel | AG5: - Onshore wind is distributed proportionally to existing wind capacity distribution | AT5: Capacity from Visual Platform | AW5: 1270
B6: [2] Project/plant name mapped to region | F6: sources: Energy Authority register, developer/operator sites, Wikipedia; cross-checked with sheet "Regions" | P6: Wind Offshore | R6: 3600 | V6: Meri-Pori | W6: 565 | X6: supercritical | Y6: coal: bituminous | AG6: - Offshore wind is distributed proportionally to existing wind capacity on the west coast regions (i.e., no Offshore wind in Gulf of Finland)
B7: [3] Heuristic assignment using Location/Name tokens and public plant lists | F7: sources: Energy Authority register, developer/operator sites, Wikipedia, sheet "Regions" | P7: Type [3] | R7: Capacity | V7: Forssa kt | W7: 352 | X7: gas turbine | Y7: heavy fuel oil | AF7: Thernal | AG7: Total differs only by 5% -> using current (i.e., plant register) values. Unit type separation followed these considerations: | AT7: Region | AU7: non-CHP | AV7: Battery
B8: In case plant site is in the boundary of region, two regions are listed | P8: Nuclear | R8: 3250 | V8: Huutokoski kt | W8: 180 | X8: gas turbine | Y8: heavy fuel oil | AG8: - Global energy monitor info allows distinction only of two unit types that nonetheless captures major distinctions present in Plexos output | AT8: North | AU8: =_xlfn.XLOOKUP(Battery[[#This Row],[Region]],P_el_final[Region],P_el_final[Total])+_xlfn.XLOOKUP(Battery[[#This Row],[Region]],P_hydro_3[Region],P_hydro_3[Capacity]) -> 28516.768 | AV8: =$AW$5*AU8/$AU$15 -> 458.3816
B9: Manually checked for validation: plants with >200 MW representing 46% of total capacity (no corrections), plants with two regions (most reduced to one region) | P9: Hard coal new Bio | R9: 928 | V9: Kellosaari | W9: 118 | X9: gas turbine | Y9: light fuel oil | AG9: dataset (burning gas vs solid). | AT9: West | AU9: =_xlfn.XLOOKUP(Battery[[#This Row],[Region]],P_el_final[Region],P_el_final[Total])+_xlfn.XLOOKUP(Battery[[#This Row],[Region]],P_hydro_3[Region],P_hydro_3[Capacity]) -> 32761.593 | AV9: =$AW$5*AU9/$AU$15 -> 526.61339
A10: Omissions | B10: Region 2, capacities bellow 100 MW in the final table | P10: Gas OCGT old | R10: 38 | V10: Mertaniemi 1 ja 2 | W10: 102 | X10: gas turbine | Y10: light fuel oil, natural gas | AG10: - Identified coal plants are separated manually while the remaining capacity is allocated to gas plants | AT10: Center | AU10: =_xlfn.XLOOKUP(Battery[[#This Row],[Region]],P_el_final[Region],P_el_final[Total])+_xlfn.XLOOKUP(Battery[[#This Row],[Region]],P_hydro_3[Region],P_hydro_3[Capacity]) -> 2773.363 | AV10: =$AW$5*AU10/$AU$15 -> 44.579337
A11: Notations | B11: For simplicity all power plant register types are renamed: nuclear energy > nuclear, wind power > wind, separate electricity production > thermal | P11: Gas CCGT old 2 | R11: 640 | V11: Olkiluoto kt | W11: 100.5 | X11: gas turbine | Y11: heavy fuel oil | AG11: - All gas capacity is assigned to unit type present in Plexos output with the largest capacity | AT11: East | AU11: =_xlfn.XLOOKUP(Battery[[#This Row],[Region]],P_el_final[Region],P_el_final[Total])+_xlfn.XLOOKUP(Battery[[#This Row],[Region]],P_hydro_3[Region],P_hydro_3[Capacity]) -> 4788.625 | AV11: =$AW$5*AU11/$AU$15 -> 76.972875
A12: Units | B12: MW | P12: Gas CCGT present 1 | R12: 234 | V12: Porvoo Tolkkinen | W12: 80 | X12: gas turbine | Y12: heavy fuel oil | AF12: Solar | AG12: Using proposed instead of built project capacities as the latter is too small to serve as a reasonable proxy for expected future capacity distribution. | AT12: South West | AU12: =_xlfn.XLOOKUP(Battery[[#This Row],[Region]],P_el_final[Region],P_el_final[Total])+_xlfn.XLOOKUP(Battery[[#This Row],[Region]],P_hydro_3[Region],P_hydro_3[Capacity]) -> 4034.3665 | AV12: =$AW$5*AU12/$AU$15 -> 64.848843
P13: Gas OCGT new | R13: 87 | V13: Kristiinankaupunki kt | W13: 60 | X13: subcritical | Y13: coal: bituminous | AT13: South East | AU13: =_xlfn.XLOOKUP(Battery[[#This Row],[Region]],P_el_final[Region],P_el_final[Total])+_xlfn.XLOOKUP(Battery[[#This Row],[Region]],P_hydro_3[Region],P_hydro_3[Capacity]) -> 4016.7228 | AV13: =$AW$5*AU13/$AU$15 -> 64.565236
A14: Powerplant register subset | E14: Region search | I14: Aggregated by region and unit type | V14: Tahkoluoto kt | W14: 52 | X14: gas turbine | Y14: heavy fuel oil | AA14: Project stages | AF14: Region | AG14: Nuclear | AH14: Wind Onshore | AI14: Wind Offshore | AJ14: Hard coal new bio | AK14: Gass CCGT old 2 | AL14: Solar | AM14: Total | AT14: Uusimaa | AU14: =_xlfn.XLOOKUP(Battery[[#This Row],[Region]],P_el_final[Region],P_el_final[Total])+_xlfn.XLOOKUP(Battery[[#This Row],[Region]],P_hydro_3[Region],P_hydro_3[Capacity]) -> 2117.6117 | AV14: =$AW$5*AU14/$AU$15 -> 34.038719
A15: Name | B15: Location | C15: Type | D15: Capacity | E15: Region 1 | F15: Region 2 | G15: Basis | I15: Region | J15: Nuclear | K15: Wind | L15: Thermal | M15: Solar | N15: Total | V15: Vanaja kt 1 | W15: 50 | X15: gas turbine | Y15: heavy fuel oil | AA15: "PV development report" does not explicitly specify for which project stages are regional values given. The closest, but not exact, national total in the report is for projects in "permitting / studies ongoing" category. It is preferable to account first "operating" and "under construction" project capacities, but they alone are not enough given their low capacities. Rewnewables Finland website does contain project specific information, but only in interactive map. Extraction of this information is deemed too time consuming and therefore not undertaken. | AF15: North | AG15: 0 | AH15: =K38/$K$45*$R$5 -> 22638.198 | AI15: =K38/SUM($K$38,$K$39,$K$42)*R$6 -> 1925.077 | AK15: =L38-AJ15 -> 120.1 | AL15: =AB49/$AB$56*$R$4 -> 2066.393 | AM15: =SUM(AG15:AL15) -> 26749.768 | AT15: Finland | AU15: =SUM(Battery[non-CHP]) -> 79009.05 | AV15: =SUM(Battery[Battery]) -> 1270
A16: Olkiluoto 3 | B16: Olkiluoto 3 | C16: Nuclear | D16: 1575 | E16: Satakunta | G16: [2] | I16: Uusimaa | J16: =SUMIFS(P_el[Capacity], P_el[Type], J$15, P_el[Region 1], P_el_2[[#This Row],[Region]]) -> 1014 | K16: =SUMIFS(P_el[Capacity], P_el[Type], K$15, P_el[Region 1], P_el_2[[#This Row],[Region]]) -> 26.65 | L16: =SUMIFS(P_el[Capacity], P_el[Type], L$15, P_el[Region 1], P_el_2[[#This Row],[Region]]) -> 226.25 | M16: =SUMIFS(P_el[Capacity], P_el[Type], M$15, P_el[Region 1], P_el_2[[#This Row],[Region]]) -> 10.33 | N16: =SUM(P_el_2[[#This Row],[Nuclear]:[Thermal]]) -> 1266.9 | V16: Naantali kt | W16: 40 | AF16: West | AG16: =J39 -> 3355 | AH16: =K39/$K$45*$R$5 -> 18945.898 | AI16: =K39/SUM($K$38,$K$39,$K$42)*R$6 -> 1611.0962 | AJ16: =W6+W13 -> 625 | AK16: =L39-AJ16 -> 205.1 | AL16: =AB50/$AB$56*$R$4 -> 7869.4987 | AM16: =SUM(AG16:AL16) -> 32611.593
A17: Olkiluoto 1 | B17: Olkiluoto 1 | C17: Nuclear | D17: 890 | E17: Satakunta | G17: [2] | I17: Southwest Finland | J17: =SUMIFS(P_el[Capacity], P_el[Type], J$15, P_el[Region 1], P_el_2[[#This Row],[Region]]) -> 0 | K17: =SUMIFS(P_el[Capacity], P_el[Type], K$15, P_el[Region 1], P_el_2[[#This Row],[Region]]) -> 83.55 | L17: =SUMIFS(P_el[Capacity], P_el[Type], L$15, P_el[Region 1], P_el_2[[#This Row],[Region]]) -> 41.1 | M17: =SUMIFS(P_el[Capacity], P_el[Type], M$15, P_el[Region 1], P_el_2[[#This Row],[Region]]) -> 0 | N17: =SUM(P_el_2[[#This Row],[Nuclear]:[Thermal]]) -> 124.65 | V17: Porvoo Kilpilahti | W17: 27 | AF17: Center | AG17: 0 | AH17: =K40/$K$45*$R$5 -> 2004.428 | AI17: 0 | AK17: =L40-AJ17 -> 7 | AL17: =AB51/$AB$56*$R$4 -> 645.83509 | AM17: =SUM(AG17:AL17) -> 2657.263
A18: Olkiluoto 2 | B18: Olkiluoto 2 | C18: Nuclear | D18: 890 | E18: Satakunta | G18: [2] | I18: Satakunta | J18: =SUMIFS(P_el[Capacity], P_el[Type], J$15, P_el[Region 1], P_el_2[[#This Row],[Region]]) -> 3355 | K18: =SUMIFS(P_el[Capacity], P_el[Type], K$15, P_el[Region 1], P_el_2[[#This Row],[Region]]) -> 452.1 | L18: =SUMIFS(P_el[Capacity], P_el[Type], L$15, P_el[Region 1], P_el_2[[#This Row],[Region]]) -> 725.9 | M18: =SUMIFS(P_el[Capacity], P_el[Type], M$15, P_el[Region 1], P_el_2[[#This Row],[Region]]) -> 27.7 | N18: =SUM(P_el_2[[#This Row],[Nuclear]:[Thermal]]) -> 4533 | P18: Aggregated comparison | V18: Vaskiluoto kt | W18: 26 | AF18: East | AG18: 0 | AH18: =K41/$K$45*$R$5 -> 1253.0378 | AI18: 0 | AK18: =L41-AJ18 -> 182.6 | AL18: =AB52/$AB$56*$R$4 -> 2895.0872 | AM18: =SUM(AG18:AL18) -> 4330.725
A19: Meri-Pori | B19: Meri-Pori | C19: Thermal | D19: 565 | E19: Satakunta | G19: [1] | I19: Kanta-Häme | J19: =SUMIFS(P_el[Capacity], P_el[Type], J$15, P_el[Region 1], P_el_2[[#This Row],[Region]]) -> 0 | K19: =SUMIFS(P_el[Capacity], P_el[Type], K$15, P_el[Region 1], P_el_2[[#This Row],[Region]]) -> 55.3 | L19: =SUMIFS(P_el[Capacity], P_el[Type], L$15, P_el[Region 1], P_el_2[[#This Row],[Region]]) -> 402 | M19: =SUMIFS(P_el[Capacity], P_el[Type], M$15, P_el[Region 1], P_el_2[[#This Row],[Region]]) -> 0 | N19: =SUM(P_el_2[[#This Row],[Nuclear]:[Thermal]]) -> 457.3 | Q19: Plant register | R19: DE 2035 | V19: Röyttä, Tornion tehtaat, 11 generaattoria | W19: 16 | AF19: South West | AG19: 0 | AH19: =K42/$K$45*$R$5 -> 750.57935 | AI19: =K42/SUM($K$38,$K$39,$K$42)*R$6 -> 63.826772 | AK19: =L42-AJ19 -> 443.1 | AL19: =AB53/$AB$56*$R$4 -> 2762.8604 | AM19: =SUM(AG19:AL19) -> 4020.3665
A20: Loviisa Y1 | B20: Loviisa I | C20: Nuclear | D20: 507 | E20: Uusimaa | G20: [1] | I20: Pirkanmaa | J20: =SUMIFS(P_el[Capacity], P_el[Type], J$15, P_el[Region 1], P_el_2[[#This Row],[Region]]) -> 0 | K20: =SUMIFS(P_el[Capacity], P_el[Type], K$15, P_el[Region 1], P_el_2[[#This Row],[Region]]) -> 20.1 | L20: =SUMIFS(P_el[Capacity], P_el[Type], L$15, P_el[Region 1], P_el_2[[#This Row],[Region]]) -> 7 | M20: =SUMIFS(P_el[Capacity], P_el[Type], M$15, P_el[Region 1], P_el_2[[#This Row],[Region]]) -> 4.6 | N20: =SUM(P_el_2[[#This Row],[Nuclear]:[Thermal]]) -> 27.1 | P20: Nuclear | Q20: =J45 -> 4369 | R20: =R8 -> 3250 | V20: Sopenkorpi | W20: 14.5 | AF20: South East | AG20: 0 | AH20: =K43/$K$45*$R$5 -> 263.79742 | AI20: 0 | AK20: =L43-AJ20 -> 17.2 | AL20: =AB54/$AB$56*$R$4 -> 3283.0254 | AM20: =SUM(AG20:AL20) -> 3564.0228
A21: Loviisa Y2 | B21: Loviisa 2 | C21: Nuclear | D21: 507 | E21: Uusimaa | G21: [1] | I21: Päijät-Häme | J21: =SUMIFS(P_el[Capacity], P_el[Type], J$15, P_el[Region 1], P_el_2[[#This Row],[Region]]) -> 0 | K21: =SUMIFS(P_el[Capacity], P_el[Type], K$15, P_el[Region 1], P_el_2[[#This Row],[Region]]) -> 19.8 | L21: =SUMIFS(P_el[Capacity], P_el[Type], L$15, P_el[Region 1], P_el_2[[#This Row],[Region]]) -> 14.5 | M21: =SUMIFS(P_el[Capacity], P_el[Type], M$15, P_el[Region 1], P_el_2[[#This Row],[Region]]) -> 2.31 | N21: =SUM(P_el_2[[#This Row],[Nuclear]:[Thermal]]) -> 34.3 | P21: Wind | Q21: =K45 -> 8509.56 | R21: =R5+R6 -> 49600 | V21: Wärtsilä tehdas | W21: 10.4 | AF21: Uusimaa | AG21: 0 | AH21: =K44/$K$45*$R$5 -> 144.0615 | AI21: 0 | AK21: =L44-AJ21 -> 226.25 | AL21: =AB55/$AB$56*$R$4 -> 1747.3002 | AM21: =SUM(AG21:AL21) -> 2117.6117
A22: Pjelax-tuulipuisto | B22: Riksåtten 664, 64200 Närpes | C22: Wind | D22: 380 | E22: Ostrobothnia | G22: [3] | I22: Kymenlaakso | J22: =SUMIFS(P_el[Capacity], P_el[Type], J$15, P_el[Region 1], P_el_2[[#This Row],[Region]]) -> 0 | K22: =SUMIFS(P_el[Capacity], P_el[Type], K$15, P_el[Region 1], P_el_2[[#This Row],[Region]]) -> 8 | L22: =SUMIFS(P_el[Capacity], P_el[Type], L$15, P_el[Region 1], P_el_2[[#This Row],[Region]]) -> 2.7 | M22: =SUMIFS(P_el[Capacity], P_el[Type], M$15, P_el[Region 1], P_el_2[[#This Row],[Region]]) -> 0 | N22: =SUM(P_el_2[[#This Row],[Nuclear]:[Thermal]]) -> 10.7 | P22: Thermal | Q22: =L45 -> 1826.35 | R22: =SUM(R9:R13) -> 1927 | V22: Kankaanpää | W22: 7 | AF22: Finland | AG22: 0 | AH22: =SUM(AH15:AH21) -> 46000 | AI22: =SUM(AI15:AI21) -> 3600 | AJ22: =SUM(AJ15:AJ21) -> 625 | AK22: =SUM(AK15:AK21) -> 1201.35 | AL22: =SUM(AL15:AL21) -> 21270 | AM22: =SUM(AM15:AM21) -> 76051.35
A23: Forssa kt | B23: Varavoimalantie 6, 30420 Forssa | C23: Thermal | D23: 352 | E23: Kanta-Häme | G23: [3] | I23: South Karelia | J23: =SUMIFS(P_el[Capacity], P_el[Type], J$15, P_el[Region 1], P_el_2[[#This Row],[Region]]) -> 0 | K23: =SUMIFS(P_el[Capacity], P_el[Type], K$15, P_el[Region 1], P_el_2[[#This Row],[Region]]) -> 21 | L23: =SUMIFS(P_el[Capacity], P_el[Type], L$15, P_el[Region 1], P_el_2[[#This Row],[Region]]) -> 0 | M23: =SUMIFS(P_el[Capacity], P_el[Type], M$15, P_el[Region 1], P_el_2[[#This Row],[Region]]) -> 0 | N23: =SUM(P_el_2[[#This Row],[Nuclear]:[Thermal]]) -> 21 | P23: Solar | Q23: =M45 -> 133.02 | R23: =R4 -> 21270 | V23: Harjavalta | W23: 6.3
A24: Lappfjärdin tuulipuisto | B24: Kristiinankaupunki | C24: Wind | D24: 241.8 | E24: Ostrobothnia | G24: [1] | I24: South Savo | J24: =SUMIFS(P_el[Capacity], P_el[Type], J$15, P_el[Region 1], P_el_2[[#This Row],[Region]]) -> 0 | K24: =SUMIFS(P_el[Capacity], P_el[Type], K$15, P_el[Region 1], P_el_2[[#This Row],[Region]]) -> 0 | L24: =SUMIFS(P_el[Capacity], P_el[Type], L$15, P_el[Region 1], P_el_2[[#This Row],[Region]]) -> 0 | M24: =SUMIFS(P_el[Capacity], P_el[Type], M$15, P_el[Region 1], P_el_2[[#This Row],[Region]]) -> 12.08 | N24: =SUM(P_el_2[[#This Row],[Nuclear]:[Thermal]]) -> 0 | V24: Waskiluoto Validation Center | W24: 5.5
A25: Karhukankaan ja Navettakankaan tuulipuisto, Siikajoki | B25: Karhukankaan ja Navettakankaan tuulipuisto, Siikajoki | C25: Wind | D25: 235.6 | E25: North Ostrobothnia | G25: [1] | I25: North Savo | J25: =SUMIFS(P_el[Capacity], P_el[Type], J$15, P_el[Region 1], P_el_2[[#This Row],[Region]]) -> 0 | K25: =SUMIFS(P_el[Capacity], P_el[Type], K$15, P_el[Region 1], P_el_2[[#This Row],[Region]]) -> 10.5 | L25: =SUMIFS(P_el[Capacity], P_el[Type], L$15, P_el[Region 1], P_el_2[[#This Row],[Region]]) -> 181.1 | M25: =SUMIFS(P_el[Capacity], P_el[Type], M$15, P_el[Region 1], P_el_2[[#This Row],[Region]]) -> 4.9 | N25: =SUM(P_el_2[[#This Row],[Nuclear]:[Thermal]]) -> 191.6 | V25: Ruusutarhat | W25: 2.7
A26: Piiparinmäen tuulipuisto | B26: Piiparinmäki, Pyhäntä/Kajaani. Piiparinmäen tuulipuisto | C26: Wind | D26: 211.4 | E26: North Ostrobothnia | F26: Kainuu | G26: [1] | I26: North Karelia | J26: =SUMIFS(P_el[Capacity], P_el[Type], J$15, P_el[Region 1], P_el_2[[#This Row],[Region]]) -> 0 | K26: =SUMIFS(P_el[Capacity], P_el[Type], K$15, P_el[Region 1], P_el_2[[#This Row],[Region]]) -> 0 | L26: =SUMIFS(P_el[Capacity], P_el[Type], L$15, P_el[Region 1], P_el_2[[#This Row],[Region]]) -> 0 | M26: =SUMIFS(P_el[Capacity], P_el[Type], M$15, P_el[Region 1], P_el_2[[#This Row],[Region]]) -> 0 | N26: =SUM(P_el_2[[#This Row],[Nuclear]:[Thermal]]) -> 0 | V26: Sänkiaho | W26: 2.1 | AA26: Region | AB26: Regional | AC26: Regional% | AD26: National
A27: Mutkalampi tuulipuisto north | B27: Kannus/Kalajoki | C27: Wind | D27: 203.8 | E27: North Ostrobothnia | F27: Central Ostrobothnia | G27: [1] | I27: Central Finland | J27: =SUMIFS(P_el[Capacity], P_el[Type], J$15, P_el[Region 1], P_el_2[[#This Row],[Region]]) -> 0 | K27: =SUMIFS(P_el[Capacity], P_el[Type], K$15, P_el[Region 1], P_el_2[[#This Row],[Region]]) -> 350.7 | L27: =SUMIFS(P_el[Capacity], P_el[Type], L$15, P_el[Region 1], P_el_2[[#This Row],[Region]]) -> 0 | M27: =SUMIFS(P_el[Capacity], P_el[Type], M$15, P_el[Region 1], P_el_2[[#This Row],[Region]]) -> 0 | N27: =SUM(P_el_2[[#This Row],[Nuclear]:[Thermal]]) -> 350.7 | V27: Hoikankangas, Kajaanin sähkölaitos | W27: 1.5 | AA27: Uusimaa | AB27: 1693 | AC27: 0.08 | AD27: =AB27/AC27 -> 21162.5
A28: Mutkalampi tuulipuisto south | B28: Kannus/Kalajoki | C28: Wind | D28: 200 | E28: North Ostrobothnia | F28: Central Ostrobothnia | G28: [1] | I28: South Ostrobothnia | J28: =SUMIFS(P_el[Capacity], P_el[Type], J$15, P_el[Region 1], P_el_2[[#This Row],[Region]]) -> 0 | K28: =SUMIFS(P_el[Capacity], P_el[Type], K$15, P_el[Region 1], P_el_2[[#This Row],[Region]]) -> 1209.91 | L28: =SUMIFS(P_el[Capacity], P_el[Type], L$15, P_el[Region 1], P_el_2[[#This Row],[Region]]) -> 1 | M28: =SUMIFS(P_el[Capacity], P_el[Type], M$15, P_el[Region 1], P_el_2[[#This Row],[Region]]) -> 44.2 | N28: =SUM(P_el_2[[#This Row],[Nuclear]:[Thermal]]) -> 1210.91 | V28: Lestijärvi | W28: 1.3 | AA28: Southwest Finland | AB28: 1542 | AC28: 0.07 | AD28: =AB28/AC28 -> 22028.571
A29: Karhunnevankankaan tuulipuisto | B29: Karhunnevankankaan tuulipuisto | C29: Wind | D29: 188.1 | E29: North Ostrobothnia | G29: [2] | I29: Ostrobothnia | J29: =SUMIFS(P_el[Capacity], P_el[Type], J$15, P_el[Region 1], P_el_2[[#This Row],[Region]]) -> 0 | K29: =SUMIFS(P_el[Capacity], P_el[Type], K$15, P_el[Region 1], P_el_2[[#This Row],[Region]]) -> 1587.2 | L29: =SUMIFS(P_el[Capacity], P_el[Type], L$15, P_el[Region 1], P_el_2[[#This Row],[Region]]) -> 101.9 | M29: =SUMIFS(P_el[Capacity], P_el[Type], M$15, P_el[Region 1], P_el_2[[#This Row],[Region]]) -> 3.6 | N29: =SUM(P_el_2[[#This Row],[Nuclear]:[Thermal]]) -> 1689.1 | V29: Kantvik | W29: 1.25 | AA29: Satakunta | AB29: 3546 | AC29: 0.17 | AD29: =AB29/AC29 -> 20858.824
A30: Huutokoski kt | B30: Huutokoski kt 1, 2, 3, 4, 5, 6 | C30: Thermal | D30: 180 | E30: North Savo | G30: [3] | I30: Central Ostrobothnia | J30: =SUMIFS(P_el[Capacity], P_el[Type], J$15, P_el[Region 1], P_el_2[[#This Row],[Region]]) -> 0 | K30: =SUMIFS(P_el[Capacity], P_el[Type], K$15, P_el[Region 1], P_el_2[[#This Row],[Region]]) -> 255.6 | L30: =SUMIFS(P_el[Capacity], P_el[Type], L$15, P_el[Region 1], P_el_2[[#This Row],[Region]]) -> 1.3 | M30: =SUMIFS(P_el[Capacity], P_el[Type], M$15, P_el[Region 1], P_el_2[[#This Row],[Region]]) -> 4 | N30: =SUM(P_el_2[[#This Row],[Nuclear]:[Thermal]]) -> 256.9 | V30: Koskensaari | W30: 1.2 | AA30: Kanta-Häme | AB30: 1135 | AC30: 0.05 | AD30: =AB30/AC30 -> 22700
A31: Kalistanneva, Kurikka | B31: Kalistantie 11, 66300 Kurikka | C31: Wind | D31: 158.65 | E31: South Ostrobothnia | G31: [1] | I31: North Ostrobothnia | J31: =SUMIFS(P_el[Capacity], P_el[Type], J$15, P_el[Region 1], P_el_2[[#This Row],[Region]]) -> 0 | K31: =SUMIFS(P_el[Capacity], P_el[Type], K$15, P_el[Region 1], P_el_2[[#This Row],[Region]]) -> 3366.6 | L31: =SUMIFS(P_el[Capacity], P_el[Type], L$15, P_el[Region 1], P_el_2[[#This Row],[Region]]) -> 103.2 | M31: =SUMIFS(P_el[Capacity], P_el[Type], M$15, P_el[Region 1], P_el_2[[#This Row],[Region]]) -> 19.3 | N31: =SUM(P_el_2[[#This Row],[Nuclear]:[Thermal]]) -> 3469.8 | V31: Karvetti | W31: 1.1 | AA31: Pirkanmaa | AB31: =AC31*$AD$29 -> 208.58824 | AC31: 0.01
A32: Oulainen, Karahka | B32: Oulainen, Karahka | C32: Wind | D32: 153.4 | E32: North Ostrobothnia | G32: [1] | I32: Kainuu | J32: =SUMIFS(P_el[Capacity], P_el[Type], J$15, P_el[Region 1], P_el_2[[#This Row],[Region]]) -> 0 | K32: =SUMIFS(P_el[Capacity], P_el[Type], K$15, P_el[Region 1], P_el_2[[#This Row],[Region]]) -> 221.3 | L32: =SUMIFS(P_el[Capacity], P_el[Type], L$15, P_el[Region 1], P_el_2[[#This Row],[Region]]) -> 1.5 | M32: =SUMIFS(P_el[Capacity], P_el[Type], M$15, P_el[Region 1], P_el_2[[#This Row],[Region]]) -> 0 | N32: =SUM(P_el_2[[#This Row],[Nuclear]:[Thermal]]) -> 222.8 | V32: Salahmin vesivoimalaitos | W32: 1.1 | AA32: Päijät-Häme | AB32: 791 | AC32: 0.04 | AD32: =AB32/AC32 -> 19775
A33: Sarvisuon tuulipuisto | B33: Simo Sarvisuon tuulipuisto (Pohjoispuolentie 33, 95200 Simo) | C33: Wind | D33: 151 | E33: Lapland | G33: [1] | I33: Lapland | J33: =SUMIFS(P_el[Capacity], P_el[Type], J$15, P_el[Region 1], P_el_2[[#This Row],[Region]]) -> 0 | K33: =SUMIFS(P_el[Capacity], P_el[Type], K$15, P_el[Region 1], P_el_2[[#This Row],[Region]]) -> 821.25 | L33: =SUMIFS(P_el[Capacity], P_el[Type], L$15, P_el[Region 1], P_el_2[[#This Row],[Region]]) -> 16.9 | M33: =SUMIFS(P_el[Capacity], P_el[Type], M$15, P_el[Region 1], P_el_2[[#This Row],[Region]]) -> 0 | N33: =SUM(P_el_2[[#This Row],[Nuclear]:[Thermal]]) -> 838.15 | V33: Mäkipää Diesel | W33: 1 | AA33: Kymenlaakso | AB33: 1090 | AC33: 0.05 | AD33: =AB33/AC33 -> 21800
A34: Matkussaari, Kurikka | B34: Kauhajoentie 610, Kurikka | C34: Wind | D34: 148.5 | E34: South Ostrobothnia | G34: [1] | J34: =SUM(P_el_2[Nuclear]) -> 4369 | K34: =SUM(P_el_2[Wind]) -> 8509.56 | L34: =SUM(P_el_2[Thermal]) -> 1826.35 | M34: =SUM(P_el_2[Solar]) -> 133.02 | V34: Sodankylän varuskunta | W34: 0.9 | AA34: South Karelia | AB34: 1300 | AC34: 0.06 | AD34: =AB34/AC34 -> 21666.667
A35: Louhukangas | B35: Louhukangas | C35: Wind | D35: 142.6 | E35: South Ostrobothnia | G35: [3] | V35: Savela | W35: 0 | AA35: South Savo | AB35: =AC35*$AD$29 -> 834.35294 | AC35: 0.04
A36: Metsälamminkankaan tuulipuisto | B36: Metsälamminkangas / Vaalan kunta | C36: Wind | D36: 132 | E36: North Ostrobothnia | G36: [3] | I36: Aggregated by model region and unit type | V36: Total | W36: =SUM(W6:W35) -> 1826.35 | AA36: North Savo | AB36: 1345 | AC36: 0.07 | AD36: =AB36/AC36 -> 19214.286
A37: Isonevan tuulipuisto | B37: Isonevan tuulipuisto | C37: Wind | D37: 126 | E37: North Ostrobothnia | G37: [3] | I37: Region | J37: Nuclear | K37: Wind | L37: Thermal | M37: Solar | N37: Total | V37: Total >50MW | W37: =SUM(W6:W15) -> 1659.5 | X37: =W37/W36 -> 0.90864292 | AA37: North Karelia | AB37: =AC37*$AD$29 -> 417.17647 | AC37: 0.02
A38: Murtotuulen tuulipuisto | B38: Murtotuulen tuulipuisto | C38: Wind | D38: 126 | E38: Lapland | G38: [2] | I38: North | J38: {=SUM(_xlfn._xlws.FILTER(P_el_2[Nuclear],ISNUMBER(MATCH(P_el_2[Region],_xlfn._xlws.FILTER(Region[Administrative],Region[Model]=P_el_3[[#This Row],[Region]]),0))))} -> 0 | K38: {=SUM(_xlfn._xlws.FILTER(P_el_2[Wind],ISNUMBER(MATCH(P_el_2[Region],_xlfn._xlws.FILTER(Region[Administrative],Region[Model]=P_el_3[[#This Row],[Region]]),0))))} -> 4187.85 | L38: {=SUM(_xlfn._xlws.FILTER(P_el_2[Thermal],ISNUMBER(MATCH(P_el_2[Region],_xlfn._xlws.FILTER(Region[Administrative],Region[Model]=P_el_3[[#This Row],[Region]]),0))))} -> 120.1 | M38: {=SUM(_xlfn._xlws.FILTER(P_el_2[Solar],ISNUMBER(MATCH(P_el_2[Region],_xlfn._xlws.FILTER(Region[Administrative],Region[Model]=P_el_3[[#This Row],[Region]]),0))))} -> 19.3 | N38: =SUM(P_el_3[[#This Row],[Nuclear]:[Thermal]]) -> 4307.95 | AA38: Central Finland | AB38: =AC38*$AD$29 -> 417.17647 | AC38: 0.02
A39: Kellosaari | B39: Kellosaari | C39: Thermal | D39: 118 | E39: Uusimaa | G39: [2] | I39: West | J39: {=SUM(_xlfn._xlws.FILTER(P_el_2[Nuclear],ISNUMBER(MATCH(P_el_2[Region],_xlfn._xlws.FILTER(Region[Administrative],Region[Model]=P_el_3[[#This Row],[Region]]),0))))} -> 3355 | K39: {=SUM(_xlfn._xlws.FILTER(P_el_2[Wind],ISNUMBER(MATCH(P_el_2[Region],_xlfn._xlws.FILTER(Region[Administrative],Region[Model]=P_el_3[[#This Row],[Region]]),0))))} -> 3504.81 | L39: {=SUM(_xlfn._xlws.FILTER(P_el_2[Thermal],ISNUMBER(MATCH(P_el_2[Region],_xlfn._xlws.FILTER(Region[Administrative],Region[Model]=P_el_3[[#This Row],[Region]]),0))))} -> 830.1 | M39: {=SUM(_xlfn._xlws.FILTER(P_el_2[Solar],ISNUMBER(MATCH(P_el_2[Region],_xlfn._xlws.FILTER(Region[Administrative],Region[Model]=P_el_3[[#This Row],[Region]]),0))))} -> 79.5 | N39: =SUM(P_el_3[[#This Row],[Nuclear]:[Thermal]]) -> 7689.91 | AA39: South Ostrobothnia | AB39: 3036 | AC39: 0.15 | AD39: =AB39/AC39 -> 20240
A40: Paskoonharju 2 | B40: Paskoonharju 2 | C40: Wind | D40: 117.6 | E40: South Ostrobothnia | G40: [3] | I40: Center | J40: {=SUM(_xlfn._xlws.FILTER(P_el_2[Nuclear],ISNUMBER(MATCH(P_el_2[Region],_xlfn._xlws.FILTER(Region[Administrative],Region[Model]=P_el_3[[#This Row],[Region]]),0))))} -> 0 | K40: {=SUM(_xlfn._xlws.FILTER(P_el_2[Wind],ISNUMBER(MATCH(P_el_2[Region],_xlfn._xlws.FILTER(Region[Administrative],Region[Model]=P_el_3[[#This Row],[Region]]),0))))} -> 370.8 | L40: {=SUM(_xlfn._xlws.FILTER(P_el_2[Thermal],ISNUMBER(MATCH(P_el_2[Region],_xlfn._xlws.FILTER(Region[Administrative],Region[Model]=P_el_3[[#This Row],[Region]]),0))))} -> 7 | M40: {=SUM(_xlfn._xlws.FILTER(P_el_2[Solar],ISNUMBER(MATCH(P_el_2[Region],_xlfn._xlws.FILTER(Region[Administrative],Region[Model]=P_el_3[[#This Row],[Region]]),0))))} -> 4.6 | N40: =SUM(P_el_3[[#This Row],[Nuclear]:[Thermal]]) -> 377.8 | AA40: Ostrobothnia | AB40: =AC40*$AD$29 -> 417.17647 | AC40: 0.02
A41: Metsälän tuulivoimapuisto | B41: Metsälän tuulivoimapuisto | C41: Wind | D41: 117.3 | E41: Ostrobothnia | G41: [3] | I41: East | J41: {=SUM(_xlfn._xlws.FILTER(P_el_2[Nuclear],ISNUMBER(MATCH(P_el_2[Region],_xlfn._xlws.FILTER(Region[Administrative],Region[Model]=P_el_3[[#This Row],[Region]]),0))))} -> 0 | K41: {=SUM(_xlfn._xlws.FILTER(P_el_2[Wind],ISNUMBER(MATCH(P_el_2[Region],_xlfn._xlws.FILTER(Region[Administrative],Region[Model]=P_el_3[[#This Row],[Region]]),0))))} -> 231.8 | L41: {=SUM(_xlfn._xlws.FILTER(P_el_2[Thermal],ISNUMBER(MATCH(P_el_2[Region],_xlfn._xlws.FILTER(Region[Administrative],Region[Model]=P_el_3[[#This Row],[Region]]),0))))} -> 182.6 | M41: {=SUM(_xlfn._xlws.FILTER(P_el_2[Solar],ISNUMBER(MATCH(P_el_2[Region],_xlfn._xlws.FILTER(Region[Administrative],Region[Model]=P_el_3[[#This Row],[Region]]),0))))} -> 16.98 | N41: =SUM(P_el_3[[#This Row],[Nuclear]:[Thermal]]) -> 414.4 | AA41: Central Ostrobothnia | AB41: =AC41*$AD$29 -> 625.76471 | AC41: 0.03
A42: Storbötet | B42: Storbötet Vind, Lillbötesvägen, Uusikaarlepyy 66840 | C42: Wind | D42: 105.4 | E42: Ostrobothnia | G42: [1] | I42: South West | J42: {=SUM(_xlfn._xlws.FILTER(P_el_2[Nuclear],ISNUMBER(MATCH(P_el_2[Region],_xlfn._xlws.FILTER(Region[Administrative],Region[Model]=P_el_3[[#This Row],[Region]]),0))))} -> 0 | K42: {=SUM(_xlfn._xlws.FILTER(P_el_2[Wind],ISNUMBER(MATCH(P_el_2[Region],_xlfn._xlws.FILTER(Region[Administrative],Region[Model]=P_el_3[[#This Row],[Region]]),0))))} -> 138.85 | L42: {=SUM(_xlfn._xlws.FILTER(P_el_2[Thermal],ISNUMBER(MATCH(P_el_2[Region],_xlfn._xlws.FILTER(Region[Administrative],Region[Model]=P_el_3[[#This Row],[Region]]),0))))} -> 443.1 | M42: {=SUM(_xlfn._xlws.FILTER(P_el_2[Solar],ISNUMBER(MATCH(P_el_2[Region],_xlfn._xlws.FILTER(Region[Administrative],Region[Model]=P_el_3[[#This Row],[Region]]),0))))} -> 0 | N42: =SUM(P_el_3[[#This Row],[Nuclear]:[Thermal]]) -> 581.95 | AA42: North Ostrobothnia | AB42: 1585 | AC42: 0.08 | AD42: =AB42/AC42 -> 19812.5
A43: Välikankaan tuulipuisto | B43: Haapajärvi Välikangas | C43: Wind | D43: 103.2 | E43: North Ostrobothnia | G43: [3] | I43: South East | J43: {=SUM(_xlfn._xlws.FILTER(P_el_2[Nuclear],ISNUMBER(MATCH(P_el_2[Region],_xlfn._xlws.FILTER(Region[Administrative],Region[Model]=P_el_3[[#This Row],[Region]]),0))))} -> 0 | K43: {=SUM(_xlfn._xlws.FILTER(P_el_2[Wind],ISNUMBER(MATCH(P_el_2[Region],_xlfn._xlws.FILTER(Region[Administrative],Region[Model]=P_el_3[[#This Row],[Region]]),0))))} -> 48.8 | L43: {=SUM(_xlfn._xlws.FILTER(P_el_2[Thermal],ISNUMBER(MATCH(P_el_2[Region],_xlfn._xlws.FILTER(Region[Administrative],Region[Model]=P_el_3[[#This Row],[Region]]),0))))} -> 17.2 | M43: {=SUM(_xlfn._xlws.FILTER(P_el_2[Solar],ISNUMBER(MATCH(P_el_2[Region],_xlfn._xlws.FILTER(Region[Administrative],Region[Model]=P_el_3[[#This Row],[Region]]),0))))} -> 2.31 | N43: =SUM(P_el_3[[#This Row],[Nuclear]:[Thermal]]) -> 66 | AA43: Kainuu | AB43: =AC43*$AD$29 -> 208.58824 | AC43: 0.01
A44: Mertaniemi 1 ja 2 | B44: Mertaniemi 2 | C44: Thermal | D44: 102 | E44: North Ostrobothnia | G44: [3] | I44: Uusimaa | J44: {=SUM(_xlfn._xlws.FILTER(P_el_2[Nuclear],ISNUMBER(MATCH(P_el_2[Region],_xlfn._xlws.FILTER(Region[Administrative],Region[Model]=P_el_3[[#This Row],[Region]]),0))))} -> 1014 | K44: {=SUM(_xlfn._xlws.FILTER(P_el_2[Wind],ISNUMBER(MATCH(P_el_2[Region],_xlfn._xlws.FILTER(Region[Administrative],Region[Model]=P_el_3[[#This Row],[Region]]),0))))} -> 26.65 | L44: {=SUM(_xlfn._xlws.FILTER(P_el_2[Thermal],ISNUMBER(MATCH(P_el_2[Region],_xlfn._xlws.FILTER(Region[Administrative],Region[Model]=P_el_3[[#This Row],[Region]]),0))))} -> 226.25 | M44: {=SUM(_xlfn._xlws.FILTER(P_el_2[Solar],ISNUMBER(MATCH(P_el_2[Region],_xlfn._xlws.FILTER(Region[Administrative],Region[Model]=P_el_3[[#This Row],[Region]]),0))))} -> 10.33 | N44: =SUM(P_el_3[[#This Row],[Nuclear]:[Thermal]]) -> 1266.9 | AA44: Lapland | AB44: =AC44*$AD$29 -> 417.17647 | AC44: 0.02
A45: Norrskogenin tuulipuisto | B45: Norrskogen | C45: Wind | D45: 102 | E45: Ostrobothnia | G45: [3] | J45: =SUM(P_el_3[Nuclear]) -> 4369 | K45: =SUM(P_el_3[Wind]) -> 8509.56 | L45: =SUM(P_el_3[Thermal]) -> 1826.35 | M45: =SUM(P_el_3[Solar]) -> 133.02 | N45: =SUM(N38:N44) -> 14704.91 | AB45: =SUM(AB27:AB44) -> 20609
A46: Olkiluoto kt | B46: Olkiluoto KT 1 ja 2, Eurajoki | C46: Thermal | D46: 100.5 | E46: Satakunta | G46: [1]
A47: Nuolivaaran tuulipuisto | B47: Nuolivaaran tuulipuisto | C47: Wind | D47: 96.9 | E47: Lapland | G47: [3] | AA47: Aggregated by model region
A48: Murtomäen tuulipuisto | B48: Pyhäjärvi, Murtomäen tuulipuisto | C48: Wind | D48: 93 | E48: North Ostrobothnia | G48: [3] | AA48: Region | AB48: Capacity
A49: Oosinselkä, Pori, Eurajoki | B49: Oosinselän tuulipuisto, Eurajoki & Pori | C49: Wind | D49: 93 | E49: Satakunta | G49: [1] | AA49: North | AB49: {=SUM(_xlfn._xlws.FILTER(P_el_S5_1[Regional],ISNUMBER(MATCH(P_el_S5_1[Region],_xlfn._xlws.FILTER(Region[Administrative],Region[Model]=P_el_S5_2[[#This Row],[Region]]),0))))} -> 2002.1765
A50: Pahkakoski, Ii | B50: Pahkakoski | C50: Wind | D50: 93 | E50: North Ostrobothnia | G50: [3] | AA50: West | AB50: {=SUM(_xlfn._xlws.FILTER(P_el_S5_1[Regional],ISNUMBER(MATCH(P_el_S5_1[Region],_xlfn._xlws.FILTER(Region[Administrative],Region[Model]=P_el_S5_2[[#This Row],[Region]]),0))))} -> 7624.9412
A51: Alajoki-Peuralinna tuulipuisto | B51: Alajoki-Peuralinna tuulipuisto, Perho & Kyyjärvi | C51: Wind | D51: 92.4 | E51: Central Ostrobothnia | F51: Central Finland | G51: [3] | AA51: Center | AB51: {=SUM(_xlfn._xlws.FILTER(P_el_S5_1[Regional],ISNUMBER(MATCH(P_el_S5_1[Region],_xlfn._xlws.FILTER(Region[Administrative],Region[Model]=P_el_S5_2[[#This Row],[Region]]),0))))} -> 625.76471
A52: Mustilankangas | B52: Kalajoki Mustilankangas | C52: Wind | D52: 92.4 | E52: North Ostrobothnia | G52: [1] | AA52: East | AB52: {=SUM(_xlfn._xlws.FILTER(P_el_S5_1[Regional],ISNUMBER(MATCH(P_el_S5_1[Region],_xlfn._xlws.FILTER(Region[Administrative],Region[Model]=P_el_S5_2[[#This Row],[Region]]),0))))} -> 2805.1176
A53: Oltavan tuulipuisto | B53: Oltava Pyhäjoki | C53: Wind | D53: 91.2 | E53: North Ostrobothnia | G53: [1] | AA53: South West | AB53: {=SUM(_xlfn._xlws.FILTER(P_el_S5_1[Regional],ISNUMBER(MATCH(P_el_S5_1[Region],_xlfn._xlws.FILTER(Region[Administrative],Region[Model]=P_el_S5_2[[#This Row],[Region]]),0))))} -> 2677
A54: Kalax | B54: Råskogsvägen 390, Närpes | C54: Wind | D54: 90.3 | E54: Ostrobothnia | G54: [2] | AA54: South East | AB54: {=SUM(_xlfn._xlws.FILTER(P_el_S5_1[Regional],ISNUMBER(MATCH(P_el_S5_1[Region],_xlfn._xlws.FILTER(Region[Administrative],Region[Model]=P_el_S5_2[[#This Row],[Region]]),0))))} -> 3181
A55: Puskakorven tuulipuisto | B55: Puskakorpi, Pyhäjoki, Puskakorven tuulipuisto | C55: Wind | D55: 88 | E55: North Ostrobothnia | G55: [1] | AA55: Uusimaa | AB55: {=SUM(_xlfn._xlws.FILTER(P_el_S5_1[Regional],ISNUMBER(MATCH(P_el_S5_1[Region],_xlfn._xlws.FILTER(Region[Administrative],Region[Model]=P_el_S5_2[[#This Row],[Region]]),0))))} -> 1693
A56: Pajuperänkangas | B56: Pajuperänkangas | C56: Wind | D56: 86.8 | E56: North Ostrobothnia | G56: [3] | AB56: =SUM(P_el_S5_2[Capacity]) -> 20609
A57: Lakiakangas 3 | B57: Lakiakangas 3 | C57: Wind | D57: 86 | E57: South Ostrobothnia | G57: [3]
A58: Merkkikallion tuulipuisto | B58: Merkkikallio, Vaasa/Mustasaari | C58: Wind | D58: 82.5 | E58: Ostrobothnia | G58: [1]
A59: Oosinselkä, Eurajoki | B59: Eurojoki Oosinselkä tuulipuisto 1 | C59: Wind | D59: 80.6 | E59: Satakunta | G59: [3]
A60: Porvoo Tolkkinen | B60: Tolkkinen kt | C60: Thermal | D60: 80 | E60: Uusimaa | G60: [2]
A61: Kalajoki Läntinen | B61: Kalajoki Läntinen | C61: Wind | D61: 79.8 | E61: North Ostrobothnia | G61: [1]
A62: Hedet | B62: Närpiö, Hedet H1-H18 | C62: Wind | D62: 79 | E62: Ostrobothnia | G62: [1]
A63: Möksy | B63: Möksy | C63: Wind | D63: 78 | E63: South Ostrobothnia | G63: [3]
A64: Tolpanvaara | B64: Tolpanvaara, Pudasjärvi | C64: Wind | D64: 72 | E64: North Ostrobothnia | G64: [3]
A65: Palokangas, Ii | B65: Ii, Pohjois Pohjanmaa | C65: Wind | D65: 70.8 | E65: North Ostrobothnia | G65: [1]
A66: Mastokankaan tuulipuisto | B66: Mastokangas, Raahe/Siikajoki | C66: Wind | D66: 68.4 | E66: North Ostrobothnia | G66: [1]
A67: Kristiinankaupunki kt | B67: Kristiinankaupunki kt 1, 2 | C67: Thermal | D67: 60 | E67: Ostrobothnia | G67: [1]
A68: Kuuronkallion tuulipuisto | B68: Kuuronkallion tuulipuisto | C68: Wind | D68: 58.8 | E68: Central Ostrobothnia | G68: [3]
... A266: Mäkipää Diesel | B266: Mäkipää Diesel | C266: Thermal | D266: 1 | E266: South Ostrobothnia | G266: [3]
A267: Puulaakso | B267: Puulaakson Energia Oy Hongantie 93 | D267: 1 | E267: Central Finland | G267: [3]
A268: Pälkäne Pälkänvedentie | B268: Pälkäne Pälkänevedentie | C268: Solar | D268: 1 | E268: Pirkanmaa | G268: [3] | I268: =COUNTIF(P_el[Basis],"=[1]") -> 88
A269: Sodankylän varuskunta | B269: Sodankylän varuskunta | C269: Thermal | D269: 0.9 | E269: Lapland | G269: [1] | I269: =COUNTIF(P_el[Basis],"=[2]") -> 50
A270: Savela | B270: Savela | C270: Thermal | D270: 0 | E270: Central Finland | G270: [3] | I270: =COUNTIF(P_el[Basis],"=[3]") -> 117
E272: Count | F272: Capacity | G272: Capacity %
D273: Total | E273: =COUNT(D16:D270) -> 255 | F273: =SUM(D16:D270) -> 14838.93
D274: >10 MW | E274: =COUNT(D16:D187) -> 172 | F274: =SUM(D16:D187) -> 14506.05 | G274: =F274/$F$273 -> 0.97756712
D275: >20 MW | E275: =COUNT(D16:D158) -> 143 | F275: =SUM(D16:D158) -> 14088.65 | G275: =F275/$F$273 -> 0.9494384
D276: >50 MW | E276: =COUNT(D16:D78) -> 63 | F276: =SUM(D16:D78) -> 11477.65 | G276: =F276/$F$273 -> 0.77348232
D277: >100 MW | E277: =COUNT(D16:D46) -> 31 | F277: =SUM(D16:D46) -> 9130.85 | G277: =F277/$F$273 -> 0.61533075
D278: >200 MW | E278: =COUNT(D16:D28) -> 13 | F278: =SUM(D16:D28) -> 6758.6 | G278: =F278/$F$273 -> 0.45546411

Sheet P_hydro
A1: Data | B1: Hydropower powerplant subset from power plant register (latest update 27.6.2025)
A2: Source | B2: Delivery reliability | Energy Authority
A3: Selection | B3: Capacities are taken from column "Maximum, total, MW"
A4: Region search | B4: Regions were identified manually looking for specified location in google maps. In most but not all cases map search lead to visible identifiable hydro power plants.
B5: Due to large number of powerplants, search was limited to powerplants over 10 MW, representing 91% of total capacity. Two locations of minor powerplants above 10MW not found on google maps were also omitted.
B6: Multi-hour-long attempt was made to obtain regions automatically with Copilot, but at most 40% of powerplants were identified despite allocation of single site to multiple regions.
B7: Given partial and questionable quality list, I decided to dismiss AI generated list altogether.
A9: Powerplant register subset | D9: Region search
A10: Name | B10: Location | C10: Capacity | D10: Region | E10: Dam visible | G10: Region | H10: Capacity | J10: Region | K10: Capacity | N10: upwardLimit | P10: userconstraint
A11: Imatra | B11: Imatra | C11: 192 | D11: South Karelia | E11: Y | G11: Uusimaa | H11: =SUMIF($D$11:$D$69, G11, $C$11:$C$69) -> 0 | J11: North | K11: {=SUM(_xlfn._xlws.FILTER(P_hydro_2[Capacity],ISNUMBER(MATCH(P_hydro_2[Region],_xlfn._xlws.FILTER(Region[Administrative],Region[Model]=P_hydro_3[[#This Row],[Region]]),0))))} -> 1767 | L11: =P_hydro_3[[#This Row],[Capacity]]/$K$19 -> 0.60026497 | N11: =$N$18*L11 -> 3319465.3 | P11: =$P$18*L11 -> 250.91076
A12: Petäjäskoski | B12: Petäjäskoski | C12: 169 | D12: North Ostrobothnia | E12: N | G12: Southwest Finland | H12: =SUMIF($D$11:$D$69, G12, $C$11:$C$69) -> 14 | J12: West | K12: {=SUM(_xlfn._xlws.FILTER(P_hydro_2[Capacity],ISNUMBER(MATCH(P_hydro_2[Region],_xlfn._xlws.FILTER(Region[Administrative],Region[Model]=P_hydro_3[[#This Row],[Region]]),0))))} -> 150 | L12: =P_hydro_3[[#This Row],[Capacity]]/$K$19 -> 0.05095628 | N12: =$N$18*L12 -> 281788.23 | P12: =$P$18*L12 -> 21.299725
A13: Pyhäkoski | B13: Pyhäkoski | C13: 146 | D13: South Savo | E13: N | G13: Satakunta | H13: =SUMIF($D$11:$D$69, G13, $C$11:$C$69) -> 150 | J13: Center | K13: {=SUM(_xlfn._xlws.FILTER(P_hydro_2[Capacity],ISNUMBER(MATCH(P_hydro_2[Region],_xlfn._xlws.FILTER(Region[Administrative],Region[Model]=P_hydro_3[[#This Row],[Region]]),0))))} -> 116.1 | L13: =P_hydro_3[[#This Row],[Capacity]]/$K$19 -> 0.03944016 | N13: =$N$18*L13 -> 218104.09 | P13: =$P$18*L13 -> 16.485987
A14: Seitakorva | B14: Seitakorva | C14: 142.5 | D14: Lapland | E14: Y | G14: Kanta-Häme | H14: =SUMIF($D$11:$D$69, G14, $C$11:$C$69) -> 0 | J14: East | K14: {=SUM(_xlfn._xlws.FILTER(P_hydro_2[Capacity],ISNUMBER(MATCH(P_hydro_2[Region],_xlfn._xlws.FILTER(Region[Administrative],Region[Model]=P_hydro_3[[#This Row],[Region]]),0))))} -> 457.9 | L14: =P_hydro_3[[#This Row],[Capacity]]/$K$19 -> 0.15555254 | N14: =$N$18*L14 -> 860205.52 | P14: =$P$18*L14 -> 65.02096
A15: Pirttikoski | B15: Pirttikoski | C15: 141 | D15: Lapland | E15: Y | G15: Pirkanmaa | H15: =SUMIF($D$11:$D$69, G15, $C$11:$C$69) -> 116.1 | J15: South West | K15: {=SUM(_xlfn._xlws.FILTER(P_hydro_2[Capacity],ISNUMBER(MATCH(P_hydro_2[Region],_xlfn._xlws.FILTER(Region[Administrative],Region[Model]=P_hydro_3[[#This Row],[Region]]),0))))} -> 14
A16: Taivalkoski | B16: Taivalkoski | C16: 133.2 | D16: North Ostrobothnia | E16: N | G16: Päijät-Häme | H16: =SUMIF($D$11:$D$69, G16, $C$11:$C$69) -> 30 | J16: South East | K16: {=SUM(_xlfn._xlws.FILTER(P_hydro_2[Capacity],ISNUMBER(MATCH(P_hydro_2[Region],_xlfn._xlws.FILTER(Region[Administrative],Region[Model]=P_hydro_3[[#This Row],[Region]]),0))))} -> 452.7 | L16: =P_hydro_3[[#This Row],[Capacity]]/$K$19 -> 0.15378605 | N16: =$N$18*L16 -> 850436.87 | P16: =$P$18*L16 -> 64.28257
A17: Ossauskoski | B17: Ossauskoski | C17: 120 | D17: Lapland | E17: Y | G17: Kymenlaakso | H17: =SUMIF($D$11:$D$69, G17, $C$11:$C$69) -> 165.2 | J17: Uusimaa | K17: {=SUM(_xlfn._xlws.FILTER(P_hydro_2[Capacity],ISNUMBER(MATCH(P_hydro_2[Region],_xlfn._xlws.FILTER(Region[Administrative],Region[Model]=P_hydro_3[[#This Row],[Region]]),0))))} -> 0
A18: Isohaara | B18: isohaara | C18: 106 | D18: Lapland | E18: N | G18: South Karelia | H18: =SUMIF($D$11:$D$69, G18, $C$11:$C$69) -> 257.5 | K18: =SUM(P_hydro_3[Capacity]) -> 2957.7 | N18: =5530000 -> 5530000 | P18: 418
A19: Harjavalta | B19: Harjavallan voimalaitos | C19: 105 | D19: Satakunta | E19: Y | G19: South Savo | H19: =SUMIF($D$11:$D$69, G19, $C$11:$C$69) -> 146 | K19: =SUM(K11:K14,K16) -> 2943.7
A20: Vanttauskoski | B20: Vanttauskoski | C20: 94.4 | D20: Lapland | E20: Y | G20: North Savo | H20: =SUMIF($D$11:$D$69, G20, $C$11:$C$69) -> 68.8
A21: Valajaskoski | B21: Valajaskoski | C21: 92 | D21: Lapland | E21: Y | G21: North Karelia | H21: =SUMIF($D$11:$D$69, G21, $C$11:$C$69) -> 169.4
A22: Nuojua | B22: Nuojua | C22: 85.2 | D22: North Ostrobothnia | E22: Y | G22: Central Finland | H22: =SUMIF($D$11:$D$69, G22, $C$11:$C$69) -> 0
A23: Pamilo | B23: Pamilon vesivoimalaitos | C23: 85 | D23: North Karelia | E23: Y | G23: South Ostrobothnia | H23: =SUMIF($D$11:$D$69, G23, $C$11:$C$69) -> 0
A24: Melo | B24: melo | C24: 70 | D24: Pirkanmaa | E24: Y | G24: Ostrobothnia | H24: =SUMIF($D$11:$D$69, G24, $C$11:$C$69) -> 0
A25: Tainionkoski | B25: Tainionkoski | C25: 65.5 | D25: South Karelia | E25: Y | G25: Central Ostrobothnia | H25: =SUMIF($D$11:$D$69, G25, $C$11:$C$69) -> 0
A26: Utanen | B26: Utanen | C26: 64.8 | D26: North Ostrobothnia | E26: Y | G26: North Ostrobothnia | H26: =SUMIF($D$11:$D$69, G26, $C$11:$C$69) -> 869.3
A27: Raasakka | B27: raasakka | C27: 60 | D27: North Ostrobothnia | E27: Y | G27: Kainuu | H27: =SUMIF($D$11:$D$69, G27, $C$11:$C$69) -> 73.7
A28: Pälli | B28: Pälli | C28: 58 | D28: North Ostrobothnia | E28: Y | G28: Lapland | H28: =SUMIF($D$11:$D$69, G28, $C$11:$C$69) -> 897.7
A29: Jylhämä | B29: Jylhämä | C29: 55 | D29: North Ostrobothnia | E29: Y | H29: =SUM(H11:H28) -> 2957.7
A30: Montta | B30: Montta | C30: 51 | D30: North Ostrobothnia | E30: Y
A31: Kolsi | B31: Kolsin voimalaitos Kokemäki | C31: 45 | D31: Satakunta | E31: Y
A32: Aittokoski | B32: Aittokoski | C32: 44.8 | D32: North Savo | E32: N
A33: Pahkakoski | B33: pahkakoski | C33: 42.1 | D33: North Ostrobothnia | E33: Y
A34: Merikoski | B34: Koskitie 30, Oulu, Merikosken voimalaitos | C34: 42 | D34: North Ostrobothnia | E34: Y
A35: Porttipahta | B35: Porttipahta | C35: 40 | D35: Lapland | E35: Y
A36: Maalismaa | B36: maalismaa | C36: 38.5 | D36: North Ostrobothnia | E36: Y
A37: Kierikki | B37: kierikki | C37: 38 | D37: North Ostrobothnia | E37: Y
A38: Seitenoikea | B38: Seitenoikea | C38: 37.9 | D38: Kainuu | E38: Y
A39: Haapakoski | B39: haapakoski | C39: 32.5 | D39: North Ostrobothnia | E39: Y
A40: Kaltimo | B40: Kaltimo | C40: 32 | D40: North Karelia | E40: Y
A41: Kuusankoski ve | B41: Kuusankoski | C41: 30 | D41: Kymenlaakso | E41: Y
... A63: Hämeenkyrö ve | B63: Kyröskoski | C63: 12.9 | D63: Pirkanmaa | E63: Y
A64: Kallioinen | B64: Kallioinen | C64: 12
A65: Katerma | B65: Katerma | C65: 11.5 | D65: Kainuu | E65: Y
A66: Portimokoski | B66: Portimokoski | C66: 11 | D66: Lapland | E66: Y
A67: Kelukoski | B67: Kelukoski | C67: 10.6 | D67: Lapland | E67: Y
A68: Matarakoski | B68: Matarakoski | C68: 10.1 | D68: Lapland | E68: Y
A69: Korkeakoski | B69: Korkeakosken voimalaitos Kotka | C69: 10 | D69: Kymenlaakso | E69: Y
A70: Vuolenkosken vesivoimalaitos | B70: Vuolenkosken vesivoimalaitos | C70: 9.5
A71: Voikkaa ve 1 | B71: Voikkaa 1 | C71: 8.9
A72: Tammerkoski | B72: Tammerkoski | C72: 8.6
A73: Hirvikoski | B73: Nurmo / Hirvikoski | C73: 8.5
A74: Kuhankoski | B74: Kuhankoski, Koskentie 76, 41340 Laukaa | C74: 8
A75: Kyrkösjärvi | B75: Kyrkösjärvi, Seinäjoki | C75: 7.8
A76: Kaitfors | B76: Kaitfors | C76: 7.6
A77: Myllykosken vesivoimalaitos 1 | B77: Myllykosken vesivoimalaitos 1 | C77: 6.9
A78: Puntarikoski | B78: Kontiolahti, Puntarikoski | C78: 6.9
A79: Hilmonkoski | B79: Kannonkoski / Hilmonkoski | C79: 6.8
A80: Palokki | B80: Heinävesi, Palokki | C80: 6.8
A81: Hietamankoski | B81: Äänekoski / Hietamankoski | C81: 6.7
... A147: Siuronkoski | B147: Siuronkoski, Nokia | C147: 0.7
A149: All | C149: =SUM(C11:C147) -> 3232.7
A150: >100 MW | C150: =SUM(C11:C19) -> 1254.7 | D150: =C150/$C$149 -> 0.38812757
A151: >50 MW | C151: =SUM(C11:C30) -> 2035.6 | D151: =C151/$C$149 -> 0.62969035
A152: >20MW | C152: =SUM(C11:C52) -> 2730.7 | D152: =C152/$C$149 -> 0.84471185
A153: >10 MW | C153: =SUM(C11:C69) -> 2969.7 | D153: =C153/$C$149 -> 0.91864386
A154: Mapped | C154: =C153-C64 -> 2957.7 | D154: =C154/$C$149 -> 0.91493179

Sheet P_ind_chp
A1: Source [1] | B1: Power plant register (latest update 27.6.2025) | F1: Delivery reliability | Energy Authority | N1: Source [2] | O1: Inputs of "H2 heavy" | S1: Flexible operation
A2: Selection | B2: Capacities are taken from column "Maximum, total, MW" | N2: Electric capacity | O2: Input | P2: Electric | Q2: Heat | S2: Ratios from H2 heavy
A3: Region search | B3: Performed manualy by looking at Finnish and English wikipedia and global energy monitor (www.gem.wiki) | N3: Other renewable | O3: 7056.6561 | P3: 2822.6624 | Q3: 4233.9937
N4: Other non-renewable | O4: 357.53724 | P4: 143.0149 | Q4: 214.52235
A5: Name | B5: Location | C5: Region | D5: Capacity | E5: Main fuel | F5: Standby fuel 1 | G5: Standby fuel 2 | H5: Unit type | J5: Unique fuel | K5: Renewable? | P5: =P3+P4 -> 2965.6773
A6: Äänekoski, Biotuotetehdas | B6: Äänekoski, Biotuotetehdas | C6: Central Finland | D6: 280 | E6: Black liquor and concentrated liquors | H6: =IF(ISNUMBER(MATCH(P_ind[[#This Row],[Main fuel]],$J$29:$J$42,0)),"RE","non-RE") -> RE | J6: Type identified manually based on fuel name
A7: Alholma AK 2 | B7: AK2 | C7: Ostrobothnia | D7: 240 | E7: Peat | F7: Hard coal and anthracite | G7: Industrial wood residues | H7: =IF(ISNUMBER(MATCH(P_ind[[#This Row],[Main fuel]],$J$29:$J$42,0)),"RE","non-RE") -> RE | J7: {=_xlfn.UNIQUE(_xlfn.TOCOL(P_ind[[Main fuel]:[Standby fuel 2]], 1))} -> Black liquor and concentrated liquors | K7: Y | N7: Heat to electric capacity ratio | P7: 1.61
A8: Kemin biotuotetehdas | B8: Kemi | C8: Lapland | D8: 228 | E8: Black liquor and concentrated liquors | F8: By-products from wood processing industry | H8: =IF(ISNUMBER(MATCH(P_ind[[#This Row],[Main fuel]],$J$29:$J$42,0)),"RE","non-RE") -> RE | K8: ? | N8: Fuel to electricity capacity ratio | P8: 0.4
A9: Anjalankoski | B9: Inkeroinen (Kouvola) | C9: Kymenlaakso | D9: 160.5 | E9: Industrial wood residues | H9: =IF(ISNUMBER(MATCH(P_ind[[#This Row],[Main fuel]],$J$29:$J$42,0)),"RE","non-RE") -> RE | J9: Peat | K9: ?
A10: Kaukopää | B10: Kaukopää | C10: South Karelia | D10: 134 | E10: Black liquor and concentrated liquors | F10: Industrial wood residues | G10: Natural gas | H10: =IF(ISNUMBER(MATCH(P_ind[[#This Row],[Main fuel]],$J$29:$J$42,0)),"RE","non-RE") -> RE | J10: Hard coal and anthracite | K10: N | N10: Hourly industrial heat demand in SW | P10: =D_heat!V8/0.00876 -> 72.651178
A11: Kirkniemi | B11: Kirkniemi, Kirkniemen voimalaitos | C11: Uusimaa | D11: 128 | E11: Natural gas | F11: Medium heavy distillates | H11: =IF(ISNUMBER(MATCH(P_ind[[#This Row],[Main fuel]],$J$29:$J$42,0)),"RE","non-RE") -> non-RE | J11: Industrial wood residues | K11: Y
A12: Oulu | B12: Oulu | C12: North Ostrobothnia | D12: 105 | E12: Black liquor and concentrated liquors | F12: Industrial wood residues | G12: Peat | H12: =IF(ISNUMBER(MATCH(P_ind[[#This Row],[Main fuel]],$J$29:$J$42,0)),"RE","non-RE") -> RE | J12: By-products from wood processing industry | K12: Y
A13: Uimaharju 2 + 1 vp/lv | B13: Uimaharjun voimalaitos | C13: North Karelia | D13: 105 | E13: Black liquor and concentrated liquors | F13: Industrial wood residues | G13: Heavy distillates | H13: =IF(ISNUMBER(MATCH(P_ind[[#This Row],[Main fuel]],$J$29:$J$42,0)),"RE","non-RE") -> RE | J13: Natural gas | K13: N | N13: Merging [1-2]
A14: Pietarsaari (TG6) | B14: Pietarsaari | C14: Ostrobothnia | D14: 95 | E14: Black liquor and concentrated liquors | F14: Heavy distillates | G14: Bioliquids | H14: =IF(ISNUMBER(MATCH(P_ind[[#This Row],[Main fuel]],$J$29:$J$42,0)),"RE","non-RE") -> RE | J14: Medium heavy distillates | K14: N | N14: Observable:
A15: Raahe | B15: Raahe | C15: North Ostrobothnia | D15: 94 | E15: Blast furnace gas | F15: Coke oven gas | G15: Natural gas | H15: =IF(ISNUMBER(MATCH(P_ind[[#This Row],[Main fuel]],$J$29:$J$42,0)),"RE","non-RE") -> RE | J15: Heavy distillates | K15: N | N15: Total changes little, but RE% increase
A16: Kymi | B16: Kuusankoski, Kouvola | C16: Kymenlaakso | D16: 87 | E16: Black liquor and concentrated liquors | F16: Natural gas | G16: Heavy distillates | H16: =IF(ISNUMBER(MATCH(P_ind[[#This Row],[Main fuel]],$J$29:$J$42,0)),"RE","non-RE") -> RE | J16: Bioliquids | K16: Y | N16: Expectation:
A17: Joutseno | B17: Metsä Fibre Joutsenon tehdas | C17: South Karelia | D17: 85 | E17: Black liquor and concentrated liquors | F17: Natural gas | H17: =IF(ISNUMBER(MATCH(P_ind[[#This Row],[Main fuel]],$J$29:$J$42,0)),"RE","non-RE") -> RE | J17: Blast furnace gas | K17: ? | N17: Industrial CHPs are either converted to or replaced by RE-burning units at the same sites to serve unchanged industrial heat demand
A18: Pori | B18: Titaanitie, 28840 PORI | C18: Satakunta | D18: 81.4 | H18: =IF(ISNUMBER(MATCH(P_ind[[#This Row],[Main fuel]],$J$29:$J$42,0)),"RE","non-RE") -> RE | J18: Coke oven gas | K18: ?
A19: Kavo | B19: Kavo | C19: Kainuu | D19: 79.2 | E19: Peat | F19: Industrial wood residues | G19: Forest fuelwood | H19: =IF(ISNUMBER(MATCH(P_ind[[#This Row],[Main fuel]],$J$29:$J$42,0)),"RE","non-RE") -> RE | J19: Forest fuelwood | K19: Y
A20: Kuusankoski bv | B20: Kuusankoski | C20: Kymenlaakso | D20: 76 | E20: Industrial wood residues | F20: Natural gas | G20: Heavy distillates | H20: =IF(ISNUMBER(MATCH(P_ind[[#This Row],[Main fuel]],$J$29:$J$42,0)),"RE","non-RE") -> RE | J20: Mixed fuels | K20: ? | N20: Assumption:
A21: Rauma | B21: Metsä Fibre Rauman tehdas | C21: Satakunta | D21: 75 | E21: Black liquor and concentrated liquors | F21: Heavy distillates | H21: =IF(ISNUMBER(MATCH(P_ind[[#This Row],[Main fuel]],$J$29:$J$42,0)),"RE","non-RE") -> RE | J21: Other by-products and wastes used as fuel | K21: ? | N21: All non-RE remains in region that currently has the largest capacity of it (Uusimaa) while the rest is converted to RE.
A22: Porvoo kt 3 | B22: Porvoo kt 3 | C22: Uusimaa | D22: 72.6 | E22: Natural gas | F22: Medium heavy distillates | H22: =IF(ISNUMBER(MATCH(P_ind[[#This Row],[Main fuel]],$J$29:$J$42,0)),"RE","non-RE") -> non-RE | J22: Exothermic heat from industry | K22: ?
A23: Kotka | B23: Kotka | C23: Kymenlaakso | D23: 72 | E23: Black liquor and concentrated liquors | F23: Natural gas | H23: =IF(ISNUMBER(MATCH(P_ind[[#This Row],[Main fuel]],$J$29:$J$42,0)),"RE","non-RE") -> RE | J23: Petroleum gases | K23: N | N23: Electric capacity | O23: RE | P23: non-RE
A24: Nokia kombi | B24: Nokia Kombi | C24: Pirkanmaa | D24: 72 | E24: Natural gas | F24: Medium heavy distillates | H24: =IF(ISNUMBER(MATCH(P_ind[[#This Row],[Main fuel]],$J$29:$J$42,0)),"RE","non-RE") -> non-RE | J24: Other non-specified energy sources | K24: ? | N24: North | O24: =M66-P24 -> 501.3 | P24: 0
A25: Rauma | B25: Rauma | C25: Satakunta | D25: 71.5 | E25: Industrial wood residues | F25: Forest fuelwood | G25: Mixed fuels | H25: =IF(ISNUMBER(MATCH(P_ind[[#This Row],[Main fuel]],$J$29:$J$42,0)),"RE","non-RE") -> RE | J25: Biogas | K25: Y | N25: West | O25: =M67-P25 -> 652.9 | P25: 0
A26: Kaukas | B26: Lappeenranta | C26: South Karelia | D26: 67.3 | E26: Black liquor and concentrated liquors | F26: Natural gas | H26: =IF(ISNUMBER(MATCH(P_ind[[#This Row],[Main fuel]],$J$29:$J$42,0)),"RE","non-RE") -> RE | J26: Light distillates | K26: N | N26: Center | O26: =M68-P26 -> 528.5 | P26: 0
A27: Varkaus lä | B27: Varkaus | C27: North Savo | D27: 51.8 | E27: Black liquor and concentrated liquors | F27: Forest fuelwood | G27: Other by-products and wastes used as fuel | H27: =IF(ISNUMBER(MATCH(P_ind[[#This Row],[Main fuel]],$J$29:$J$42,0)),"RE","non-RE") -> RE | J27: Unique RE fuel | N27: East | O27: =M69-P27 -> 281.6 | P27: 0
A28: Porvoo kt 2 | B28: Porvoo kt 2 | C28: Uusimaa | D28: 48 | E28: Natural gas | F28: Medium heavy distillates | H28: =IF(ISNUMBER(MATCH(P_ind[[#This Row],[Main fuel]],$J$29:$J$42,0)),"RE","non-RE") -> non-RE | J28: Include clearly RE and unknown fuel types | N28: South West | O28: =P10/P7+5 -> 50.124955 | P28: 0
A29: Hinkismäki | B29: Kouvola / Hinkismäki | C29: Kymenlaakso | D29: 45 | E29: Natural gas | F29: Medium heavy distillates | H29: =IF(ISNUMBER(MATCH(P_ind[[#This Row],[Main fuel]],$J$29:$J$42,0)),"RE","non-RE") -> non-RE | J29: Black liquor and concentrated liquors | N29: South East | O29: =M71-P29 -> 765.4 | P29: 0
A30: Jämsänkoski bv | B30: Jämsänkosken tehtaan voimalaitos | C30: Central Finland | D30: 43 | H30: =IF(ISNUMBER(MATCH(P_ind[[#This Row],[Main fuel]],$J$29:$J$42,0)),"RE","non-RE") -> RE | N30: Uusimaa | O30: =M72-P30 -> 146.5851 | P30: =P4 -> 143.0149
A31: Kilpilahden voimalaitos | B31: Porvoo | C31: Uusimaa | D31: 41 | E31: Heavy distillates | F31: Heavy distillates | G31: Natural gas | H31: =IF(ISNUMBER(MATCH(P_ind[[#This Row],[Main fuel]],$J$29:$J$42,0)),"RE","non-RE") -> non-RE | J31: Peat
A32: Tornio | B32: Tornio; Tornion voimalaitos | C32: Lapland | D32: 39.3 | E32: Peat | F32: Forest fuelwood | G32: Mixed fuels | H32: =IF(ISNUMBER(MATCH(P_ind[[#This Row],[Main fuel]],$J$29:$J$42,0)),"RE","non-RE") -> RE | J32: Industrial wood residues
A33: Äänekoski ht | B33: Metsä Fibre Oy Äänekosken voimalaitos | C33: Central Finland | D33: 35 | E33: Industrial wood residues | F33: Forest fuelwood | G33: Peat | H33: =IF(ISNUMBER(MATCH(P_ind[[#This Row],[Main fuel]],$J$29:$J$42,0)),"RE","non-RE") -> RE | J33: By-products from wood processing industry
A34: Alholma AK 1 | B34: AK1 | C34: Ostrobothnia | D34: 30 | E34: Industrial wood residues | G34: Heavy distillates | H34: =IF(ISNUMBER(MATCH(P_ind[[#This Row],[Main fuel]],$J$29:$J$42,0)),"RE","non-RE") -> RE | J34: Bioliquids
A35: Kokkola | B35: Voimalaitos Power (ent. Kokkolan voimalaitos) | C35: Central Ostrobothnia | D35: 27 | E35: Peat | F35: Forest fuelwood | G35: Industrial wood residues | H35: =IF(ISNUMBER(MATCH(P_ind[[#This Row],[Main fuel]],$J$29:$J$42,0)),"RE","non-RE") -> RE | J35: Blast furnace gas
A36: Siilinjärvi, V1 turb. ja vp turb. | B36: Siilinjärvi | C36: North Savo | D36: 25.1 | E36: Exothermic heat from industry | F36: Heavy distillates | H36: =IF(ISNUMBER(MATCH(P_ind[[#This Row],[Main fuel]],$J$29:$J$42,0)),"RE","non-RE") -> RE | J36: Coke oven gas
A37: Kaipola | B37: Kaipola VP3 | C37: Central Finland | D37: 25 | E37: Mixed fuels | F37: Other by-products and wastes used as fuel | G37: Industrial wood residues | H37: =IF(ISNUMBER(MATCH(P_ind[[#This Row],[Main fuel]],$J$29:$J$42,0)),"RE","non-RE") -> RE | J37: Forest fuelwood
A38: Tervasaari vp | B38: Tervasaari VP | C38: Pirkanmaa | D38: 25 | E38: Forest fuelwood | F38: Industrial wood residues | G38: Natural gas | H38: =IF(ISNUMBER(MATCH(P_ind[[#This Row],[Main fuel]],$J$29:$J$42,0)),"RE","non-RE") -> RE | J38: Mixed fuels
A39: Veitsiluoto | B39: Veitsiluoto | C39: Lapland | D39: 25 | E39: Black liquor and concentrated liquors | F39: Industrial wood residues | G39: Peat | H39: =IF(ISNUMBER(MATCH(P_ind[[#This Row],[Main fuel]],$J$29:$J$42,0)),"RE","non-RE") -> RE | J39: Other by-products and wastes used as fuel
A40: Kuopio, Savon Sellu | B40: Savon Sellu Vastapainevoimalaitos | C40: North Savo | D40: 20.5 | E40: Black liquor and concentrated liquors | F40: Peat | G40: Industrial wood residues | H40: =IF(ISNUMBER(MATCH(P_ind[[#This Row],[Main fuel]],$J$29:$J$42,0)),"RE","non-RE") -> RE | J40: Exothermic heat from industry
A41: Hämeenkyrö lä | B41: Metsä Board, Kyron tehdasalue Hämeenkyrö | C41: Pirkanmaa | D41: 20 | E41: Forest fuelwood | F41: Natural gas | H41: =IF(ISNUMBER(MATCH(P_ind[[#This Row],[Main fuel]],$J$29:$J$42,0)),"RE","non-RE") -> RE | J41: Other non-specified energy sources
A42: Simpele | B42: Simpele | C42: South Karelia | D42: 19.6 | E42: Industrial wood residues | F42: Heavy distillates | H42: =IF(ISNUMBER(MATCH(P_ind[[#This Row],[Main fuel]],$J$29:$J$42,0)),"RE","non-RE") -> RE | J42: Biogas
A43: Heinola vp | B43: Heinolan Flutigtehdas | C43: Päijät-Häme | D43: 19 | E43: Peat | F43: Industrial wood residues | G43: Black liquor and concentrated liquors | H43: =IF(ISNUMBER(MATCH(P_ind[[#This Row],[Main fuel]],$J$29:$J$42,0)),"RE","non-RE") -> RE
A44: Kauttua | B44: Kauttuan voimalaitos | C44: Satakunta | D44: 19 | E44: Peat | H44: =IF(ISNUMBER(MATCH(P_ind[[#This Row],[Main fuel]],$J$29:$J$42,0)),"RE","non-RE") -> RE | J44: Region | K44: RE | L44: non-RE
A45: Tako T2 ja T5 | B45: M-real Tako Board kartonkitehdas, Tampere | C45: Pirkanmaa | D45: 16.5 | E45: Natural gas | F45: Heavy distillates | H45: =IF(ISNUMBER(MATCH(P_ind[[#This Row],[Main fuel]],$J$29:$J$42,0)),"RE","non-RE") -> non-RE | J45: Uusimaa | K45: =SUMIFS(P_ind[Capacity], P_ind[Unit type], K$44, P_ind[Region], P_chp_ind14[[#This Row],[Region]]) -> 0 | L45: =SUMIFS(P_ind[Capacity], P_ind[Unit type], L$44, P_ind[Region], P_chp_ind14[[#This Row],[Region]]) -> 289.6 | M45: =SUM(P_chp_ind14[[#This Row],[RE]:[non-RE]]) -> 289.6
A46: Uusikaupunki | B46: Uusukaupunki, Hangonsaari | C46: Southwest Finland | D46: 14.2 | E46: Exothermic heat from industry | F46: Heavy distillates | H46: =IF(ISNUMBER(MATCH(P_ind[[#This Row],[Main fuel]],$J$29:$J$42,0)),"RE","non-RE") -> RE | J46: Southwest Finland | K46: =SUMIFS(P_ind[Capacity], P_ind[Unit type], K$44, P_ind[Region], P_chp_ind14[[#This Row],[Region]]) -> 14.2 | L46: =SUMIFS(P_ind[Capacity], P_ind[Unit type], L$44, P_ind[Region], P_chp_ind14[[#This Row],[Region]]) -> 0 | M46: =SUM(P_chp_ind14[[#This Row],[RE]:[non-RE]]) -> 14.2
A47: Aittaluoto | B47: Pori Aittaluoto | C47: Satakunta | D47: 14 | E47: Peat | F47: Industrial wood residues | G47: Industrial wood residues | H47: =IF(ISNUMBER(MATCH(P_ind[[#This Row],[Main fuel]],$J$29:$J$42,0)),"RE","non-RE") -> RE | J47: Satakunta | K47: =SUMIFS(P_ind[Capacity], P_ind[Unit type], K$44, P_ind[Region], P_chp_ind14[[#This Row],[Region]]) -> 260.9 | L47: =SUMIFS(P_ind[Capacity], P_ind[Unit type], L$44, P_ind[Region], P_chp_ind14[[#This Row],[Region]]) -> 0 | M47: =SUM(P_chp_ind14[[#This Row],[RE]:[non-RE]]) -> 260.9
A48: Kiimassuo | B48: Forssa | C48: Kanta-Häme | D48: 13.5 | E48: Forest fuelwood | F48: Mixed fuels | G48: Industrial wood residues | H48: =IF(ISNUMBER(MATCH(P_ind[[#This Row],[Main fuel]],$J$29:$J$42,0)),"RE","non-RE") -> RE | J48: Kanta-Häme | K48: =SUMIFS(P_ind[Capacity], P_ind[Unit type], K$44, P_ind[Region], P_chp_ind14[[#This Row],[Region]]) -> 13.5 | L48: =SUMIFS(P_ind[Capacity], P_ind[Unit type], L$44, P_ind[Region], P_chp_ind14[[#This Row],[Region]]) -> 11.4 | M48: =SUM(P_chp_ind14[[#This Row],[RE]:[non-RE]]) -> 24.9
A49: Mänttä lä | B49: Tehtaankatu 20 Mänttä | C49: Pirkanmaa | D49: 12 | E49: Peat | F49: Forest fuelwood | G49: Heavy distillates | H49: =IF(ISNUMBER(MATCH(P_ind[[#This Row],[Main fuel]],$J$29:$J$42,0)),"RE","non-RE") -> RE | J49: Pirkanmaa | K49: =SUMIFS(P_ind[Capacity], P_ind[Unit type], K$44, P_ind[Region], P_chp_ind14[[#This Row],[Region]]) -> 57 | L49: =SUMIFS(P_ind[Capacity], P_ind[Unit type], L$44, P_ind[Region], P_chp_ind14[[#This Row],[Region]]) -> 88.5 | M49: =SUM(P_chp_ind14[[#This Row],[RE]:[non-RE]]) -> 145.5
A50: Tervakoski lä | B50: Tervakoski | C50: Kanta-Häme | D50: 11.4 | E50: Natural gas | F50: Heavy distillates | H50: =IF(ISNUMBER(MATCH(P_ind[[#This Row],[Main fuel]],$J$29:$J$42,0)),"RE","non-RE") -> non-RE | J50: Päijät-Häme | K50: =SUMIFS(P_ind[Capacity], P_ind[Unit type], K$44, P_ind[Region], P_chp_ind14[[#This Row],[Region]]) -> 19 | L50: =SUMIFS(P_ind[Capacity], P_ind[Unit type], L$44, P_ind[Region], P_chp_ind14[[#This Row],[Region]]) -> 0 | M50: =SUM(P_chp_ind14[[#This Row],[RE]:[non-RE]]) -> 19
A51: Ekovoimalaitos | B51: Oulu, Laanila | C51: North Ostrobothnia | D51: 10 | E51: Mixed fuels | F51: Medium heavy distillates | G51: Petroleum gases | H51: =IF(ISNUMBER(MATCH(P_ind[[#This Row],[Main fuel]],$J$29:$J$42,0)),"RE","non-RE") -> RE | J51: Kymenlaakso | K51: =SUMIFS(P_ind[Capacity], P_ind[Unit type], K$44, P_ind[Region], P_chp_ind14[[#This Row],[Region]]) -> 395.5 | L51: =SUMIFS(P_ind[Capacity], P_ind[Unit type], L$44, P_ind[Region], P_chp_ind14[[#This Row],[Region]]) -> 45 | M51: =SUM(P_chp_ind14[[#This Row],[RE]:[non-RE]]) -> 440.5
A52: Säkylä | B52: Säkylä | D52: 8.8 | E52: Heavy distillates | H52: =IF(ISNUMBER(MATCH(P_ind[[#This Row],[Main fuel]],$J$29:$J$42,0)),"RE","non-RE") -> non-RE | J52: South Karelia | K52: =SUMIFS(P_ind[Capacity], P_ind[Unit type], K$44, P_ind[Region], P_chp_ind14[[#This Row],[Region]]) -> 305.9 | L52: =SUMIFS(P_ind[Capacity], P_ind[Unit type], L$44, P_ind[Region], P_chp_ind14[[#This Row],[Region]]) -> 0 | M52: =SUM(P_chp_ind14[[#This Row],[RE]:[non-RE]]) -> 305.9
A53: Ristiina | B53: Ristiina | D53: 8.5 | E53: Industrial wood residues | F53: Heavy distillates | H53: =IF(ISNUMBER(MATCH(P_ind[[#This Row],[Main fuel]],$J$29:$J$42,0)),"RE","non-RE") -> RE | J53: South Savo | K53: =SUMIFS(P_ind[Capacity], P_ind[Unit type], K$44, P_ind[Region], P_chp_ind14[[#This Row],[Region]]) -> 0 | L53: =SUMIFS(P_ind[Capacity], P_ind[Unit type], L$44, P_ind[Region], P_chp_ind14[[#This Row],[Region]]) -> 0 | M53: =SUM(P_chp_ind14[[#This Row],[RE]:[non-RE]]) -> 0
A54: Hyötyvoimalaitos | B54: Hyötyvoimalaitos | D54: 7 | F54: Natural gas | H54: =IF(ISNUMBER(MATCH(P_ind[[#This Row],[Main fuel]],$J$29:$J$42,0)),"RE","non-RE") -> RE | J54: North Savo | K54: =SUMIFS(P_ind[Capacity], P_ind[Unit type], K$44, P_ind[Region], P_chp_ind14[[#This Row],[Region]]) -> 97.4 | L54: =SUMIFS(P_ind[Capacity], P_ind[Unit type], L$44, P_ind[Region], P_chp_ind14[[#This Row],[Region]]) -> 0 | M54: =SUM(P_chp_ind14[[#This Row],[RE]:[non-RE]]) -> 97.4
A55: Lieksa Kevätniemi | B55: Lieksa | D55: 7 | E55: Industrial wood residues | F55: Forest fuelwood | H55: =IF(ISNUMBER(MATCH(P_ind[[#This Row],[Main fuel]],$J$29:$J$42,0)),"RE","non-RE") -> RE | J55: North Karelia | K55: =SUMIFS(P_ind[Capacity], P_ind[Unit type], K$44, P_ind[Region], P_chp_ind14[[#This Row],[Region]]) -> 105 | L55: =SUMIFS(P_ind[Capacity], P_ind[Unit type], L$44, P_ind[Region], P_chp_ind14[[#This Row],[Region]]) -> 0 | M55: =SUM(P_chp_ind14[[#This Row],[RE]:[non-RE]]) -> 105
A56: Ikaalinen | B56: Ikaalinen, moottorivoimalaitos | D56: 6 | E56: Natural gas | H56: =IF(ISNUMBER(MATCH(P_ind[[#This Row],[Main fuel]],$J$29:$J$42,0)),"RE","non-RE") -> non-RE | J56: Central Finland | K56: =SUMIFS(P_ind[Capacity], P_ind[Unit type], K$44, P_ind[Region], P_chp_ind14[[#This Row],[Region]]) -> 383 | L56: =SUMIFS(P_ind[Capacity], P_ind[Unit type], L$44, P_ind[Region], P_chp_ind14[[#This Row],[Region]]) -> 0 | M56: =SUM(P_chp_ind14[[#This Row],[RE]:[non-RE]]) -> 383
A57: Kuhmon Lämpö | B57: Kuhmo | D57: 4 | E57: Industrial wood residues | F57: Industrial wood residues | G57: Peat | H57: =IF(ISNUMBER(MATCH(P_ind[[#This Row],[Main fuel]],$J$29:$J$42,0)),"RE","non-RE") -> RE | J57: South Ostrobothnia | K57: =SUMIFS(P_ind[Capacity], P_ind[Unit type], K$44, P_ind[Region], P_chp_ind14[[#This Row],[Region]]) -> 0 | L57: =SUMIFS(P_ind[Capacity], P_ind[Unit type], L$44, P_ind[Region], P_chp_ind14[[#This Row],[Region]]) -> 0 | M57: =SUM(P_chp_ind14[[#This Row],[RE]:[non-RE]]) -> 0
A58: Joutseno | B58: Joutseno | D58: 3.9 | E58: Other non-specified energy sources | H58: =IF(ISNUMBER(MATCH(P_ind[[#This Row],[Main fuel]],$J$29:$J$42,0)),"RE","non-RE") -> RE | J58: Ostrobothnia | K58: =SUMIFS(P_ind[Capacity], P_ind[Unit type], K$44, P_ind[Region], P_chp_ind14[[#This Row],[Region]]) -> 365 | L58: =SUMIFS(P_ind[Capacity], P_ind[Unit type], L$44, P_ind[Region], P_chp_ind14[[#This Row],[Region]]) -> 0 | M58: =SUM(P_chp_ind14[[#This Row],[RE]:[non-RE]]) -> 365
A59: Vilppulan saha | B59: Vilppula | D59: 2.9 | E59: Industrial wood residues | F59: Industrial wood residues | H59: =IF(ISNUMBER(MATCH(P_ind[[#This Row],[Main fuel]],$J$29:$J$42,0)),"RE","non-RE") -> RE | J59: Central Ostrobothnia | K59: =SUMIFS(P_ind[Capacity], P_ind[Unit type], K$44, P_ind[Region], P_chp_ind14[[#This Row],[Region]]) -> 27 | L59: =SUMIFS(P_ind[Capacity], P_ind[Unit type], L$44, P_ind[Region], P_chp_ind14[[#This Row],[Region]]) -> 0 | M59: =SUM(P_chp_ind14[[#This Row],[RE]:[non-RE]]) -> 27
A60: Ilomantsin pellettitehdas | B60: Ilomantsi | D60: 2.8 | E60: Peat | F60: Medium heavy distillates | G60: Forest fuelwood | H60: =IF(ISNUMBER(MATCH(P_ind[[#This Row],[Main fuel]],$J$29:$J$42,0)),"RE","non-RE") -> RE | J60: North Ostrobothnia | K60: =SUMIFS(P_ind[Capacity], P_ind[Unit type], K$44, P_ind[Region], P_chp_ind14[[#This Row],[Region]]) -> 209 | L60: =SUMIFS(P_ind[Capacity], P_ind[Unit type], L$44, P_ind[Region], P_chp_ind14[[#This Row],[Region]]) -> 0 | M60: =SUM(P_chp_ind14[[#This Row],[RE]:[non-RE]]) -> 209
A61: Haapavesi | B61: Haapavesi | D61: 2.7 | E61: Industrial wood residues | F61: Forest fuelwood | G61: Peat | H61: =IF(ISNUMBER(MATCH(P_ind[[#This Row],[Main fuel]],$J$29:$J$42,0)),"RE","non-RE") -> RE | J61: Kainuu | K61: =SUMIFS(P_ind[Capacity], P_ind[Unit type], K$44, P_ind[Region], P_chp_ind14[[#This Row],[Region]]) -> 79.2 | L61: =SUMIFS(P_ind[Capacity], P_ind[Unit type], L$44, P_ind[Region], P_chp_ind14[[#This Row],[Region]]) -> 0 | M61: =SUM(P_chp_ind14[[#This Row],[RE]:[non-RE]]) -> 79.2
A62: Viikinmäki | B62: Viikinmäen jätevedenpuhdistamo | D62: 2.7 | E62: Biogas | F62: Medium heavy distillates | H62: =IF(ISNUMBER(MATCH(P_ind[[#This Row],[Main fuel]],$J$29:$J$42,0)),"RE","non-RE") -> RE | J62: Lapland | K62: =SUMIFS(P_ind[Capacity], P_ind[Unit type], K$44, P_ind[Region], P_chp_ind14[[#This Row],[Region]]) -> 292.3 | L62: =SUMIFS(P_ind[Capacity], P_ind[Unit type], L$44, P_ind[Region], P_chp_ind14[[#This Row],[Region]]) -> 0 | M62: =SUM(P_chp_ind14[[#This Row],[RE]:[non-RE]]) -> 292.3
A63: Kumpuniemi | B63: Vaneritehtaankatu 1 Suolahti | D63: 2.5 | E63: Industrial wood residues | H63: =IF(ISNUMBER(MATCH(P_ind[[#This Row],[Main fuel]],$J$29:$J$42,0)),"RE","non-RE") -> RE | K63: =SUM(P_chp_ind14[RE]) -> 2623.9 | L63: =SUM(P_chp_ind14[non-RE]) -> 434.5 | M63: =SUM(M45:M62) -> 3058.4
A64: Järvelän vaneritehdas | B64: Koskisen Oy, Järvelän levyteollisuus | D64: 1.6 | E64: Industrial wood residues | F64: Forest fuelwood | G64: Heavy distillates | H64: =IF(ISNUMBER(MATCH(P_ind[[#This Row],[Main fuel]],$J$29:$J$42,0)),"RE","non-RE") -> RE
A65: Haminan höyrykattilalaitos | B65: Hamina | D65: 1.5 | E65: Natural gas | H65: =IF(ISNUMBER(MATCH(P_ind[[#This Row],[Main fuel]],$J$29:$J$42,0)),"RE","non-RE") -> non-RE | J65: Region | K65: RE | L65: non-RE
A66: Vehmaa | B66: markku.ahlqvist@biovakka.fi | D66: 1.4 | E66: Biogas | H66: =IF(ISNUMBER(MATCH(P_ind[[#This Row],[Main fuel]],$J$29:$J$42,0)),"RE","non-RE") -> RE | J66: North | K66: {=SUM(_xlfn._xlws.FILTER(P_chp_ind14[RE],ISNUMBER(MATCH(P_chp_ind14[Region],_xlfn._xlws.FILTER(Region[Administrative],Region[Model]=P_chp_ind216[[#This Row],[Region]]),0))))} -> 501.3 | L66: {=SUM(_xlfn._xlws.FILTER(P_chp_ind14[non-RE],ISNUMBER(MATCH(P_chp_ind14[Region],_xlfn._xlws.FILTER(Region[Administrative],Region[Model]=P_chp_ind216[[#This Row],[Region]]),0))))} -> 0 | M66: =SUM(P_chp_ind216[[#This Row],[RE]:[non-RE]]) -> 501.3
A67: Rengon saha | B67: Renko | D67: 1.3 | E67: Industrial wood residues | F67: Industrial wood residues | H67: =IF(ISNUMBER(MATCH(P_ind[[#This Row],[Main fuel]],$J$29:$J$42,0)),"RE","non-RE") -> RE | J67: West | K67: {=SUM(_xlfn._xlws.FILTER(P_chp_ind14[RE],ISNUMBER(MATCH(P_chp_ind14[Region],_xlfn._xlws.FILTER(Region[Administrative],Region[Model]=P_chp_ind216[[#This Row],[Region]]),0))))} -> 652.9 | L67: {=SUM(_xlfn._xlws.FILTER(P_chp_ind14[non-RE],ISNUMBER(MATCH(P_chp_ind14[Region],_xlfn._xlws.FILTER(Region[Administrative],Region[Model]=P_chp_ind216[[#This Row],[Region]]),0))))} -> 0 | M67: =SUM(P_chp_ind216[[#This Row],[RE]:[non-RE]]) -> 652.9
A68: Sotkamo | B68: Sotkamo | D68: 1.3 | E68: Peat | F68: Industrial wood residues | G68: Forest fuelwood | H68: =IF(ISNUMBER(MATCH(P_ind[[#This Row],[Main fuel]],$J$29:$J$42,0)),"RE","non-RE") -> RE | J68: Center | K68: {=SUM(_xlfn._xlws.FILTER(P_chp_ind14[RE],ISNUMBER(MATCH(P_chp_ind14[Region],_xlfn._xlws.FILTER(Region[Administrative],Region[Model]=P_chp_ind216[[#This Row],[Region]]),0))))} -> 440 | L68: {=SUM(_xlfn._xlws.FILTER(P_chp_ind14[non-RE],ISNUMBER(MATCH(P_chp_ind14[Region],_xlfn._xlws.FILTER(Region[Administrative],Region[Model]=P_chp_ind216[[#This Row],[Region]]),0))))} -> 88.5 | M68: =SUM(P_chp_ind216[[#This Row],[RE]:[non-RE]]) -> 528.5
A69: Tiihala | B69: Tiihala, Kangasala | D69: 1 | E69: Light distillates | H69: =IF(ISNUMBER(MATCH(P_ind[[#This Row],[Main fuel]],$J$29:$J$42,0)),"RE","non-RE") -> non-RE | J69: East | K69: {=SUM(_xlfn._xlws.FILTER(P_chp_ind14[RE],ISNUMBER(MATCH(P_chp_ind14[Region],_xlfn._xlws.FILTER(Region[Administrative],Region[Model]=P_chp_ind216[[#This Row],[Region]]),0))))} -> 281.6 | L69: {=SUM(_xlfn._xlws.FILTER(P_chp_ind14[non-RE],ISNUMBER(MATCH(P_chp_ind14[Region],_xlfn._xlws.FILTER(Region[Administrative],Region[Model]=P_chp_ind216[[#This Row],[Region]]),0))))} -> 0 | M69: =SUM(P_chp_ind216[[#This Row],[RE]:[non-RE]]) -> 281.6
A70: Topinojan Biokaasulaitos | B70: Topinojan Biokaasulaitos | D70: 0.8 | E70: Biogas | F70: Biogas | H70: =IF(ISNUMBER(MATCH(P_ind[[#This Row],[Main fuel]],$J$29:$J$42,0)),"RE","non-RE") -> RE | J70: South West | K70: {=SUM(_xlfn._xlws.FILTER(P_chp_ind14[RE],ISNUMBER(MATCH(P_chp_ind14[Region],_xlfn._xlws.FILTER(Region[Administrative],Region[Model]=P_chp_ind216[[#This Row],[Region]]),0))))} -> 27.7 | L70: {=SUM(_xlfn._xlws.FILTER(P_chp_ind14[non-RE],ISNUMBER(MATCH(P_chp_ind14[Region],_xlfn._xlws.FILTER(Region[Administrative],Region[Model]=P_chp_ind216[[#This Row],[Region]]),0))))} -> 11.4 | M70: =SUM(P_chp_ind216[[#This Row],[RE]:[non-RE]]) -> 39.1
A71: Heinola | B71: Heinola Vuorikatu 24 c | D71: 0 | E71: Industrial wood residues | F71: Medium heavy distillates | G71: Petroleum gases | H71: =IF(ISNUMBER(MATCH(P_ind[[#This Row],[Main fuel]],$J$29:$J$42,0)),"RE","non-RE") -> RE | J71: South East | K71: {=SUM(_xlfn._xlws.FILTER(P_chp_ind14[RE],ISNUMBER(MATCH(P_chp_ind14[Region],_xlfn._xlws.FILTER(Region[Administrative],Region[Model]=P_chp_ind216[[#This Row],[Region]]),0))))} -> 720.4 | L71: {=SUM(_xlfn._xlws.FILTER(P_chp_ind14[non-RE],ISNUMBER(MATCH(P_chp_ind14[Region],_xlfn._xlws.FILTER(Region[Administrative],Region[Model]=P_chp_ind216[[#This Row],[Region]]),0))))} -> 45 | M71: =SUM(P_chp_ind216[[#This Row],[RE]:[non-RE]]) -> 765.4
A72: Kaskinen lv ja vp | B72: Metsä Fibre Kaskisten tehdas | D72: 0 | E72: Black liquor and concentrated liquors | F72: Heavy distillates | G72: Industrial wood residues | H72: =IF(ISNUMBER(MATCH(P_ind[[#This Row],[Main fuel]],$J$29:$J$42,0)),"RE","non-RE") -> RE | J72: Uusimaa | K72: {=SUM(_xlfn._xlws.FILTER(P_chp_ind14[RE],ISNUMBER(MATCH(P_chp_ind14[Region],_xlfn._xlws.FILTER(Region[Administrative],Region[Model]=P_chp_ind216[[#This Row],[Region]]),0))))} -> 0 | L72: {=SUM(_xlfn._xlws.FILTER(P_chp_ind14[non-RE],ISNUMBER(MATCH(P_chp_ind14[Region],_xlfn._xlws.FILTER(Region[Administrative],Region[Model]=P_chp_ind216[[#This Row],[Region]]),0))))} -> 289.6 | M72: =SUM(P_chp_ind216[[#This Row],[RE]:[non-RE]]) -> 289.6
A73: Kemi | B73: Metsä Fibre Kemin tehdas | D73: 0 | E73: Black liquor and concentrated liquors | F73: Industrial wood residues | G73: Heavy distillates | H73: =IF(ISNUMBER(MATCH(P_ind[[#This Row],[Main fuel]],$J$29:$J$42,0)),"RE","non-RE") -> RE | K73: =SUM(P_chp_ind216[RE]) -> 2623.9 | L73: =SUM(P_chp_ind216[non-RE]) -> 434.5 | M73: =SUM(K73:L73) -> 3058.4
A74: Pihlava | B74: Pori Pihlava | D74: 0 | E74: Industrial wood residues | F74: Heavy distillates | H74: =IF(ISNUMBER(MATCH(P_ind[[#This Row],[Main fuel]],$J$29:$J$42,0)),"RE","non-RE") -> RE
A75: Raisio | B75: Raisio | D75: 0 | E75: Heavy distillates | H75: =IF(ISNUMBER(MATCH(P_ind[[#This Row],[Main fuel]],$J$29:$J$42,0)),"RE","non-RE") -> non-RE
C77: Count | D77: Capacity | E77: Capacity %
B78: Total | C78: =COUNT(P_ind[Capacity]) -> 70 | D78: =SUM(P_ind[Capacity]) -> 3126.1
B79: >10 MW | C79: =COUNT(D6:D51) -> 46 | D79: =SUM(D6:D51) -> 3058.4 | E79: =D79/$D$78 -> 0.97834362
B80: >20 MW | C80: =COUNT(D6:D42) -> 37 | D80: =SUM(D6:D42) -> 2928.8 | E80: =D80/$D$78 -> 0.93688622
B81: >50 MW | C81: =COUNT(D6:D27) -> 22 | D81: =SUM(D6:D27) -> 2460.3 | E81: =D81/$D$78 -> 0.78701897
B82: >100 MW | C82: =COUNT(D6:D13) -> 8 | D82: =SUM(D6:D13) -> 1380.5 | E82: =D82/$D$78 -> 0.44160456
B83: >200 MW | C83: =COUNT(D6:D8) -> 3 | D83: =SUM(D6:D8) -> 748 | E83: =D83/$D$78 -> 0.23927577

Sheet P_dh_chp
A1: Source [1] | C1: Power plant register (latest update 27.6.2025) | F1: Delivery reliability | Energy Authority | P1: Source [2] | Q1: Inputs of "H2 heavy" | AE1: Merging [1-2] for CHP
A2: Selection | C2: Capacities are taken from column "Maximum, total, MW" | P2: Additional values (cb, eff0, eff1) are coppied to unitdata sheet
A3: Region search | C3: Performed manualy by looking at Finnish and English wikipedia and global energy monitor (www.gem.wiki) | P3: CHP: all city data can be coppied dirrectly to unitdata sheet, but included here for electricity capacity to enable ROF breakdown | AE3: Sector-specific ratios of electicity capacity between sources 1-2
A4: Unit type classification | C4: Main fuels grouped into three categories that are present in "H2 heavy" DH CHP types (Gass OCGT CHP is omitted due to its insignificance) | AF4: Gas | AG4: Bio | AH4: Waste
C5: Fuels with unclear match to CHP type were classified as the largest (bio) type and colored in red. | P5: CHP: Electric capacity | W5: CHP: ROF capacities | AE5: ROF | AF5: =(R15+Q15)/K53 -> 1.0136465 | AG5: =S15/L53 -> 1.3586579 | AH5: =T15/M53 -> 2.6215865
Q6: Gas OCGT | R6: Gas CCGT | S6: Bio | T6: Waste | Y6: Gas CCGT | Z6: Bio | AA6: Waste
A7: Name | B7: Location | C7: Region | D7: Capacity | E7: Main fuel | F7: Standby fuel 1 | G7: Standby fuel 2 | H7: Unit type | J7: Unique fuel | K7: CHP type | P7: ROF | R7: 211.3 | S7: 1426.6 | T7: 113.2 | U7: =SUM(Q7:T7) -> 1751.1 | W7: Electricity | Y7: =R7 -> 211.3 | Z7: =S7 -> 1426.6 | AA7: =T7 -> 113.2 | AE7: Electric capacity. Steps of merging:
A8: Vuosaari B | B8: Vuosaari B-voimalaitos | C8: Uusimaa | D8: 485 | E8: Natural gas | F8: Medium heavy distillates | H8: =_xlfn.XLOOKUP(P_dh_chp[[#This Row],[Main fuel]],$J$7:$J$21,$K$7:$K$21) -> Gas | J8: {=_xlfn.UNIQUE(_xlfn.TOCOL(P_dh_chp[[Main fuel]:[Standby fuel 2]], 1))} -> Natural gas | K8: Gas | P8: JKL | S8: 250 | U8: =SUM(Q8:T8) -> 250 | W8: Heat | Y8: 356.6 | Z8: 3099.3 | AA8: 345 | AE8: Take major city values from [2] without modifications
A9: Suomenojan voimalaitos | B9: Suomenojan voimalaitos | C9: Uusimaa | D9: 276 | E9: Natural gas | F9: Medium heavy distillates | H9: =_xlfn.XLOOKUP(P_dh_chp[[#This Row],[Main fuel]],$J$7:$J$21,$K$7:$K$21) -> Gas | J9: Medium heavy distillates | K9: Gas | P9: TKU | S9: 160 | U9: =SUM(Q9:T9) -> 160 | W9: Heat/electiricty | Y9: =Y8/R7 -> 1.6876479 | Z9: =Z8/S7 -> 2.1725081 | AA9: =AA8/T7 -> 3.0477032 | AE9: Scale regional values from [1] towards [2] for each CHP type and then subtract city values
A10: Vaskiluoto 2 | B10: Vaasa ( Vaskiluoto 2 ) | C10: Ostrobothnia | D10: 230 | E10: Hard coal and anthracite | F10: Heavy distillates | H10: =_xlfn.XLOOKUP(P_dh_chp[[#This Row],[Main fuel]],$J$7:$J$21,$K$7:$K$21) -> Gas | K10: Bio | P10: OUL | S10: 152 | U10: =SUM(Q10:T10) -> 152
A11: Keljonlahti | B11: Keljonrannantie 276 | C11: Central Finland | D11: 190 | E11: Peat | F11: Forest fuelwood | G11: Industrial wood residues | H11: =_xlfn.XLOOKUP(P_dh_chp[[#This Row],[Main fuel]],$J$7:$J$21,$K$7:$K$21) -> Bio | J11: Hard coal and anthracite | K11: Gas | P11: TRE | R11: 147 | S11: 55 | T11: 12 | U11: =SUM(Q11:T11) -> 214 | AE11: Negative regional values are avoided by setting floor of 0
A12: Vuosaari A | B12: Vuosaari A-voimalaitos | C12: Uusimaa | D12: 163 | E12: Natural gas | F12: Medium heavy distillates | H12: =_xlfn.XLOOKUP(P_dh_chp[[#This Row],[Main fuel]],$J$7:$J$21,$K$7:$K$21) -> Gas | J12: Heavy distillates | K12: Gas | P12: VAN | R12: 88 | S12: 28 | T12: 76.4 | U12: =SUM(Q12:T12) -> 192.4 | AE12: Region | AF12: Gas CCGT | AG12: Bio | AH12: Waste
A13: Lielahti | B13: Lielahti | C13: Pirkanmaa | D13: 142 | E13: Natural gas | F13: Medium heavy distillates | H13: =_xlfn.XLOOKUP(P_dh_chp[[#This Row],[Main fuel]],$J$7:$J$21,$K$7:$K$21) -> Gas | J13: Peat | K13: Bio | P13: ESP | Q13: 49 | R13: 234 | U13: =SUM(Q13:T13) -> 283 | AE13: North | AF13: =MAX(K46*AF$5-R10,0) -> 0 | AG13: =MAX(L46*AG$5-S10,0) -> 112.25896 | AH13: =MAX(M46*AH$5-T10,0) -> 0 | AI13: =SUM(AF13:AH13) -> 112.25896
A14: Naantali | B14: Naantalin voimalaitos | C14: Southwest Finland | D14: 130 | E14: Forest fuelwood | F14: Industrial wood residues | G14: Hard coal and anthracite | H14: =_xlfn.XLOOKUP(P_dh_chp[[#This Row],[Main fuel]],$J$7:$J$21,$K$7:$K$21) -> Bio | J14: Forest fuelwood | K14: Bio | P14: HKI | R14: 630 | U14: =SUM(Q14:T14) -> 630 | AE14: West | AF14: =MAX(K47*AF$5,0) -> 233.1387 | AG14: =MAX(L47*AG$5,0) -> 207.46706 | AH14: =MAX(M47*AH$5,0) -> 0 | AI14: =SUM(AF14:AH14) -> 440.60576
A15: Seinäjoki (SEVO) | B15: Seinäjoki Sevo | C15: South Ostrobothnia | D15: 120 | E15: Peat | F15: Heavy distillates | G15: Medium heavy distillates | H15: =_xlfn.XLOOKUP(P_dh_chp[[#This Row],[Main fuel]],$J$7:$J$21,$K$7:$K$21) -> Bio | J15: Industrial wood residues | K15: Bio | Q15: =SUM(Q7:Q14) -> 49 | R15: =SUM(R7:R14) -> 1310.3 | S15: =SUM(S7:S14) -> 2071.6 | T15: =SUM(T7:T14) -> 201.6 | U15: =SUM(U7:U14) -> 3632.5 | AE15: Center | AF15: =MAX(K48*AF$5-R8-R11,0) -> 0 | AG15: =MAX(L48*AG$5-S8-S11,0) -> 34.664467 | AH15: =MAX(M48*AH$5-T8-T11,0) -> 20.245514 | AI15: =SUM(AF15:AH15) -> 54.909981
A16: Lappeenranta, Kaukaan tehdas | C16: South Karelia | D16: 119 | E16: Industrial wood residues | F16: Natural gas | H16: =_xlfn.XLOOKUP(P_dh_chp[[#This Row],[Main fuel]],$J$7:$J$21,$K$7:$K$21) -> Bio | J16: Mixed fuels | K16: Bio | AE16: East | AF16: =MAX(K49*AF$5,0) -> 0 | AG16: =MAX(L49*AG$5,0) -> 473.3564 | AH16: =MAX(M49*AH$5,0) -> 0 | AI16: =SUM(AF16:AH16) -> 473.3564
A17: Haapaniemi | B17: Haapaniemen voimalaitos | C17: North Savo | D17: 118.1 | E17: Peat | F17: Heavy distillates | G17: Forest fuelwood | H17: =_xlfn.XLOOKUP(P_dh_chp[[#This Row],[Main fuel]],$J$7:$J$21,$K$7:$K$21) -> Bio | J17: Gasified waste | K17: Waste | P17: Heat capacity of non-CHP units. Currently omitted from regional breakdown | AE17: South West | AF17: =MAX(K50*AF$5-R9,0) -> 0 | AG17: =MAX(L50*AG$5-S9,0) -> 123.28017 | AH17: =MAX(M50*AH$5-T9,0) -> 51.383095 | AI17: =SUM(AF17:AH17) -> 174.66326
A18: Toppila 2 | B18: Tervahovintie 10, Oulu, Toppila 2 | C18: North Ostrobothnia | D18: 98 | E18: Peat | F18: Industrial wood residues | G18: Heavy distillates | H18: =_xlfn.XLOOKUP(P_dh_chp[[#This Row],[Main fuel]],$J$7:$J$21,$K$7:$K$21) -> Bio | J18: Other by-products and wastes used as fuel | K18: Waste | Q18: Oil HOB | R18: Waste HOB | S18: Bio HOB | T18: Gas HOB | U18: Ground source heat pump | V18: Electric boiler | W18: Heat storage charger | X18: Heat storage discharger | Y18: Large heat storage charger | Z18: Large heat storage discharger | AA18: Seasonal heat storage charger | AB18: Seasonal heat storage discharger | AE18: South East | AF18: =MAX(K51*AF$5,0) -> 45.614094 | AG18: =MAX(L51*AG$5,0) -> 223.49922 | AH18: =MAX(M51*AH$5,0) -> 117.97139 | AI18: =SUM(AF18:AH18) -> 387.0847
A19: Vantaan jätevoimala | B19: Vantaan Jätevoimala | C19: Uusimaa | D19: 81.4 | E19: Mixed fuels | F19: Natural gas | G19: Medium heavy distillates | H19: =_xlfn.XLOOKUP(P_dh_chp[[#This Row],[Main fuel]],$J$7:$J$21,$K$7:$K$21) -> Bio | J19: Vegetable-based fuels and other field biomass | K19: Bio | AE19: Uusimaa | AF19: =MAX(K52*AF$5-SUM(R12:R14),0) -> 0 | AG19: =MAX(L52*AG$5-SUM(S12:S14),0) -> 252.07373 | AH19: =MAX(M52*AH$5-SUM(T12:T14),0) -> 0 | AI19: =SUM(AF19:AH19) -> 252.07373
A20: Rauhalahti | B20: Rauhalahti | C20: North Savo | D20: 80 | E20: Peat | F20: Industrial wood residues | G20: Forest fuelwood | H20: =_xlfn.XLOOKUP(P_dh_chp[[#This Row],[Main fuel]],$J$7:$J$21,$K$7:$K$21) -> Bio | J20: Biogas | K20: Bio | AE20: ROF | AF20: =SUM(AF13:AF19) -> 278.7528 | AG20: =SUM(AG13:AG19) -> 1426.6 | AH20: =SUM(AH13:AH19) -> 189.6 | AI20: =SUM(AI13:AI19) -> 1894.9528
A21: Laanilan biovoimalaitos | B21: Typpitie 3, Oulu, Laanilan biovoimalaitos | C21: North Ostrobothnia | D21: 66.5 | E21: Forest fuelwood | F21: Industrial wood residues | G21: Mixed fuels | H21: =_xlfn.XLOOKUP(P_dh_chp[[#This Row],[Main fuel]],$J$7:$J$21,$K$7:$K$21) -> Bio | J21: Recovered wood | K21: Bio
A22: Hämeenlinna | B22: Hämeenlinna | C22: Kanta-Häme | D22: 65 | E22: Forest fuelwood | F22: Peat | G22: Natural gas | H22: =_xlfn.XLOOKUP(P_dh_chp[[#This Row],[Main fuel]],$J$7:$J$21,$K$7:$K$21) -> Bio | P22: ROF | Q22: 3520.3 | R22: 10 | S22: 2701.9 | T22: 1850 | U22: 148.8 | V22: 1042.9 | W22: 625.5 | X22: 625.5 | Y22: 170 | Z22: 170 | AC22: =SUM(Q22:AB22) -> 10864.9 | AE22: Heat capacity
A23: Naistenlahti 3 | B23: Naistenlahti 3 | C23: Pirkanmaa | D23: 60 | E23: Forest fuelwood | F23: Peat | G23: Natural gas | H23: =_xlfn.XLOOKUP(P_dh_chp[[#This Row],[Main fuel]],$J$7:$J$21,$K$7:$K$21) -> Bio | J23: Region | K23: Gas | L23: Bio | M23: Waste | P23: JKL | Q23: 200 | S23: 26.8 | T23: 3.1 | U23: 45 | V23: 120 | W23: 80 | X23: 80 | AC23: =SUM(Q23:AB23) -> 554.9 | AE23: Region | AF23: Gas CCGT | AG23: Bio | AH23: Waste
A24: Joensuu | B24: Joensuu, Iiksenvaarantie 2 | C24: North Karelia | D24: 47 | E24: Peat | F24: Forest fuelwood | G24: Industrial wood residues | H24: =_xlfn.XLOOKUP(P_dh_chp[[#This Row],[Main fuel]],$J$7:$J$21,$K$7:$K$21) -> Bio | J24: Uusimaa | K24: =SUMIFS(P_dh_chp[Capacity], P_dh_chp[Unit type], K$23, P_dh_chp[Region], P_dh_chp_2[[#This Row],[Region]]) -> 924 | L24: =SUMIFS(P_dh_chp[Capacity], P_dh_chp[Unit type], L$23, P_dh_chp[Region], P_dh_chp_2[[#This Row],[Region]]) -> 206.14 | M24: =SUMIFS(P_dh_chp[Capacity], P_dh_chp[Unit type], M$23, P_dh_chp[Region], P_dh_chp_2[[#This Row],[Region]]) -> 0 | N24: =SUM(P_dh_chp_2[[#This Row],[Gas]:[Waste]]) -> 1130.14 | P24: TKU | Q24: 624 | S24: 106.8 | U24: 64.4 | V24: 50 | W24: 75 | X24: 75 | AC24: =SUM(Q24:AB24) -> 995.2 | AE24: North | AF24: =AF13*Y$9 -> 0 | AG24: =AG13*Z$9 -> 243.88349 | AH24: =AH13*AA$9 -> 0 | AI24: =SUM(AF24:AH24) -> 243.88349
A25: Hovinsaari | B25: Hovinsaari | C25: Kymenlaakso | D25: 45.5 | G25: Natural gas | H25: =_xlfn.XLOOKUP(P_dh_chp[[#This Row],[Main fuel]],$J$7:$J$21,$K$7:$K$21) -> Bio | J25: Southwest Finland | K25: =SUMIFS(P_dh_chp[Capacity], P_dh_chp[Unit type], K$23, P_dh_chp[Region], P_dh_chp_2[[#This Row],[Region]]) -> 0 | L25: =SUMIFS(P_dh_chp[Capacity], P_dh_chp[Unit type], L$23, P_dh_chp[Region], P_dh_chp_2[[#This Row],[Region]]) -> 143.5 | M25: =SUMIFS(P_dh_chp[Capacity], P_dh_chp[Unit type], M$23, P_dh_chp[Region], P_dh_chp_2[[#This Row],[Region]]) -> 0 | N25: =SUM(P_dh_chp_2[[#This Row],[Gas]:[Waste]]) -> 143.5 | P25: OUL | Q25: 348 | U25: 2.1 | V25: 140 | W25: 55 | X25: 55 | Y25: 80 | Z25: 80 | AC25: =SUM(Q25:AB25) -> 760.1 | AE25: West | AF25: =AF14*Y$9 -> 393.45604 | AG25: =AG14*Z$9 -> 450.72385 | AH25: =AH14*AA$9 -> 0 | AI25: =SUM(AF25:AH25) -> 844.17989
A26: Kymijärvi 1 | B26: Kymijärvi Voimakatu 16, Lahti | C26: Päijät-Häme | D26: 45 | E26: Hard coal and anthracite | F26: Natural gas | G26: Gasified waste | H26: =_xlfn.XLOOKUP(P_dh_chp[[#This Row],[Main fuel]],$J$7:$J$21,$K$7:$K$21) -> Gas | J26: Satakunta | K26: =SUMIFS(P_dh_chp[Capacity], P_dh_chp[Unit type], K$23, P_dh_chp[Region], P_dh_chp_2[[#This Row],[Region]]) -> 0 | L26: =SUMIFS(P_dh_chp[Capacity], P_dh_chp[Unit type], L$23, P_dh_chp[Region], P_dh_chp_2[[#This Row],[Region]]) -> 0 | M26: =SUMIFS(P_dh_chp[Capacity], P_dh_chp[Unit type], M$23, P_dh_chp[Region], P_dh_chp_2[[#This Row],[Region]]) -> 0 | N26: =SUM(P_dh_chp_2[[#This Row],[Gas]:[Waste]]) -> 0 | P26: TRE | Q26: 305 | S26: 92 | T26: 235 | V26: 145 | W26: 100 | X26: 100 | AC26: =SUM(Q26:AB26) -> 977 | AE26: Center | AF26: =AF15*Y$9 -> 0 | AG26: =AG15*Z$9 -> 75.308835 | AH26: =AH15*AA$9 -> 61.702316 | AI26: =SUM(AF26:AH26) -> 137.01115
A27: Kymijärvi 2 | B27: Kymijärvi2 Voimakatu 16, Lahti | C27: Päijät-Häme | D27: 45 | E27: Gasified waste | F27: Natural gas | H27: =_xlfn.XLOOKUP(P_dh_chp[[#This Row],[Main fuel]],$J$7:$J$21,$K$7:$K$21) -> Waste | J27: Kanta-Häme | K27: =SUMIFS(P_dh_chp[Capacity], P_dh_chp[Unit type], K$23, P_dh_chp[Region], P_dh_chp_2[[#This Row],[Region]]) -> 0 | L27: =SUMIFS(P_dh_chp[Capacity], P_dh_chp[Unit type], L$23, P_dh_chp[Region], P_dh_chp_2[[#This Row],[Region]]) -> 65 | M27: =SUMIFS(P_dh_chp[Capacity], P_dh_chp[Unit type], M$23, P_dh_chp[Region], P_dh_chp_2[[#This Row],[Region]]) -> 19.6 | N27: =SUM(P_dh_chp_2[[#This Row],[Gas]:[Waste]]) -> 84.6 | P27: VAN | Q27: 92 | R27: 80 | S27: 23 | T27: 427 | U27: 35 | V27: 180 | W27: 180 | X27: 180 | AA27: 200 | AB27: 200 | AC27: =SUM(Q27:AB27) -> 1597 | AE27: East | AF27: =AF16*Y$9 -> 0 | AG27: =AG16*Z$9 -> 1028.3706 | AH27: =AH16*AA$9 -> 0 | AI27: =SUM(AF27:AH27) -> 1028.3706
A28: Martinlaakso | B28: Martinlaakso | C28: Uusimaa | D28: 37.1 | H28: =_xlfn.XLOOKUP(P_dh_chp[[#This Row],[Main fuel]],$J$7:$J$21,$K$7:$K$21) -> Bio | J28: Pirkanmaa | K28: =SUMIFS(P_dh_chp[Capacity], P_dh_chp[Unit type], K$23, P_dh_chp[Region], P_dh_chp_2[[#This Row],[Region]]) -> 142 | L28: =SUMIFS(P_dh_chp[Capacity], P_dh_chp[Unit type], L$23, P_dh_chp[Region], P_dh_chp_2[[#This Row],[Region]]) -> 60 | M28: =SUMIFS(P_dh_chp[Capacity], P_dh_chp[Unit type], M$23, P_dh_chp[Region], P_dh_chp_2[[#This Row],[Region]]) -> 12.3 | N28: =SUM(P_dh_chp_2[[#This Row],[Gas]:[Waste]]) -> 214.3 | P28: ESP | Q28: 88 | S28: 139 | T28: 757.4 | U28: 295 | V28: 150 | W28: 280 | X28: 280 | AC28: =SUM(Q28:AB28) -> 1989.4 | AE28: South West | AF28: =AF17*Y$9 -> 0 | AG28: =AG17*Z$9 -> 267.82715 | AH28: =AH17*AA$9 -> 156.60042 | AI28: =SUM(AF28:AH28) -> 424.42758
A29: Suosiola | B29: Lampelankatu 24, Suosiola | C29: Lapland | D29: 30 | E29: Peat | F29: Industrial wood residues | G29: Forest fuelwood | H29: =_xlfn.XLOOKUP(P_dh_chp[[#This Row],[Main fuel]],$J$7:$J$21,$K$7:$K$21) -> Bio | J29: Päijät-Häme | K29: =SUMIFS(P_dh_chp[Capacity], P_dh_chp[Unit type], K$23, P_dh_chp[Region], P_dh_chp_2[[#This Row],[Region]]) -> 45 | L29: =SUMIFS(P_dh_chp[Capacity], P_dh_chp[Unit type], L$23, P_dh_chp[Region], P_dh_chp_2[[#This Row],[Region]]) -> 0 | M29: =SUMIFS(P_dh_chp[Capacity], P_dh_chp[Unit type], M$23, P_dh_chp[Region], P_dh_chp_2[[#This Row],[Region]]) -> 45 | N29: =SUM(P_dh_chp_2[[#This Row],[Gas]:[Waste]]) -> 90 | P29: HKI | Q29: 671 | S29: 527 | T29: 912 | U29: 343.2 | V29: 540 | W29: 340 | X29: 340 | Y29: 120 | Z29: 120 | AC29: =SUM(Q29:AB29) -> 3913.2 | AE29: South East | AF29: =AF18*Y$9 -> 76.98053 | AG29: =AG18*Z$9 -> 485.55386 | AH29: =AH18*AA$9 -> 359.54178 | AI29: =SUM(AF29:AH29) -> 922.07617
A30: Pursiala 1 | B30: Pursiala 1 | C30: South Savo | D30: 27 | E30: Forest fuelwood | F30: Industrial wood residues | G30: Peat | H30: =_xlfn.XLOOKUP(P_dh_chp[[#This Row],[Main fuel]],$J$7:$J$21,$K$7:$K$21) -> Bio | J30: Kymenlaakso | K30: =SUMIFS(P_dh_chp[Capacity], P_dh_chp[Unit type], K$23, P_dh_chp[Region], P_dh_chp_2[[#This Row],[Region]]) -> 0 | L30: =SUMIFS(P_dh_chp[Capacity], P_dh_chp[Unit type], L$23, P_dh_chp[Region], P_dh_chp_2[[#This Row],[Region]]) -> 45.5 | M30: =SUMIFS(P_dh_chp[Capacity], P_dh_chp[Unit type], M$23, P_dh_chp[Region], P_dh_chp_2[[#This Row],[Region]]) -> 0 | N30: =SUM(P_dh_chp_2[[#This Row],[Gas]:[Waste]]) -> 45.5 | Q30: =SUM(Q22:Q29) -> 5848.3 | R30: =SUM(R22:R29) -> 90 | S30: =SUM(S22:S29) -> 3616.5 | T30: =SUM(T22:T29) -> 4184.5 | U30: =SUM(U22:U29) -> 933.5 | V30: =SUM(V22:V29) -> 2367.9 | W30: =SUM(W22:W29) -> 1735.5 | X30: =SUM(X22:X29) -> 1735.5 | ... AC30: =SUM(AC22:AC29) -> 21651.7 | AE30: Uusimaa | AF30: =AF19*Y$9 -> 0 | AG30: =AG19*Z$9 -> 547.63222 | AH30: =AH19*AA$9 -> 0 | AI30: =SUM(AF30:AH30) -> 547.63222
A31: Järvenpää | B31: Voimalankatu, 04430 Järvenpää | C31: Uusimaa | D31: 23.8 | E31: Forest fuelwood | H31: =_xlfn.XLOOKUP(P_dh_chp[[#This Row],[Main fuel]],$J$7:$J$21,$K$7:$K$21) -> Bio | J31: South Karelia | K31: =SUMIFS(P_dh_chp[Capacity], P_dh_chp[Unit type], K$23, P_dh_chp[Region], P_dh_chp_2[[#This Row],[Region]]) -> 0 | L31: =SUMIFS(P_dh_chp[Capacity], P_dh_chp[Unit type], L$23, P_dh_chp[Region], P_dh_chp_2[[#This Row],[Region]]) -> 119 | M31: =SUMIFS(P_dh_chp[Capacity], P_dh_chp[Unit type], M$23, P_dh_chp[Region], P_dh_chp_2[[#This Row],[Region]]) -> 0 | N31: =SUM(P_dh_chp_2[[#This Row],[Gas]:[Waste]]) -> 119 | AE31: ROF | AF31: =SUM(AF24:AF30) -> 470.43657 | AG31: =SUM(AG24:AG30) -> 3099.3 | AH31: =SUM(AH24:AH30) -> 577.84452 | AI31: =SUM(AI24:AI30) -> 4147.5811
A32: Pursiala 2 | B32: Pursiala 2 | C32: South Savo | D32: 22 | E32: Forest fuelwood | F32: Industrial wood residues | G32: Peat | H32: =_xlfn.XLOOKUP(P_dh_chp[[#This Row],[Main fuel]],$J$7:$J$21,$K$7:$K$21) -> Bio | J32: South Savo | K32: =SUMIFS(P_dh_chp[Capacity], P_dh_chp[Unit type], K$23, P_dh_chp[Region], P_dh_chp_2[[#This Row],[Region]]) -> 0 | L32: =SUMIFS(P_dh_chp[Capacity], P_dh_chp[Unit type], L$23, P_dh_chp[Region], P_dh_chp_2[[#This Row],[Region]]) -> 76.5 | M32: =SUMIFS(P_dh_chp[Capacity], P_dh_chp[Unit type], M$23, P_dh_chp[Region], P_dh_chp_2[[#This Row],[Region]]) -> 0 | N32: =SUM(P_dh_chp_2[[#This Row],[Gas]:[Waste]]) -> 76.5
A33: Riihimäki (Ekokem) | B33: Kuulojankatu 1, 11120 RIIHIMÄKI | C33: Kanta-Häme | D33: 19.6 | E33: Other by-products and wastes used as fuel | F33: Heavy distillates | G33: Medium heavy distillates | H33: =_xlfn.XLOOKUP(P_dh_chp[[#This Row],[Main fuel]],$J$7:$J$21,$K$7:$K$21) -> Waste | J33: North Savo | K33: =SUMIFS(P_dh_chp[Capacity], P_dh_chp[Unit type], K$23, P_dh_chp[Region], P_dh_chp_2[[#This Row],[Region]]) -> 0 | L33: =SUMIFS(P_dh_chp[Capacity], P_dh_chp[Unit type], L$23, P_dh_chp[Region], P_dh_chp_2[[#This Row],[Region]]) -> 224.9 | M33: =SUMIFS(P_dh_chp[Capacity], P_dh_chp[Unit type], M$23, P_dh_chp[Region], P_dh_chp_2[[#This Row],[Region]]) -> 0 | N33: =SUM(P_dh_chp_2[[#This Row],[Gas]:[Waste]]) -> 224.9
A34: Kokkola | B34: Voimalaitos Voima | C34: Central Ostrobothnia | D34: 19.5 | E34: Industrial wood residues | F34: Forest fuelwood | G34: Peat | H34: =_xlfn.XLOOKUP(P_dh_chp[[#This Row],[Main fuel]],$J$7:$J$21,$K$7:$K$21) -> Bio | J34: North Karelia | K34: =SUMIFS(P_dh_chp[Capacity], P_dh_chp[Unit type], K$23, P_dh_chp[Region], P_dh_chp_2[[#This Row],[Region]]) -> 0 | L34: =SUMIFS(P_dh_chp[Capacity], P_dh_chp[Unit type], L$23, P_dh_chp[Region], P_dh_chp_2[[#This Row],[Region]]) -> 47 | M34: =SUMIFS(P_dh_chp[Capacity], P_dh_chp[Unit type], M$23, P_dh_chp[Region], P_dh_chp_2[[#This Row],[Region]]) -> 0 | N34: =SUM(P_dh_chp_2[[#This Row],[Gas]:[Waste]]) -> 47
A35: Kerava | B35: 04260 Kerava, Alikeravantie 83 | C35: Uusimaa | D35: 19.04 | E35: Forest fuelwood | F35: Industrial wood residues | G35: Vegetable-based fuels and other field biomass | H35: =_xlfn.XLOOKUP(P_dh_chp[[#This Row],[Main fuel]],$J$7:$J$21,$K$7:$K$21) -> Bio | J35: Central Finland | K35: =SUMIFS(P_dh_chp[Capacity], P_dh_chp[Unit type], K$23, P_dh_chp[Region], P_dh_chp_2[[#This Row],[Region]]) -> 0 | L35: =SUMIFS(P_dh_chp[Capacity], P_dh_chp[Unit type], L$23, P_dh_chp[Region], P_dh_chp_2[[#This Row],[Region]]) -> 190 | M35: =SUMIFS(P_dh_chp[Capacity], P_dh_chp[Unit type], M$23, P_dh_chp[Region], P_dh_chp_2[[#This Row],[Region]]) -> 0 | N35: =SUM(P_dh_chp_2[[#This Row],[Gas]:[Waste]]) -> 190
A36: Tolkkinen 1 | B36: Tolkkinen | C36: Uusimaa | D36: 17.8 | E36: Forest fuelwood | F36: Medium heavy distillates | H36: =_xlfn.XLOOKUP(P_dh_chp[[#This Row],[Main fuel]],$J$7:$J$21,$K$7:$K$21) -> Bio | J36: South Ostrobothnia | K36: =SUMIFS(P_dh_chp[Capacity], P_dh_chp[Unit type], K$23, P_dh_chp[Region], P_dh_chp_2[[#This Row],[Region]]) -> 0 | L36: =SUMIFS(P_dh_chp[Capacity], P_dh_chp[Unit type], L$23, P_dh_chp[Region], P_dh_chp_2[[#This Row],[Region]]) -> 120 | M36: =SUMIFS(P_dh_chp[Capacity], P_dh_chp[Unit type], M$23, P_dh_chp[Region], P_dh_chp_2[[#This Row],[Region]]) -> 0 | N36: =SUM(P_dh_chp_2[[#This Row],[Gas]:[Waste]]) -> 120
A37: Savonlinna | B37: Savonlinna | C37: South Savo | D37: 17.5 | E37: Industrial wood residues | F37: Forest fuelwood | G37: Peat | H37: =_xlfn.XLOOKUP(P_dh_chp[[#This Row],[Main fuel]],$J$7:$J$21,$K$7:$K$21) -> Bio | J37: Ostrobothnia | K37: =SUMIFS(P_dh_chp[Capacity], P_dh_chp[Unit type], K$23, P_dh_chp[Region], P_dh_chp_2[[#This Row],[Region]]) -> 230 | L37: =SUMIFS(P_dh_chp[Capacity], P_dh_chp[Unit type], L$23, P_dh_chp[Region], P_dh_chp_2[[#This Row],[Region]]) -> 13.2 | M37: =SUMIFS(P_dh_chp[Capacity], P_dh_chp[Unit type], M$23, P_dh_chp[Region], P_dh_chp_2[[#This Row],[Region]]) -> 0 | N37: =SUM(P_dh_chp_2[[#This Row],[Gas]:[Waste]]) -> 243.2
A38: Ämmässuo | B38: Ämmässuon jätteenkäsittelykeskus CHP1 | C38: Uusimaa | D38: 15.7 | E38: Biogas | H38: =_xlfn.XLOOKUP(P_dh_chp[[#This Row],[Main fuel]],$J$7:$J$21,$K$7:$K$21) -> Bio | J38: Central Ostrobothnia | K38: =SUMIFS(P_dh_chp[Capacity], P_dh_chp[Unit type], K$23, P_dh_chp[Region], P_dh_chp_2[[#This Row],[Region]]) -> 0 | L38: =SUMIFS(P_dh_chp[Capacity], P_dh_chp[Unit type], L$23, P_dh_chp[Region], P_dh_chp_2[[#This Row],[Region]]) -> 19.5 | M38: =SUMIFS(P_dh_chp[Capacity], P_dh_chp[Unit type], M$23, P_dh_chp[Region], P_dh_chp_2[[#This Row],[Region]]) -> 0 | N38: =SUM(P_dh_chp_2[[#This Row],[Gas]:[Waste]]) -> 19.5
A39: Iisalmi | B39: Iisalmi, Energiakuja 3 | C39: North Savo | D39: 15 | E39: Peat | F39: Forest fuelwood | G39: Industrial wood residues | H39: =_xlfn.XLOOKUP(P_dh_chp[[#This Row],[Main fuel]],$J$7:$J$21,$K$7:$K$21) -> Bio | J39: North Ostrobothnia | K39: =SUMIFS(P_dh_chp[Capacity], P_dh_chp[Unit type], K$23, P_dh_chp[Region], P_dh_chp_2[[#This Row],[Region]]) -> 0 | L39: =SUMIFS(P_dh_chp[Capacity], P_dh_chp[Unit type], L$23, P_dh_chp[Region], P_dh_chp_2[[#This Row],[Region]]) -> 164.5 | M39: =SUMIFS(P_dh_chp[Capacity], P_dh_chp[Unit type], M$23, P_dh_chp[Region], P_dh_chp_2[[#This Row],[Region]]) -> 0 | N39: =SUM(P_dh_chp_2[[#This Row],[Gas]:[Waste]]) -> 164.5
A40: Salo | B40: Salo | C40: Southwest Finland | D40: 13.5 | E40: Forest fuelwood | F40: Recovered wood | G40: Peat | H40: =_xlfn.XLOOKUP(P_dh_chp[[#This Row],[Main fuel]],$J$7:$J$21,$K$7:$K$21) -> Bio | J40: Kainuu | K40: =SUMIFS(P_dh_chp[Capacity], P_dh_chp[Unit type], K$23, P_dh_chp[Region], P_dh_chp_2[[#This Row],[Region]]) -> 0 | L40: =SUMIFS(P_dh_chp[Capacity], P_dh_chp[Unit type], L$23, P_dh_chp[Region], P_dh_chp_2[[#This Row],[Region]]) -> 0 | M40: =SUMIFS(P_dh_chp[Capacity], P_dh_chp[Unit type], M$23, P_dh_chp[Region], P_dh_chp_2[[#This Row],[Region]]) -> 0 | N40: =SUM(P_dh_chp_2[[#This Row],[Gas]:[Waste]]) -> 0
A41: Westenergy jätteenpolttolaitos | B41: Energiatie 37, 66530 Koivulahti | C41: Ostrobothnia | D41: 13.2 | E41: Mixed fuels | H41: =_xlfn.XLOOKUP(P_dh_chp[[#This Row],[Main fuel]],$J$7:$J$21,$K$7:$K$21) -> Bio | J41: Lapland | K41: =SUMIFS(P_dh_chp[Capacity], P_dh_chp[Unit type], K$23, P_dh_chp[Region], P_dh_chp_2[[#This Row],[Region]]) -> 0 | L41: =SUMIFS(P_dh_chp[Capacity], P_dh_chp[Unit type], L$23, P_dh_chp[Region], P_dh_chp_2[[#This Row],[Region]]) -> 30 | M41: =SUMIFS(P_dh_chp[Capacity], P_dh_chp[Unit type], M$23, P_dh_chp[Region], P_dh_chp_2[[#This Row],[Region]]) -> 0 | N41: =SUM(P_dh_chp_2[[#This Row],[Gas]:[Waste]]) -> 30
A42: Tammervoima | B42: Tammervoima / Hyötyvoimankuja 1 | C42: Pirkanmaa | D42: 12.3 | E42: Other by-products and wastes used as fuel | F42: Medium heavy distillates | G42: Biogas | H42: =_xlfn.XLOOKUP(P_dh_chp[[#This Row],[Main fuel]],$J$7:$J$21,$K$7:$K$21) -> Waste | K42: =SUM(P_dh_chp_2[Gas]) -> 1341 | L42: =SUM(P_dh_chp_2[Bio]) -> 1524.74 | M42: =SUM(P_dh_chp_2[Waste]) -> 76.9 | N42: =SUM(N24:N41) -> 2942.64
A43: Riikinvoima | B43: Riikinvoima | C43: North Savo | D43: 11.8 | E43: Mixed fuels | F43: Medium heavy distillates | H43: =_xlfn.XLOOKUP(P_dh_chp[[#This Row],[Main fuel]],$J$7:$J$21,$K$7:$K$21) -> Bio
A44: Energia-Tietola | B44: Energia-Tietola | C44: ? | D44: 11.6 | E44: Natural gas | H44: =_xlfn.XLOOKUP(P_dh_chp[[#This Row],[Main fuel]],$J$7:$J$21,$K$7:$K$21) -> Gas
A45: Tolkkinen, Biolaitos | B45: Tolkkinen, Biolaitos | C45: Uusimaa | D45: 11.3 | E45: Forest fuelwood | F45: Industrial wood residues | G45: Peat | H45: =_xlfn.XLOOKUP(P_dh_chp[[#This Row],[Main fuel]],$J$7:$J$21,$K$7:$K$21) -> Bio | J45: Region | K45: Gas | L45: Bio | M45: Waste
A46: Pieksämäki | B46: Pieksämäki, Kutteritie 2A | C46: South Savo | D46: 10 | E46: Peat | F46: Forest fuelwood | G46: Industrial wood residues | H46: =_xlfn.XLOOKUP(P_dh_chp[[#This Row],[Main fuel]],$J$7:$J$21,$K$7:$K$21) -> Bio | J46: North | K46: {=SUM(_xlfn._xlws.FILTER(P_dh_chp_2[Gas],ISNUMBER(MATCH(P_dh_chp_2[Region],_xlfn._xlws.FILTER(Region[Administrative],Region[Model]=P_chp_ind2[[#This Row],[Region]]),0))))} -> 0 | L46: {=SUM(_xlfn._xlws.FILTER(P_dh_chp_2[Bio],ISNUMBER(MATCH(P_dh_chp_2[Region],_xlfn._xlws.FILTER(Region[Administrative],Region[Model]=P_chp_ind2[[#This Row],[Region]]),0))))} -> 194.5 | M46: {=SUM(_xlfn._xlws.FILTER(P_dh_chp_2[Waste],ISNUMBER(MATCH(P_dh_chp_2[Region],_xlfn._xlws.FILTER(Region[Administrative],Region[Model]=P_chp_ind2[[#This Row],[Region]]),0))))} -> 0 | N46: =SUM(P_chp_ind2[[#This Row],[Gas]:[Waste]]) -> 194.5
A47: Harabacka | B47: Harabacka | D47: 9.6 | E47: Natural gas | F47: Medium heavy distillates | H47: =_xlfn.XLOOKUP(P_dh_chp[[#This Row],[Main fuel]],$J$7:$J$21,$K$7:$K$21) -> Gas | J47: West | K47: {=SUM(_xlfn._xlws.FILTER(P_dh_chp_2[Gas],ISNUMBER(MATCH(P_dh_chp_2[Region],_xlfn._xlws.FILTER(Region[Administrative],Region[Model]=P_chp_ind2[[#This Row],[Region]]),0))))} -> 230 | L47: {=SUM(_xlfn._xlws.FILTER(P_dh_chp_2[Bio],ISNUMBER(MATCH(P_dh_chp_2[Region],_xlfn._xlws.FILTER(Region[Administrative],Region[Model]=P_chp_ind2[[#This Row],[Region]]),0))))} -> 152.7 | M47: {=SUM(_xlfn._xlws.FILTER(P_dh_chp_2[Waste],ISNUMBER(MATCH(P_dh_chp_2[Region],_xlfn._xlws.FILTER(Region[Administrative],Region[Model]=P_chp_ind2[[#This Row],[Region]]),0))))} -> 0 | N47: =SUM(P_chp_ind2[[#This Row],[Gas]:[Bio]]) -> 382.7
A48: Korvenmäen ekovoimalaitos | B48: Korvenmäen ekovoimalaitos | D48: 9.6 | E48: Other by-products and wastes used as fuel | F48: Medium heavy distillates | H48: =_xlfn.XLOOKUP(P_dh_chp[[#This Row],[Main fuel]],$J$7:$J$21,$K$7:$K$21) -> Waste | J48: Center | K48: {=SUM(_xlfn._xlws.FILTER(P_dh_chp_2[Gas],ISNUMBER(MATCH(P_dh_chp_2[Region],_xlfn._xlws.FILTER(Region[Administrative],Region[Model]=P_chp_ind2[[#This Row],[Region]]),0))))} -> 142 | L48: {=SUM(_xlfn._xlws.FILTER(P_dh_chp_2[Bio],ISNUMBER(MATCH(P_dh_chp_2[Region],_xlfn._xlws.FILTER(Region[Administrative],Region[Model]=P_chp_ind2[[#This Row],[Region]]),0))))} -> 250 | M48: {=SUM(_xlfn._xlws.FILTER(P_dh_chp_2[Waste],ISNUMBER(MATCH(P_dh_chp_2[Region],_xlfn._xlws.FILTER(Region[Administrative],Region[Model]=P_chp_ind2[[#This Row],[Region]]),0))))} -> 12.3 | N48: =SUM(P_chp_ind2[[#This Row],[Gas]:[Bio]]) -> 392
A49: Ylivieska | B49: Tulolantien voimalaitos, Ylivieska, Vieskan Voima | D49: 6.2 | E49: Peat | H49: =_xlfn.XLOOKUP(P_dh_chp[[#This Row],[Main fuel]],$J$7:$J$21,$K$7:$K$21) -> Bio | J49: East | K49: {=SUM(_xlfn._xlws.FILTER(P_dh_chp_2[Gas],ISNUMBER(MATCH(P_dh_chp_2[Region],_xlfn._xlws.FILTER(Region[Administrative],Region[Model]=P_chp_ind2[[#This Row],[Region]]),0))))} -> 0 | L49: {=SUM(_xlfn._xlws.FILTER(P_dh_chp_2[Bio],ISNUMBER(MATCH(P_dh_chp_2[Region],_xlfn._xlws.FILTER(Region[Administrative],Region[Model]=P_chp_ind2[[#This Row],[Region]]),0))))} -> 348.4 | M49: {=SUM(_xlfn._xlws.FILTER(P_dh_chp_2[Waste],ISNUMBER(MATCH(P_dh_chp_2[Region],_xlfn._xlws.FILTER(Region[Administrative],Region[Model]=P_chp_ind2[[#This Row],[Region]]),0))))} -> 0 | N49: =SUM(P_chp_ind2[[#This Row],[Gas]:[Bio]]) -> 348.4
A50: Kuusamo | B50: Kuusamon voimalaitos | D50: 6 | E50: Industrial wood residues | F50: Peat | H50: =_xlfn.XLOOKUP(P_dh_chp[[#This Row],[Main fuel]],$J$7:$J$21,$K$7:$K$21) -> Bio | J50: South West | K50: {=SUM(_xlfn._xlws.FILTER(P_dh_chp_2[Gas],ISNUMBER(MATCH(P_dh_chp_2[Region],_xlfn._xlws.FILTER(Region[Administrative],Region[Model]=P_chp_ind2[[#This Row],[Region]]),0))))} -> 0 | L50: {=SUM(_xlfn._xlws.FILTER(P_dh_chp_2[Bio],ISNUMBER(MATCH(P_dh_chp_2[Region],_xlfn._xlws.FILTER(Region[Administrative],Region[Model]=P_chp_ind2[[#This Row],[Region]]),0))))} -> 208.5 | M50: {=SUM(_xlfn._xlws.FILTER(P_dh_chp_2[Waste],ISNUMBER(MATCH(P_dh_chp_2[Region],_xlfn._xlws.FILTER(Region[Administrative],Region[Model]=P_chp_ind2[[#This Row],[Region]]),0))))} -> 19.6 | N50: =SUM(P_chp_ind2[[#This Row],[Gas]:[Bio]]) -> 208.5
A51: Nikkilä | B51: Nikkilän voimalaitos | D51: 5.4 | E51: Natural gas | F51: Medium heavy distillates | H51: =_xlfn.XLOOKUP(P_dh_chp[[#This Row],[Main fuel]],$J$7:$J$21,$K$7:$K$21) -> Gas | J51: South East | K51: {=SUM(_xlfn._xlws.FILTER(P_dh_chp_2[Gas],ISNUMBER(MATCH(P_dh_chp_2[Region],_xlfn._xlws.FILTER(Region[Administrative],Region[Model]=P_chp_ind2[[#This Row],[Region]]),0))))} -> 45 | L51: {=SUM(_xlfn._xlws.FILTER(P_dh_chp_2[Bio],ISNUMBER(MATCH(P_dh_chp_2[Region],_xlfn._xlws.FILTER(Region[Administrative],Region[Model]=P_chp_ind2[[#This Row],[Region]]),0))))} -> 164.5 | M51: {=SUM(_xlfn._xlws.FILTER(P_dh_chp_2[Waste],ISNUMBER(MATCH(P_dh_chp_2[Region],_xlfn._xlws.FILTER(Region[Administrative],Region[Model]=P_chp_ind2[[#This Row],[Region]]),0))))} -> 45 | N51: =SUM(P_chp_ind2[[#This Row],[Gas]:[Bio]]) -> 209.5
A52: Nivala | B52: Lämpölä/Hyttitie 5 Nivala | D52: 5.3 | E52: Forest fuelwood | F52: Heavy distillates | H52: =_xlfn.XLOOKUP(P_dh_chp[[#This Row],[Main fuel]],$J$7:$J$21,$K$7:$K$21) -> Bio | J52: Uusimaa | K52: {=SUM(_xlfn._xlws.FILTER(P_dh_chp_2[Gas],ISNUMBER(MATCH(P_dh_chp_2[Region],_xlfn._xlws.FILTER(Region[Administrative],Region[Model]=P_chp_ind2[[#This Row],[Region]]),0))))} -> 924 | L52: {=SUM(_xlfn._xlws.FILTER(P_dh_chp_2[Bio],ISNUMBER(MATCH(P_dh_chp_2[Region],_xlfn._xlws.FILTER(Region[Administrative],Region[Model]=P_chp_ind2[[#This Row],[Region]]),0))))} -> 206.14 | M52: {=SUM(_xlfn._xlws.FILTER(P_dh_chp_2[Waste],ISNUMBER(MATCH(P_dh_chp_2[Region],_xlfn._xlws.FILTER(Region[Administrative],Region[Model]=P_chp_ind2[[#This Row],[Region]]),0))))} -> 0 | N52: =SUM(P_chp_ind2[[#This Row],[Gas]:[Bio]]) -> 1130.14
A53: Koneharju kt | B53: Koneharju Koneharjunkatu, Lahti | D53: 4.6 | E53: Natural gas | F53: Medium heavy distillates | H53: =_xlfn.XLOOKUP(P_dh_chp[[#This Row],[Main fuel]],$J$7:$J$21,$K$7:$K$21) -> Gas | K53: =SUM(P_chp_ind2[Gas]) -> 1341 | L53: =SUM(P_chp_ind2[Bio]) -> 1524.74 | M53: =SUM(P_chp_ind2[Waste]) -> 76.9 | N53: =SUM(K53:M53) -> 2942.64
A54: Varissaari | B54: Varissaari | D54: 4.5 | E54: Forest fuelwood | F54: Peat | G54: Medium heavy distillates | H54: =_xlfn.XLOOKUP(P_dh_chp[[#This Row],[Main fuel]],$J$7:$J$21,$K$7:$K$21) -> Bio
A55: Kemijärvi | B55: Kemijärvi | D55: 4 | E55: Forest fuelwood | F55: Peat | G55: Industrial wood residues | H55: =_xlfn.XLOOKUP(P_dh_chp[[#This Row],[Main fuel]],$J$7:$J$21,$K$7:$K$21) -> Bio
A56: Lapua | B56: Lapua | D56: 4 | E56: Peat | F56: Forest fuelwood | G56: Industrial wood residues | H56: =_xlfn.XLOOKUP(P_dh_chp[[#This Row],[Main fuel]],$J$7:$J$21,$K$7:$K$21) -> Bio
A57: Savio | B57: Savion voimalaitos | D57: 3.9 | E57: Natural gas | H57: =_xlfn.XLOOKUP(P_dh_chp[[#This Row],[Main fuel]],$J$7:$J$21,$K$7:$K$21) -> Gas
A58: Björknäs kraftvärmeverk | B58: Björknäs kraftvärmeverk | D58: 3.7 | H58: =_xlfn.XLOOKUP(P_dh_chp[[#This Row],[Main fuel]],$J$7:$J$21,$K$7:$K$21) -> Bio
A59: Kerava | B59: Alikeravan voimalaitos | D59: 3.7 | E59: Natural gas | H59: =_xlfn.XLOOKUP(P_dh_chp[[#This Row],[Main fuel]],$J$7:$J$21,$K$7:$K$21) -> Gas
A60: Ämmässuo 2 | B60: Ämmässuon jätteenkäsittelykeskus CHP2 | D60: 3.125 | E60: Biogas | H60: =_xlfn.XLOOKUP(P_dh_chp[[#This Row],[Main fuel]],$J$7:$J$21,$K$7:$K$21) -> Bio
A61: Lemene KM1 | B61: Ruokosmetsänkatu 11, 37550 Lempäälä | D61: 3 | E61: Natural gas | H61: =_xlfn.XLOOKUP(P_dh_chp[[#This Row],[Main fuel]],$J$7:$J$21,$K$7:$K$21) -> Gas
A62: Lemene KM2 | B62: Kalliokummuntie 28, 37550 Lempäälä | D62: 2.4 | E62: Natural gas | H62: =_xlfn.XLOOKUP(P_dh_chp[[#This Row],[Main fuel]],$J$7:$J$21,$K$7:$K$21) -> Gas
A63: Toholampi | B63: Toholampi | D63: 1.3 | E63: Forest fuelwood | F63: Industrial wood residues | G63: Industrial wood residues | H63: =_xlfn.XLOOKUP(P_dh_chp[[#This Row],[Main fuel]],$J$7:$J$21,$K$7:$K$21) -> Bio
A64: Posion CHP-laitos | B64: Posion Voimalaitos Rantatie 3 97900 Posio | D64: 0.6 | E64: Forest fuelwood | F64: Forest fuelwood | H64: =_xlfn.XLOOKUP(P_dh_chp[[#This Row],[Main fuel]],$J$7:$J$21,$K$7:$K$21) -> Bio
A65: Naistenlahti 1 | B65: Naistenlahti 1 | D65: 0 | E65: Natural gas | F65: Medium heavy distillates | H65: =_xlfn.XLOOKUP(P_dh_chp[[#This Row],[Main fuel]],$J$7:$J$21,$K$7:$K$21) -> Gas
A66: Vaskiluoto 3 | B66: Vaasa ( Vaskiluoto 3 ) | D66: 0 | E66: Heavy distillates | H66: =_xlfn.XLOOKUP(P_dh_chp[[#This Row],[Main fuel]],$J$7:$J$21,$K$7:$K$21) -> Gas
C68: Count | D68: Capacity | E68: Capacity %
B69: Total | C69: =COUNT(P_dh_chp[Capacity]) -> 59 | D69: =SUM(P_dh_chp[Capacity]) -> 3035.165
B70: >10 MW | C70: =COUNT(D8:D46) -> 39 | D70: =SUM(D8:D46) -> 2954.24 | E70: =D70/$D$69 -> 0.97333753
B71: >20 MW | C71: =COUNT(D8:D34) -> 27 | D71: =SUM(D8:D34) -> 2785.5 | E71: =D71/$D$69 -> 0.91774253
B72: >50 MW | C72: =COUNT(D8:D23) -> 16 | D72: =SUM(D8:D23) -> 2424 | E72: =D72/$D$69 -> 0.79863862
B73: >100 MW | C73: =COUNT(D8:D17) -> 10 | D73: =SUM(D8:D17) -> 1973.1 | E73: =D73/$D$69 -> 0.65007998
B74: >200 MW | C74: =COUNT(D8:D10) -> 3 | D74: =SUM(D8:D10) -> 991 | E74: =D74/$D$69 -> 0.32650614

Sheet P_heat
A1: 1. Heat unit mapping to model regions | Q1: 2. Aggregation by regions
A2: Sources | B2: Dirrect coppy from: Finland_dheat_and_industry.xlsx ROF sheet.
B3: Primery: lines 6-879 - Finnish Energy (2023 values from https://energia.fi/en/statistics/district-heating-statistics/), lines 880-919 - Confederation of Finnish Industries (https://ek.fi/tutkittua-tietoa/vihreat-investoinnit/). | Q3: Heat capacity
A4: (Dis)charge | B4: Charge and discharge capacities of storage units are represented by single (heat) value as they were equal for all storage units.
A5: Matching order | B5: Functions in Exact and Exact+n match first municipality (according to order in Municipality table) that is found in info string. The more accurate approach would be to search according to info string composed in following order: unit, location (Company string after comma), company name (Company string before comma). This was attempted, but reverted due to insignificant result changes at expense of significant complication to table and its functions.
Q6: Region | R6: Excluded | S6: Included in industry | T6: Bio CHP | U6: Gas CCGT CHP | V6: Waste CHP | W6: Oil HOB | X6: Bio HOB | Y6: Electric boiler | Z6: Gas HOB | AA6: Ground source heat pump | AB6: Waste HOB | AC6: Heat storage | AD6: Large heat storage
A7: Company | B7: Unit | C7: Info string | D7: Start | E7: Heat | F7: Power | G7: Storage | H7: Fuel | I7: Type | J7: Exact | K7: Exact+n | L7: Copilot | M7: Copilot basis | N7: Municipality | O7: Region | Q7: North | R7: {=SUMPRODUCT((H_unit[Region]=P_heat[[#This Row],[Region]])*(H_unit[Type]=P_heat[[#Headers],[Excluded]])*IFERROR(_xlfn.NUMBERVALUE(H_unit[Heat]),0))} -> 150.3 | S7: {=SUMPRODUCT((H_unit[Region]=P_heat[[#This Row],[Region]])*(H_unit[Type]=P_heat[[#Headers],[Included in industry]])*IFERROR(_xlfn.NUMBERVALUE(H_unit[Heat]),0))} -> 620 | T7: {=SUMPRODUCT((H_unit[Region]=P_heat[[#This Row],[Region]])*(H_unit[Type]=P_heat[[#Headers],[Bio CHP]])*IFERROR(_xlfn.NUMBERVALUE(H_unit[Heat]),0))} -> 225 | U7: {=SUMPRODUCT((H_unit[Region]=P_heat[[#This Row],[Region]])*(H_unit[Type]=P_heat[[#Headers],[Gas CCGT CHP]])*IFERROR(_xlfn.NUMBERVALUE(H_unit[Heat]),0))} -> 0 | V7: {=SUMPRODUCT((H_unit[Region]=P_heat[[#This Row],[Region]])*(H_unit[Type]=P_heat[[#Headers],[Waste CHP]])*IFERROR(_xlfn.NUMBERVALUE(H_unit[Heat]),0))} -> 0 | W7: {=SUMPRODUCT((H_unit[Region]=P_heat[[#This Row],[Region]])*(H_unit[Type]=P_heat[[#Headers],[Oil HOB]])*IFERROR(_xlfn.NUMBERVALUE(H_unit[Heat]),0))} -> 406.4 | X7: {=SUMPRODUCT((H_unit[Region]=P_heat[[#This Row],[Region]])*(H_unit[Type]=P_heat[[#Headers],[Bio HOB]])*IFERROR(_xlfn.NUMBERVALUE(H_unit[Heat]),0))} -> 592.4 | Y7: {=SUMPRODUCT((H_unit[Region]=P_heat[[#This Row],[Region]])*(H_unit[Type]=P_heat[[#Headers],[Electric boiler]])*IFERROR(_xlfn.NUMBERVALUE(H_unit[Heat]),0))} -> 60 | Z7: {=SUMPRODUCT((H_unit[Region]=P_heat[[#This Row],[Region]])*(H_unit[Type]=P_heat[[#Headers],[Gas HOB]])*IFERROR(_xlfn.NUMBERVALUE(H_unit[Heat]),0))} -> 1 | AA7: {=SUMPRODUCT((H_unit[Region]=P_heat[[#This Row],[Region]])*(H_unit[Type]=P_heat[[#Headers],[Ground source heat pump]])*IFERROR(_xlfn.NUMBERVALUE(H_unit[Heat]),0))} -> 5.2 | AB7: {=SUMPRODUCT((H_unit[Region]=P_heat[[#This Row],[Region]])*(H_unit[Type]=P_heat[[#Headers],[Waste HOB]])*IFERROR(_xlfn.NUMBERVALUE(H_unit[Heat]),0))} -> 0 | AC7: {=SUMPRODUCT((H_unit[Region]=P_heat[[#This Row],[Region]])*(H_unit[Type]=P_heat[[#Headers],[Heat storage ]])*IFERROR(_xlfn.NUMBERVALUE(H_unit[Heat]),0))} -> 61 | AD7: {=SUMPRODUCT((H_unit[Region]=P_heat[[#This Row],[Region]])*(H_unit[Type]=P_heat[[#Headers],[Large heat storage]])*IFERROR(_xlfn.NUMBERVALUE(H_unit[Heat]),0))} -> 0 | AE7: =SUM(P_heat[#This Row]) -> 2121.3
A8: Stora Enso Oyj, Heinola | B8: Stora Enso | C8: {=" "&LOWER(_xlfn.REDUCE(H_unit[[#This Row],[Company]]&" "&H_unit[[#This Row],[Unit]],{",",".","(",")","/"},_xlfn.LAMBDA(_xlpm.txt,_xlpm.delim,SUBSTITUTE(_xlpm.txt,_xlpm.delim," "))))&" "} -> stora enso oyj heinola stora enso | D8: 1961 | E8: .. | F8: 17 | H8: jtu | I8: Included in industry | J8: {=_xlfn.XLOOKUP(TRUE,ISNUMBER(SEARCH(" "&Municipality[Municipality]&" ",H_unit[[#This Row],[Info string]])),Municipality[Municipality],"")} -> Heinola | K8: {=IF(H_unit[[#This Row],[Exact]]<>"","",_xlfn.XLOOKUP(TRUE,ISNUMBER(SEARCH(" "&Municipality[Municipality]&"n ",H_unit[[#This Row],[Info string]])),Municipality[Municipality],""))} | N8: =_xlfn.TEXTJOIN("",TRUE,H_unit[[#This Row],[Exact]],H_unit[[#This Row],[Exact+n]],H_unit[[#This Row],[Copilot]]) -> Heinola | O8: =_xlfn.XLOOKUP(H_unit[[#This Row],[Municipality]],Municipality[Municipality],Municipality[Model],"") -> South East | Q8: West | R8: {=SUMPRODUCT((H_unit[Region]=P_heat[[#This Row],[Region]])*(H_unit[Type]=P_heat[[#Headers],[Excluded]])*IFERROR(_xlfn.NUMBERVALUE(H_unit[Heat]),0))} -> 17.3 | S8: {=SUMPRODUCT((H_unit[Region]=P_heat[[#This Row],[Region]])*(H_unit[Type]=P_heat[[#Headers],[Included in industry]])*IFERROR(_xlfn.NUMBERVALUE(H_unit[Heat]),0))} -> 0 | T8: {=SUMPRODUCT((H_unit[Region]=P_heat[[#This Row],[Region]])*(H_unit[Type]=P_heat[[#Headers],[Bio CHP]])*IFERROR(_xlfn.NUMBERVALUE(H_unit[Heat]),0))} -> 1127 | U8: {=SUMPRODUCT((H_unit[Region]=P_heat[[#This Row],[Region]])*(H_unit[Type]=P_heat[[#Headers],[Gas CCGT CHP]])*IFERROR(_xlfn.NUMBERVALUE(H_unit[Heat]),0))} -> 0 | V8: {=SUMPRODUCT((H_unit[Region]=P_heat[[#This Row],[Region]])*(H_unit[Type]=P_heat[[#Headers],[Waste CHP]])*IFERROR(_xlfn.NUMBERVALUE(H_unit[Heat]),0))} -> 52 | W8: {=SUMPRODUCT((H_unit[Region]=P_heat[[#This Row],[Region]])*(H_unit[Type]=P_heat[[#Headers],[Oil HOB]])*IFERROR(_xlfn.NUMBERVALUE(H_unit[Heat]),0))} -> 832.3 | X8: {=SUMPRODUCT((H_unit[Region]=P_heat[[#This Row],[Region]])*(H_unit[Type]=P_heat[[#Headers],[Bio HOB]])*IFERROR(_xlfn.NUMBERVALUE(H_unit[Heat]),0))} -> 572.2 | Y8: {=SUMPRODUCT((H_unit[Region]=P_heat[[#This Row],[Region]])*(H_unit[Type]=P_heat[[#Headers],[Electric boiler]])*IFERROR(_xlfn.NUMBERVALUE(H_unit[Heat]),0))} -> 545 | Z8: {=SUMPRODUCT((H_unit[Region]=P_heat[[#This Row],[Region]])*(H_unit[Type]=P_heat[[#Headers],[Gas HOB]])*IFERROR(_xlfn.NUMBERVALUE(H_unit[Heat]),0))} -> 0 | AA8: {=SUMPRODUCT((H_unit[Region]=P_heat[[#This Row],[Region]])*(H_unit[Type]=P_heat[[#Headers],[Ground source heat pump]])*IFERROR(_xlfn.NUMBERVALUE(H_unit[Heat]),0))} -> 34.7 | AB8: {=SUMPRODUCT((H_unit[Region]=P_heat[[#This Row],[Region]])*(H_unit[Type]=P_heat[[#Headers],[Waste HOB]])*IFERROR(_xlfn.NUMBERVALUE(H_unit[Heat]),0))} -> 10 | AC8: {=SUMPRODUCT((H_unit[Region]=P_heat[[#This Row],[Region]])*(H_unit[Type]=P_heat[[#Headers],[Heat storage ]])*IFERROR(_xlfn.NUMBERVALUE(H_unit[Heat]),0))} -> 108 | AD8: {=SUMPRODUCT((H_unit[Region]=P_heat[[#This Row],[Region]])*(H_unit[Type]=P_heat[[#Headers],[Large heat storage]])*IFERROR(_xlfn.NUMBERVALUE(H_unit[Heat]),0))} -> 170 | AE8: =SUM(P_heat[#This Row]) -> 3468.5
A9: Finnsementti Oy, Lappeenranta | B9: Finnsementti Oy | C9: {=" "&LOWER(_xlfn.REDUCE(H_unit[[#This Row],[Company]]&" "&H_unit[[#This Row],[Unit]],{",",".","(",")","/"},_xlfn.LAMBDA(_xlpm.txt,_xlpm.delim,SUBSTITUTE(_xlpm.txt,_xlpm.delim," "))))&" "} -> finnsementti oy lappeenranta finnsementti oy | D9: 1983 | E9: .. | H9: sek | I9: Excluded | J9: {=_xlfn.XLOOKUP(TRUE,ISNUMBER(SEARCH(" "&Municipality[Municipality]&" ",H_unit[[#This Row],[Info string]])),Municipality[Municipality],"")} -> Lappeenranta | K9: {=IF(H_unit[[#This Row],[Exact]]<>"","",_xlfn.XLOOKUP(TRUE,ISNUMBER(SEARCH(" "&Municipality[Municipality]&"n ",H_unit[[#This Row],[Info string]])),Municipality[Municipality],""))} | N9: =_xlfn.TEXTJOIN("",TRUE,H_unit[[#This Row],[Exact]],H_unit[[#This Row],[Exact+n]],H_unit[[#This Row],[Copilot]]) -> Lappeenranta | O9: =_xlfn.XLOOKUP(H_unit[[#This Row],[Municipality]],Municipality[Municipality],Municipality[Model],"") -> South East | Q9: Center | R9: {=SUMPRODUCT((H_unit[Region]=P_heat[[#This Row],[Region]])*(H_unit[Type]=P_heat[[#Headers],[Excluded]])*IFERROR(_xlfn.NUMBERVALUE(H_unit[Heat]),0))} -> 130.7 | S9: {=SUMPRODUCT((H_unit[Region]=P_heat[[#This Row],[Region]])*(H_unit[Type]=P_heat[[#Headers],[Included in industry]])*IFERROR(_xlfn.NUMBERVALUE(H_unit[Heat]),0))} -> 65 | T9: {=SUMPRODUCT((H_unit[Region]=P_heat[[#This Row],[Region]])*(H_unit[Type]=P_heat[[#Headers],[Bio CHP]])*IFERROR(_xlfn.NUMBERVALUE(H_unit[Heat]),0))} -> 130.4 | U9: {=SUMPRODUCT((H_unit[Region]=P_heat[[#This Row],[Region]])*(H_unit[Type]=P_heat[[#Headers],[Gas CCGT CHP]])*IFERROR(_xlfn.NUMBERVALUE(H_unit[Heat]),0))} -> 13 | V9: {=SUMPRODUCT((H_unit[Region]=P_heat[[#This Row],[Region]])*(H_unit[Type]=P_heat[[#Headers],[Waste CHP]])*IFERROR(_xlfn.NUMBERVALUE(H_unit[Heat]),0))} -> 0 | W9: {=SUMPRODUCT((H_unit[Region]=P_heat[[#This Row],[Region]])*(H_unit[Type]=P_heat[[#Headers],[Oil HOB]])*IFERROR(_xlfn.NUMBERVALUE(H_unit[Heat]),0))} -> 226.6 | X9: {=SUMPRODUCT((H_unit[Region]=P_heat[[#This Row],[Region]])*(H_unit[Type]=P_heat[[#Headers],[Bio HOB]])*IFERROR(_xlfn.NUMBERVALUE(H_unit[Heat]),0))} -> 240.8 | Y9: {=SUMPRODUCT((H_unit[Region]=P_heat[[#This Row],[Region]])*(H_unit[Type]=P_heat[[#Headers],[Electric boiler]])*IFERROR(_xlfn.NUMBERVALUE(H_unit[Heat]),0))} -> 0.3 | Z9: {=SUMPRODUCT((H_unit[Region]=P_heat[[#This Row],[Region]])*(H_unit[Type]=P_heat[[#Headers],[Gas HOB]])*IFERROR(_xlfn.NUMBERVALUE(H_unit[Heat]),0))} -> 149.9 | AA9: {=SUMPRODUCT((H_unit[Region]=P_heat[[#This Row],[Region]])*(H_unit[Type]=P_heat[[#Headers],[Ground source heat pump]])*IFERROR(_xlfn.NUMBERVALUE(H_unit[Heat]),0))} -> 3.5 | AB9: {=SUMPRODUCT((H_unit[Region]=P_heat[[#This Row],[Region]])*(H_unit[Type]=P_heat[[#Headers],[Waste HOB]])*IFERROR(_xlfn.NUMBERVALUE(H_unit[Heat]),0))} -> 0 | AC9: {=SUMPRODUCT((H_unit[Region]=P_heat[[#This Row],[Region]])*(H_unit[Type]=P_heat[[#Headers],[Heat storage ]])*IFERROR(_xlfn.NUMBERVALUE(H_unit[Heat]),0))} -> 3.5 | AD9: {=SUMPRODUCT((H_unit[Region]=P_heat[[#This Row],[Region]])*(H_unit[Type]=P_heat[[#Headers],[Large heat storage]])*IFERROR(_xlfn.NUMBERVALUE(H_unit[Heat]),0))} -> 0 | AE9: =SUM(P_heat[#This Row]) -> 963.7
A10: Stora Enso Oulu Oy | B10: Soodakattila SK7 | C10: {=" "&LOWER(_xlfn.REDUCE(H_unit[[#This Row],[Company]]&" "&H_unit[[#This Row],[Unit]],{",",".","(",")","/"},_xlfn.LAMBDA(_xlpm.txt,_xlpm.delim,SUBSTITUTE(_xlpm.txt,_xlpm.delim," "))))&" "} -> stora enso oulu oy soodakattila sk7 | D10: 1988 | E10: .. | F10: 77 | H10: jätel | I10: Included in industry | J10: {=_xlfn.XLOOKUP(TRUE,ISNUMBER(SEARCH(" "&Municipality[Municipality]&" ",H_unit[[#This Row],[Info string]])),Municipality[Municipality],"")} -> Oulu | K10: {=IF(H_unit[[#This Row],[Exact]]<>"","",_xlfn.XLOOKUP(TRUE,ISNUMBER(SEARCH(" "&Municipality[Municipality]&"n ",H_unit[[#This Row],[Info string]])),Municipality[Municipality],""))} | N10: =_xlfn.TEXTJOIN("",TRUE,H_unit[[#This Row],[Exact]],H_unit[[#This Row],[Exact+n]],H_unit[[#This Row],[Copilot]]) -> Oulu | O10: =_xlfn.XLOOKUP(H_unit[[#This Row],[Municipality]],Municipality[Municipality],Municipality[Model],"") -> North | Q10: East | R10: {=SUMPRODUCT((H_unit[Region]=P_heat[[#This Row],[Region]])*(H_unit[Type]=P_heat[[#Headers],[Excluded]])*IFERROR(_xlfn.NUMBERVALUE(H_unit[Heat]),0))} -> 27 | S10: {=SUMPRODUCT((H_unit[Region]=P_heat[[#This Row],[Region]])*(H_unit[Type]=P_heat[[#Headers],[Included in industry]])*IFERROR(_xlfn.NUMBERVALUE(H_unit[Heat]),0))} -> 79.9 | T10: {=SUMPRODUCT((H_unit[Region]=P_heat[[#This Row],[Region]])*(H_unit[Type]=P_heat[[#Headers],[Bio CHP]])*IFERROR(_xlfn.NUMBERVALUE(H_unit[Heat]),0))} -> 905.7 | U10: {=SUMPRODUCT((H_unit[Region]=P_heat[[#This Row],[Region]])*(H_unit[Type]=P_heat[[#Headers],[Gas CCGT CHP]])*IFERROR(_xlfn.NUMBERVALUE(H_unit[Heat]),0))} -> 1.6 | V10: {=SUMPRODUCT((H_unit[Region]=P_heat[[#This Row],[Region]])*(H_unit[Type]=P_heat[[#Headers],[Waste CHP]])*IFERROR(_xlfn.NUMBERVALUE(H_unit[Heat]),0))} -> 0 | W10: {=SUMPRODUCT((H_unit[Region]=P_heat[[#This Row],[Region]])*(H_unit[Type]=P_heat[[#Headers],[Oil HOB]])*IFERROR(_xlfn.NUMBERVALUE(H_unit[Heat]),0))} -> 1052.4 | X10: {=SUMPRODUCT((H_unit[Region]=P_heat[[#This Row],[Region]])*(H_unit[Type]=P_heat[[#Headers],[Bio HOB]])*IFERROR(_xlfn.NUMBERVALUE(H_unit[Heat]),0))} -> 539.3 | Y10: {=SUMPRODUCT((H_unit[Region]=P_heat[[#This Row],[Region]])*(H_unit[Type]=P_heat[[#Headers],[Electric boiler]])*IFERROR(_xlfn.NUMBERVALUE(H_unit[Heat]),0))} -> 195 | Z10: {=SUMPRODUCT((H_unit[Region]=P_heat[[#This Row],[Region]])*(H_unit[Type]=P_heat[[#Headers],[Gas HOB]])*IFERROR(_xlfn.NUMBERVALUE(H_unit[Heat]),0))} -> 105 | AA10: {=SUMPRODUCT((H_unit[Region]=P_heat[[#This Row],[Region]])*(H_unit[Type]=P_heat[[#Headers],[Ground source heat pump]])*IFERROR(_xlfn.NUMBERVALUE(H_unit[Heat]),0))} -> 5.9 | AB10: {=SUMPRODUCT((H_unit[Region]=P_heat[[#This Row],[Region]])*(H_unit[Type]=P_heat[[#Headers],[Waste HOB]])*IFERROR(_xlfn.NUMBERVALUE(H_unit[Heat]),0))} -> 0 | AC10: {=SUMPRODUCT((H_unit[Region]=P_heat[[#This Row],[Region]])*(H_unit[Type]=P_heat[[#Headers],[Heat storage ]])*IFERROR(_xlfn.NUMBERVALUE(H_unit[Heat]),0))} -> 155 | AD10: {=SUMPRODUCT((H_unit[Region]=P_heat[[#This Row],[Region]])*(H_unit[Type]=P_heat[[#Headers],[Large heat storage]])*IFERROR(_xlfn.NUMBERVALUE(H_unit[Heat]),0))} -> 0 | AE10: =SUM(P_heat[#This Row]) -> 3066.8
A11: Adven Oy, Levi | B11: Savukaasupesuri | C11: {=" "&LOWER(_xlfn.REDUCE(H_unit[[#This Row],[Company]]&" "&H_unit[[#This Row],[Unit]],{",",".","(",")","/"},_xlfn.LAMBDA(_xlpm.txt,_xlpm.delim,SUBSTITUTE(_xlpm.txt,_xlpm.delim," "))))&" "} -> adven oy levi savukaasupesuri | D11: 2013 | E11: .. | H11: - | J11: {=_xlfn.XLOOKUP(TRUE,ISNUMBER(SEARCH(" "&Municipality[Municipality]&" ",H_unit[[#This Row],[Info string]])),Municipality[Municipality],"")} | K11: {=IF(H_unit[[#This Row],[Exact]]<>"","",_xlfn.XLOOKUP(TRUE,ISNUMBER(SEARCH(" "&Municipality[Municipality]&"n ",H_unit[[#This Row],[Info string]])),Municipality[Municipality],""))} | L11: Kittilä | M11: Levi locality/ski resort in Kittilä | N11: =_xlfn.TEXTJOIN("",TRUE,H_unit[[#This Row],[Exact]],H_unit[[#This Row],[Exact+n]],H_unit[[#This Row],[Copilot]]) -> Kittilä | O11: =_xlfn.XLOOKUP(H_unit[[#This Row],[Municipality]],Municipality[Municipality],Municipality[Model],"") -> North | Q11: South West | R11: {=SUMPRODUCT((H_unit[Region]=P_heat[[#This Row],[Region]])*(H_unit[Type]=P_heat[[#Headers],[Excluded]])*IFERROR(_xlfn.NUMBERVALUE(H_unit[Heat]),0))} -> 96.5 | S11: {=SUMPRODUCT((H_unit[Region]=P_heat[[#This Row],[Region]])*(H_unit[Type]=P_heat[[#Headers],[Included in industry]])*IFERROR(_xlfn.NUMBERVALUE(H_unit[Heat]),0))} -> 0 | T11: {=SUMPRODUCT((H_unit[Region]=P_heat[[#This Row],[Region]])*(H_unit[Type]=P_heat[[#Headers],[Bio CHP]])*IFERROR(_xlfn.NUMBERVALUE(H_unit[Heat]),0))} -> 179 | U11: {=SUMPRODUCT((H_unit[Region]=P_heat[[#This Row],[Region]])*(H_unit[Type]=P_heat[[#Headers],[Gas CCGT CHP]])*IFERROR(_xlfn.NUMBERVALUE(H_unit[Heat]),0))} -> 65 | V11: {=SUMPRODUCT((H_unit[Region]=P_heat[[#This Row],[Region]])*(H_unit[Type]=P_heat[[#Headers],[Waste CHP]])*IFERROR(_xlfn.NUMBERVALUE(H_unit[Heat]),0))} -> 143 | W11: {=SUMPRODUCT((H_unit[Region]=P_heat[[#This Row],[Region]])*(H_unit[Type]=P_heat[[#Headers],[Oil HOB]])*IFERROR(_xlfn.NUMBERVALUE(H_unit[Heat]),0))} -> 475.8 | X11: {=SUMPRODUCT((H_unit[Region]=P_heat[[#This Row],[Region]])*(H_unit[Type]=P_heat[[#Headers],[Bio HOB]])*IFERROR(_xlfn.NUMBERVALUE(H_unit[Heat]),0))} -> 278.4 | Y11: {=SUMPRODUCT((H_unit[Region]=P_heat[[#This Row],[Region]])*(H_unit[Type]=P_heat[[#Headers],[Electric boiler]])*IFERROR(_xlfn.NUMBERVALUE(H_unit[Heat]),0))} -> 42.6 | Z11: {=SUMPRODUCT((H_unit[Region]=P_heat[[#This Row],[Region]])*(H_unit[Type]=P_heat[[#Headers],[Gas HOB]])*IFERROR(_xlfn.NUMBERVALUE(H_unit[Heat]),0))} -> 169.3 | AA11: {=SUMPRODUCT((H_unit[Region]=P_heat[[#This Row],[Region]])*(H_unit[Type]=P_heat[[#Headers],[Ground source heat pump]])*IFERROR(_xlfn.NUMBERVALUE(H_unit[Heat]),0))} -> 18.6 | AB11: {=SUMPRODUCT((H_unit[Region]=P_heat[[#This Row],[Region]])*(H_unit[Type]=P_heat[[#Headers],[Waste HOB]])*IFERROR(_xlfn.NUMBERVALUE(H_unit[Heat]),0))} -> 0 | AC11: {=SUMPRODUCT((H_unit[Region]=P_heat[[#This Row],[Region]])*(H_unit[Type]=P_heat[[#Headers],[Heat storage ]])*IFERROR(_xlfn.NUMBERVALUE(H_unit[Heat]),0))} -> 58 | AD11: {=SUMPRODUCT((H_unit[Region]=P_heat[[#This Row],[Region]])*(H_unit[Type]=P_heat[[#Headers],[Large heat storage]])*IFERROR(_xlfn.NUMBERVALUE(H_unit[Heat]),0))} -> 0 | AE11: =SUM(P_heat[#This Row]) -> 1526.2
A12: Vantaan Energia Keski-Uusimaa Oy, Järvenpää | B12: Järvenpään voimalaitos | C12: {=" "&LOWER(_xlfn.REDUCE(H_unit[[#This Row],[Company]]&" "&H_unit[[#This Row],[Unit]],{",",".","(",")","/"},_xlfn.LAMBDA(_xlpm.txt,_xlpm.delim,SUBSTITUTE(_xlpm.txt,_xlpm.delim," "))))&" "} -> vantaan energia keski-uusimaa oy järvenpää järvenpään voimalaitos | D12: 2013 | E12: .. | F12: 22 | H12: popu | I12: Bio CHP | J12: {=_xlfn.XLOOKUP(TRUE,ISNUMBER(SEARCH(" "&Municipality[Municipality]&" ",H_unit[[#This Row],[Info string]])),Municipality[Municipality],"")} -> Järvenpää | K12: {=IF(H_unit[[#This Row],[Exact]]<>"","",_xlfn.XLOOKUP(TRUE,ISNUMBER(SEARCH(" "&Municipality[Municipality]&"n ",H_unit[[#This Row],[Info string]])),Municipality[Municipality],""))} | N12: =_xlfn.TEXTJOIN("",TRUE,H_unit[[#This Row],[Exact]],H_unit[[#This Row],[Exact+n]],H_unit[[#This Row],[Copilot]]) -> Järvenpää | O12: =_xlfn.XLOOKUP(H_unit[[#This Row],[Municipality]],Municipality[Municipality],Municipality[Model],"") -> Uusimaa | Q12: South East | R12: {=SUMPRODUCT((H_unit[Region]=P_heat[[#This Row],[Region]])*(H_unit[Type]=P_heat[[#Headers],[Excluded]])*IFERROR(_xlfn.NUMBERVALUE(H_unit[Heat]),0))} -> 17 | S12: {=SUMPRODUCT((H_unit[Region]=P_heat[[#This Row],[Region]])*(H_unit[Type]=P_heat[[#Headers],[Included in industry]])*IFERROR(_xlfn.NUMBERVALUE(H_unit[Heat]),0))} -> 5 | T12: {=SUMPRODUCT((H_unit[Region]=P_heat[[#This Row],[Region]])*(H_unit[Type]=P_heat[[#Headers],[Bio CHP]])*IFERROR(_xlfn.NUMBERVALUE(H_unit[Heat]),0))} -> 375 | U12: {=SUMPRODUCT((H_unit[Region]=P_heat[[#This Row],[Region]])*(H_unit[Type]=P_heat[[#Headers],[Gas CCGT CHP]])*IFERROR(_xlfn.NUMBERVALUE(H_unit[Heat]),0))} -> 254 | V12: {=SUMPRODUCT((H_unit[Region]=P_heat[[#This Row],[Region]])*(H_unit[Type]=P_heat[[#Headers],[Waste CHP]])*IFERROR(_xlfn.NUMBERVALUE(H_unit[Heat]),0))} -> 112 | W12: {=SUMPRODUCT((H_unit[Region]=P_heat[[#This Row],[Region]])*(H_unit[Type]=P_heat[[#Headers],[Oil HOB]])*IFERROR(_xlfn.NUMBERVALUE(H_unit[Heat]),0))} -> 215.7 | X12: {=SUMPRODUCT((H_unit[Region]=P_heat[[#This Row],[Region]])*(H_unit[Type]=P_heat[[#Headers],[Bio HOB]])*IFERROR(_xlfn.NUMBERVALUE(H_unit[Heat]),0))} -> 164.2 | Y12: {=SUMPRODUCT((H_unit[Region]=P_heat[[#This Row],[Region]])*(H_unit[Type]=P_heat[[#Headers],[Electric boiler]])*IFERROR(_xlfn.NUMBERVALUE(H_unit[Heat]),0))} -> 160 | Z12: {=SUMPRODUCT((H_unit[Region]=P_heat[[#This Row],[Region]])*(H_unit[Type]=P_heat[[#Headers],[Gas HOB]])*IFERROR(_xlfn.NUMBERVALUE(H_unit[Heat]),0))} -> 914.8 | AA12: {=SUMPRODUCT((H_unit[Region]=P_heat[[#This Row],[Region]])*(H_unit[Type]=P_heat[[#Headers],[Ground source heat pump]])*IFERROR(_xlfn.NUMBERVALUE(H_unit[Heat]),0))} -> 64.8 | AB12: {=SUMPRODUCT((H_unit[Region]=P_heat[[#This Row],[Region]])*(H_unit[Type]=P_heat[[#Headers],[Waste HOB]])*IFERROR(_xlfn.NUMBERVALUE(H_unit[Heat]),0))} -> 0 | AC12: {=SUMPRODUCT((H_unit[Region]=P_heat[[#This Row],[Region]])*(H_unit[Type]=P_heat[[#Headers],[Heat storage ]])*IFERROR(_xlfn.NUMBERVALUE(H_unit[Heat]),0))} -> 190 | AD12: {=SUMPRODUCT((H_unit[Region]=P_heat[[#This Row],[Region]])*(H_unit[Type]=P_heat[[#Headers],[Large heat storage]])*IFERROR(_xlfn.NUMBERVALUE(H_unit[Heat]),0))} -> 0 | AE12: =SUM(P_heat[#This Row]) -> 2472.5
A13: Suomen Teollisuuden Energiapalvelut Oy, Harjavalta | B13: Boliden Harjavalta Oyn lämmönsiirtimet | C13: {=" "&LOWER(_xlfn.REDUCE(H_unit[[#This Row],[Company]]&" "&H_unit[[#This Row],[Unit]],{",",".","(",")","/"},_xlfn.LAMBDA(_xlpm.txt,_xlpm.delim,SUBSTITUTE(_xlpm.txt,_xlpm.delim," "))))&" "} -> suomen teollisuuden energiapalvelut oy harjavalta boliden harjavalta oyn lämmönsiirtimet | D13: 2018 | E13: .. | H13: muu | I13: Excluded | J13: {=_xlfn.XLOOKUP(TRUE,ISNUMBER(SEARCH(" "&Municipality[Municipality]&" ",H_unit[[#This Row],[Info string]])),Municipality[Municipality],"")} -> Harjavalta | K13: {=IF(H_unit[[#This Row],[Exact]]<>"","",_xlfn.XLOOKUP(TRUE,ISNUMBER(SEARCH(" "&Municipality[Municipality]&"n ",H_unit[[#This Row],[Info string]])),Municipality[Municipality],""))} | N13: =_xlfn.TEXTJOIN("",TRUE,H_unit[[#This Row],[Exact]],H_unit[[#This Row],[Exact+n]],H_unit[[#This Row],[Copilot]]) -> Harjavalta | O13: =_xlfn.XLOOKUP(H_unit[[#This Row],[Municipality]],Municipality[Municipality],Municipality[Model],"") -> West | Q13: Uusimaa | R13: {=SUMPRODUCT((H_unit[Region]=P_heat[[#This Row],[Region]])*(H_unit[Type]=P_heat[[#Headers],[Excluded]])*IFERROR(_xlfn.NUMBERVALUE(H_unit[Heat]),0))} -> 3.5 | S13: {=SUMPRODUCT((H_unit[Region]=P_heat[[#This Row],[Region]])*(H_unit[Type]=P_heat[[#Headers],[Included in industry]])*IFERROR(_xlfn.NUMBERVALUE(H_unit[Heat]),0))} -> 0 | T13: {=SUMPRODUCT((H_unit[Region]=P_heat[[#This Row],[Region]])*(H_unit[Type]=P_heat[[#Headers],[Bio CHP]])*IFERROR(_xlfn.NUMBERVALUE(H_unit[Heat]),0))} -> 157.2 | U13: {=SUMPRODUCT((H_unit[Region]=P_heat[[#This Row],[Region]])*(H_unit[Type]=P_heat[[#Headers],[Gas CCGT CHP]])*IFERROR(_xlfn.NUMBERVALUE(H_unit[Heat]),0))} -> 23 | V13: {=SUMPRODUCT((H_unit[Region]=P_heat[[#This Row],[Region]])*(H_unit[Type]=P_heat[[#Headers],[Waste CHP]])*IFERROR(_xlfn.NUMBERVALUE(H_unit[Heat]),0))} -> 0 | W13: {=SUMPRODUCT((H_unit[Region]=P_heat[[#This Row],[Region]])*(H_unit[Type]=P_heat[[#Headers],[Oil HOB]])*IFERROR(_xlfn.NUMBERVALUE(H_unit[Heat]),0))} -> 284.3 | X13: {=SUMPRODUCT((H_unit[Region]=P_heat[[#This Row],[Region]])*(H_unit[Type]=P_heat[[#Headers],[Bio HOB]])*IFERROR(_xlfn.NUMBERVALUE(H_unit[Heat]),0))} -> 249.4 | Y13: {=SUMPRODUCT((H_unit[Region]=P_heat[[#This Row],[Region]])*(H_unit[Type]=P_heat[[#Headers],[Electric boiler]])*IFERROR(_xlfn.NUMBERVALUE(H_unit[Heat]),0))} -> 40 | Z13: {=SUMPRODUCT((H_unit[Region]=P_heat[[#This Row],[Region]])*(H_unit[Type]=P_heat[[#Headers],[Gas HOB]])*IFERROR(_xlfn.NUMBERVALUE(H_unit[Heat]),0))} -> 510 | AA13: {=SUMPRODUCT((H_unit[Region]=P_heat[[#This Row],[Region]])*(H_unit[Type]=P_heat[[#Headers],[Ground source heat pump]])*IFERROR(_xlfn.NUMBERVALUE(H_unit[Heat]),0))} -> 14.1 | AB13: {=SUMPRODUCT((H_unit[Region]=P_heat[[#This Row],[Region]])*(H_unit[Type]=P_heat[[#Headers],[Waste HOB]])*IFERROR(_xlfn.NUMBERVALUE(H_unit[Heat]),0))} -> 0 | AC13: {=SUMPRODUCT((H_unit[Region]=P_heat[[#This Row],[Region]])*(H_unit[Type]=P_heat[[#Headers],[Heat storage ]])*IFERROR(_xlfn.NUMBERVALUE(H_unit[Heat]),0))} -> 50 | AD13: {=SUMPRODUCT((H_unit[Region]=P_heat[[#This Row],[Region]])*(H_unit[Type]=P_heat[[#Headers],[Large heat storage]])*IFERROR(_xlfn.NUMBERVALUE(H_unit[Heat]),0))} -> 0 | AE13: =SUM(P_heat[#This Row]) -> 1331.5
A14: Adven Oy, Nummela | B14: Nummela | C14: {=" "&LOWER(_xlfn.REDUCE(H_unit[[#This Row],[Company]]&" "&H_unit[[#This Row],[Unit]],{",",".","(",")","/"},_xlfn.LAMBDA(_xlpm.txt,_xlpm.delim,SUBSTITUTE(_xlpm.txt,_xlpm.delim," "))))&" "} -> adven oy nummela nummela | D14: .. | E14: .. | H14: - | J14: {=_xlfn.XLOOKUP(TRUE,ISNUMBER(SEARCH(" "&Municipality[Municipality]&" ",H_unit[[#This Row],[Info string]])),Municipality[Municipality],"")} | K14: {=IF(H_unit[[#This Row],[Exact]]<>"","",_xlfn.XLOOKUP(TRUE,ISNUMBER(SEARCH(" "&Municipality[Municipality]&"n ",H_unit[[#This Row],[Info string]])),Municipality[Municipality],""))} | L14: Vihti | M14: Nummela locality in Vihti | N14: =_xlfn.TEXTJOIN("",TRUE,H_unit[[#This Row],[Exact]],H_unit[[#This Row],[Exact+n]],H_unit[[#This Row],[Copilot]]) -> Vihti | O14: =_xlfn.XLOOKUP(H_unit[[#This Row],[Municipality]],Municipality[Municipality],Municipality[Model],"") -> Uusimaa | R14: =SUM(P_heat[Excluded]) -> 442.3 | S14: =SUM(P_heat[Included in industry]) -> 769.9 | T14: =SUM(P_heat[Bio CHP]) -> 3099.3 | U14: =SUM(P_heat[Gas CCGT CHP]) -> 356.6 | V14: =SUM(P_heat[Waste CHP]) -> 307 | W14: =SUM(P_heat[Oil HOB]) -> 3493.5 | X14: =SUM(P_heat[Bio HOB]) -> 2636.7 | Y14: =SUM(P_heat[Electric boiler]) -> 1042.9 | Z14: =SUM(P_heat[Gas HOB]) -> 1850 | AA14: =SUM(P_heat[Ground source heat pump]) -> 146.8 | AB14: =SUM(P_heat[Waste HOB]) -> 10 | AC14: =SUM(P_heat[[Heat storage ]]) -> 625.5 | AD14: =SUM(P_heat[Large heat storage]) -> 170 | AE14: =SUM(R14:AD14) -> 14950.5
A15: Adven Oy, Siilinjärvi | B15: Siilinjärvi | C15: {=" "&LOWER(_xlfn.REDUCE(H_unit[[#This Row],[Company]]&" "&H_unit[[#This Row],[Unit]],{",",".","(",")","/"},_xlfn.LAMBDA(_xlpm.txt,_xlpm.delim,SUBSTITUTE(_xlpm.txt,_xlpm.delim," "))))&" "} -> adven oy siilinjärvi siilinjärvi | D15: .. | E15: .. | H15: muu | J15: {=_xlfn.XLOOKUP(TRUE,ISNUMBER(SEARCH(" "&Municipality[Municipality]&" ",H_unit[[#This Row],[Info string]])),Municipality[Municipality],"")} -> Siilinjärvi | K15: {=IF(H_unit[[#This Row],[Exact]]<>"","",_xlfn.XLOOKUP(TRUE,ISNUMBER(SEARCH(" "&Municipality[Municipality]&"n ",H_unit[[#This Row],[Info string]])),Municipality[Municipality],""))} | N15: =_xlfn.TEXTJOIN("",TRUE,H_unit[[#This Row],[Exact]],H_unit[[#This Row],[Exact+n]],H_unit[[#This Row],[Copilot]]) -> Siilinjärvi | O15: =_xlfn.XLOOKUP(H_unit[[#This Row],[Municipality]],Municipality[Municipality],Municipality[Model],"") -> East
A16: Nevel Oy, Kemi | B16: .. | C16: {=" "&LOWER(_xlfn.REDUCE(H_unit[[#This Row],[Company]]&" "&H_unit[[#This Row],[Unit]],{",",".","(",")","/"},_xlfn.LAMBDA(_xlpm.txt,_xlpm.delim,SUBSTITUTE(_xlpm.txt,_xlpm.delim," "))))&" "} -> nevel oy kemi | D16: .. | E16: .. | H16: .. | I16: Excluded | J16: {=_xlfn.XLOOKUP(TRUE,ISNUMBER(SEARCH(" "&Municipality[Municipality]&" ",H_unit[[#This Row],[Info string]])),Municipality[Municipality],"")} -> Kemi | K16: {=IF(H_unit[[#This Row],[Exact]]<>"","",_xlfn.XLOOKUP(TRUE,ISNUMBER(SEARCH(" "&Municipality[Municipality]&"n ",H_unit[[#This Row],[Info string]])),Municipality[Municipality],""))} | N16: =_xlfn.TEXTJOIN("",TRUE,H_unit[[#This Row],[Exact]],H_unit[[#This Row],[Exact+n]],H_unit[[#This Row],[Copilot]]) -> Kemi | O16: =_xlfn.XLOOKUP(H_unit[[#This Row],[Municipality]],Municipality[Municipality],Municipality[Model],"") -> North | Q16: Electric capacity | Y16: Heat storage capacity [MWh]
A17: Pori Energia Oy, Pori | B17: Aurubis lämmönsiirtimet | C17: {=" "&LOWER(_xlfn.REDUCE(H_unit[[#This Row],[Company]]&" "&H_unit[[#This Row],[Unit]],{",",".","(",")","/"},_xlfn.LAMBDA(_xlpm.txt,_xlpm.delim,SUBSTITUTE(_xlpm.txt,_xlpm.delim," "))))&" "} -> pori energia oy pori aurubis lämmönsiirtimet | D17: .. | E17: .. | H17: muu | I17: Excluded | J17: {=_xlfn.XLOOKUP(TRUE,ISNUMBER(SEARCH(" "&Municipality[Municipality]&" ",H_unit[[#This Row],[Info string]])),Municipality[Municipality],"")} -> Pori | K17: {=IF(H_unit[[#This Row],[Exact]]<>"","",_xlfn.XLOOKUP(TRUE,ISNUMBER(SEARCH(" "&Municipality[Municipality]&"n ",H_unit[[#This Row],[Info string]])),Municipality[Municipality],""))} | N17: =_xlfn.TEXTJOIN("",TRUE,H_unit[[#This Row],[Exact]],H_unit[[#This Row],[Exact+n]],H_unit[[#This Row],[Copilot]]) -> Pori | O17: =_xlfn.XLOOKUP(H_unit[[#This Row],[Municipality]],Municipality[Municipality],Municipality[Model],"") -> West | Q17: Region | R17: Excluded | S17: Bio CHP | T17: Gas CCGT CHP | U17: Waste CHP | V17: Included in industry | Y17: Region | Z17: Heat storage | AA17: Large heat storage
A18: Biolinja Oy Uusikaupunki | B18: Biolinja Oy Uusikaupunki | C18: {=" "&LOWER(_xlfn.REDUCE(H_unit[[#This Row],[Company]]&" "&H_unit[[#This Row],[Unit]],{",",".","(",")","/"},_xlfn.LAMBDA(_xlpm.txt,_xlpm.delim,SUBSTITUTE(_xlpm.txt,_xlpm.delim," "))))&" "} -> biolinja oy uusikaupunki biolinja oy uusikaupunki | D18: .. | E18: .. | H18: biok | I18: Excluded | J18: {=_xlfn.XLOOKUP(TRUE,ISNUMBER(SEARCH(" "&Municipality[Municipality]&" ",H_unit[[#This Row],[Info string]])),Municipality[Municipality],"")} -> Uusikaupunki | K18: {=IF(H_unit[[#This Row],[Exact]]<>"","",_xlfn.XLOOKUP(TRUE,ISNUMBER(SEARCH(" "&Municipality[Municipality]&"n ",H_unit[[#This Row],[Info string]])),Municipality[Municipality],""))} | N18: =_xlfn.TEXTJOIN("",TRUE,H_unit[[#This Row],[Exact]],H_unit[[#This Row],[Exact+n]],H_unit[[#This Row],[Copilot]]) -> Uusikaupunki | O18: =_xlfn.XLOOKUP(H_unit[[#This Row],[Municipality]],Municipality[Municipality],Municipality[Model],"") -> South West | Q18: North | R18: {=SUMPRODUCT((H_unit[Region]=P_heat2[[#This Row],[Region]])*(H_unit[Type]=P_heat2[[#Headers],[Excluded]])*IFERROR(_xlfn.NUMBERVALUE(H_unit[Power]),0))} -> 175 | S18: {=SUMPRODUCT((H_unit[Region]=P_heat2[[#This Row],[Region]])*(H_unit[Type]=P_heat2[[#Headers],[Bio CHP]])*IFERROR(_xlfn.NUMBERVALUE(H_unit[Power]),0))} -> 53.3 | T18: {=SUMPRODUCT((H_unit[Region]=P_heat2[[#This Row],[Region]])*(H_unit[Type]=P_heat2[[#Headers],[Gas CCGT CHP]])*IFERROR(_xlfn.NUMBERVALUE(H_unit[Power]),0))} -> 0 | U18: {=SUMPRODUCT((H_unit[Region]=P_heat2[[#This Row],[Region]])*(H_unit[Type]=P_heat2[[#Headers],[Waste CHP]])*IFERROR(_xlfn.NUMBERVALUE(H_unit[Power]),0))} -> 0 | V18: {=SUMPRODUCT((H_unit[Region]=P_heat2[[#This Row],[Region]])*(H_unit[Type]=P_heat2[[#Headers],[Included in industry]])*IFERROR(_xlfn.NUMBERVALUE(H_unit[Power]),0))} -> 357 | W18: =SUM(R18:V18) -> 585.3 | Y18: North | Z18: {=SUMPRODUCT((H_unit[Region]=P_heat3[[#This Row],[Region]])*(H_unit[Type]=P_heat3[[#Headers],[Heat storage ]])*IFERROR(_xlfn.NUMBERVALUE(H_unit[Storage]),0))} -> 610 | AA18: {=SUMPRODUCT((H_unit[Region]=P_heat3[[#This Row],[Region]])*(H_unit[Type]=P_heat3[[#Headers],[Large heat storage]])*IFERROR(_xlfn.NUMBERVALUE(H_unit[Storage]),0))} -> 0 | AB18: =Z18+AA18 -> 610
A19: Nordic Soya Oy, Uusikaupunki | B19: Nordic Soya Oy | C19: {=" "&LOWER(_xlfn.REDUCE(H_unit[[#This Row],[Company]]&" "&H_unit[[#This Row],[Unit]],{",",".","(",")","/"},_xlfn.LAMBDA(_xlpm.txt,_xlpm.delim,SUBSTITUTE(_xlpm.txt,_xlpm.delim," "))))&" "} -> nordic soya oy uusikaupunki nordic soya oy | D19: .. | E19: .. | H19: sek | I19: Excluded | J19: {=_xlfn.XLOOKUP(TRUE,ISNUMBER(SEARCH(" "&Municipality[Municipality]&" ",H_unit[[#This Row],[Info string]])),Municipality[Municipality],"")} -> Uusikaupunki | K19: {=IF(H_unit[[#This Row],[Exact]]<>"","",_xlfn.XLOOKUP(TRUE,ISNUMBER(SEARCH(" "&Municipality[Municipality]&"n ",H_unit[[#This Row],[Info string]])),Municipality[Municipality],""))} | N19: =_xlfn.TEXTJOIN("",TRUE,H_unit[[#This Row],[Exact]],H_unit[[#This Row],[Exact+n]],H_unit[[#This Row],[Copilot]]) -> Uusikaupunki | O19: =_xlfn.XLOOKUP(H_unit[[#This Row],[Municipality]],Municipality[Municipality],Municipality[Model],"") -> South West | Q19: West | R19: {=SUMPRODUCT((H_unit[Region]=P_heat2[[#This Row],[Region]])*(H_unit[Type]=P_heat2[[#Headers],[Excluded]])*IFERROR(_xlfn.NUMBERVALUE(H_unit[Power]),0))} -> 0.1 | S19: {=SUMPRODUCT((H_unit[Region]=P_heat2[[#This Row],[Region]])*(H_unit[Type]=P_heat2[[#Headers],[Bio CHP]])*IFERROR(_xlfn.NUMBERVALUE(H_unit[Power]),0))} -> 754.2 | T19: {=SUMPRODUCT((H_unit[Region]=P_heat2[[#This Row],[Region]])*(H_unit[Type]=P_heat2[[#Headers],[Gas CCGT CHP]])*IFERROR(_xlfn.NUMBERVALUE(H_unit[Power]),0))} -> 0 | U19: {=SUMPRODUCT((H_unit[Region]=P_heat2[[#This Row],[Region]])*(H_unit[Type]=P_heat2[[#Headers],[Waste CHP]])*IFERROR(_xlfn.NUMBERVALUE(H_unit[Power]),0))} -> 15 | V19: {=SUMPRODUCT((H_unit[Region]=P_heat2[[#This Row],[Region]])*(H_unit[Type]=P_heat2[[#Headers],[Included in industry]])*IFERROR(_xlfn.NUMBERVALUE(H_unit[Power]),0))} -> 0 | W19: =SUM(R19:V19) -> 769.3 | Y19: West | Z19: {=SUMPRODUCT((H_unit[Region]=P_heat3[[#This Row],[Region]])*(H_unit[Type]=P_heat3[[#Headers],[Heat storage ]])*IFERROR(_xlfn.NUMBERVALUE(H_unit[Storage]),0))} -> 1080 | AA19: {=SUMPRODUCT((H_unit[Region]=P_heat3[[#This Row],[Region]])*(H_unit[Type]=P_heat3[[#Headers],[Large heat storage]])*IFERROR(_xlfn.NUMBERVALUE(H_unit[Storage]),0))} -> 17000 | AB19: =Z19+AA19 -> 18080
A20: Parkanon Listatehdas | B20: Parkanon Listatehdas LK | C20: {=" "&LOWER(_xlfn.REDUCE(H_unit[[#This Row],[Company]]&" "&H_unit[[#This Row],[Unit]],{",",".","(",")","/"},_xlfn.LAMBDA(_xlpm.txt,_xlpm.delim,SUBSTITUTE(_xlpm.txt,_xlpm.delim," "))))&" "} -> parkanon listatehdas parkanon listatehdas lk | D20: .. | E20: .. | H20: tept | I20: Excluded | J20: {=_xlfn.XLOOKUP(TRUE,ISNUMBER(SEARCH(" "&Municipality[Municipality]&" ",H_unit[[#This Row],[Info string]])),Municipality[Municipality],"")} | K20: {=IF(H_unit[[#This Row],[Exact]]<>"","",_xlfn.XLOOKUP(TRUE,ISNUMBER(SEARCH(" "&Municipality[Municipality]&"n ",H_unit[[#This Row],[Info string]])),Municipality[Municipality],""))} -> Parkano | N20: =_xlfn.TEXTJOIN("",TRUE,H_unit[[#This Row],[Exact]],H_unit[[#This Row],[Exact+n]],H_unit[[#This Row],[Copilot]]) -> Parkano | O20: =_xlfn.XLOOKUP(H_unit[[#This Row],[Municipality]],Municipality[Municipality],Municipality[Model],"") -> Center | Q20: Center | R20: {=SUMPRODUCT((H_unit[Region]=P_heat2[[#This Row],[Region]])*(H_unit[Type]=P_heat2[[#Headers],[Excluded]])*IFERROR(_xlfn.NUMBERVALUE(H_unit[Power]),0))} -> 6 | S20: {=SUMPRODUCT((H_unit[Region]=P_heat2[[#This Row],[Region]])*(H_unit[Type]=P_heat2[[#Headers],[Bio CHP]])*IFERROR(_xlfn.NUMBERVALUE(H_unit[Power]),0))} -> 65.9 | T20: {=SUMPRODUCT((H_unit[Region]=P_heat2[[#This Row],[Region]])*(H_unit[Type]=P_heat2[[#Headers],[Gas CCGT CHP]])*IFERROR(_xlfn.NUMBERVALUE(H_unit[Power]),0))} -> 12 | U20: {=SUMPRODUCT((H_unit[Region]=P_heat2[[#This Row],[Region]])*(H_unit[Type]=P_heat2[[#Headers],[Waste CHP]])*IFERROR(_xlfn.NUMBERVALUE(H_unit[Power]),0))} -> 0 | V20: {=SUMPRODUCT((H_unit[Region]=P_heat2[[#This Row],[Region]])*(H_unit[Type]=P_heat2[[#Headers],[Included in industry]])*IFERROR(_xlfn.NUMBERVALUE(H_unit[Power]),0))} -> 321.7 | W20: =SUM(R20:V20) -> 405.6 | Y20: Center | Z20: {=SUMPRODUCT((H_unit[Region]=P_heat3[[#This Row],[Region]])*(H_unit[Type]=P_heat3[[#Headers],[Heat storage ]])*IFERROR(_xlfn.NUMBERVALUE(H_unit[Storage]),0))} -> 35 | AA20: {=SUMPRODUCT((H_unit[Region]=P_heat3[[#This Row],[Region]])*(H_unit[Type]=P_heat3[[#Headers],[Large heat storage]])*IFERROR(_xlfn.NUMBERVALUE(H_unit[Storage]),0))} -> 0 | AB20: =Z20+AA20 -> 35
A21: UPM-Kymmene Oyj, Lappeenranta | B21: UPM-Kymmene, Kaukas | C21: {=" "&LOWER(_xlfn.REDUCE(H_unit[[#This Row],[Company]]&" "&H_unit[[#This Row],[Unit]],{",",".","(",")","/"},_xlfn.LAMBDA(_xlpm.txt,_xlpm.delim,SUBSTITUTE(_xlpm.txt,_xlpm.delim," "))))&" "} -> upm-kymmene oyj lappeenranta upm-kymmene kaukas | D21: .. | E21: .. | H21: jätel | I21: Excluded | J21: {=_xlfn.XLOOKUP(TRUE,ISNUMBER(SEARCH(" "&Municipality[Municipality]&" ",H_unit[[#This Row],[Info string]])),Municipality[Municipality],"")} -> Lappeenranta | K21: {=IF(H_unit[[#This Row],[Exact]]<>"","",_xlfn.XLOOKUP(TRUE,ISNUMBER(SEARCH(" "&Municipality[Municipality]&"n ",H_unit[[#This Row],[Info string]])),Municipality[Municipality],""))} | N21: =_xlfn.TEXTJOIN("",TRUE,H_unit[[#This Row],[Exact]],H_unit[[#This Row],[Exact+n]],H_unit[[#This Row],[Copilot]]) -> Lappeenranta | O21: =_xlfn.XLOOKUP(H_unit[[#This Row],[Municipality]],Municipality[Municipality],Municipality[Model],"") -> South East | Q21: East | R21: {=SUMPRODUCT((H_unit[Region]=P_heat2[[#This Row],[Region]])*(H_unit[Type]=P_heat2[[#Headers],[Excluded]])*IFERROR(_xlfn.NUMBERVALUE(H_unit[Power]),0))} -> 2 | S21: {=SUMPRODUCT((H_unit[Region]=P_heat2[[#This Row],[Region]])*(H_unit[Type]=P_heat2[[#Headers],[Bio CHP]])*IFERROR(_xlfn.NUMBERVALUE(H_unit[Power]),0))} -> 298.9 | T21: {=SUMPRODUCT((H_unit[Region]=P_heat2[[#This Row],[Region]])*(H_unit[Type]=P_heat2[[#Headers],[Gas CCGT CHP]])*IFERROR(_xlfn.NUMBERVALUE(H_unit[Power]),0))} -> 1.6 | U21: {=SUMPRODUCT((H_unit[Region]=P_heat2[[#This Row],[Region]])*(H_unit[Type]=P_heat2[[#Headers],[Waste CHP]])*IFERROR(_xlfn.NUMBERVALUE(H_unit[Power]),0))} -> 0 | V21: {=SUMPRODUCT((H_unit[Region]=P_heat2[[#This Row],[Region]])*(H_unit[Type]=P_heat2[[#Headers],[Included in industry]])*IFERROR(_xlfn.NUMBERVALUE(H_unit[Power]),0))} -> 13.5 | W21: =SUM(R21:V21) -> 316 | Y21: East | Z21: {=SUMPRODUCT((H_unit[Region]=P_heat3[[#This Row],[Region]])*(H_unit[Type]=P_heat3[[#Headers],[Heat storage ]])*IFERROR(_xlfn.NUMBERVALUE(H_unit[Storage]),0))} -> 1550 | AA21: {=SUMPRODUCT((H_unit[Region]=P_heat3[[#This Row],[Region]])*(H_unit[Type]=P_heat3[[#Headers],[Large heat storage]])*IFERROR(_xlfn.NUMBERVALUE(H_unit[Storage]),0))} -> 0 | AB21: =Z21+AA21 -> 1550
